Workbook
Name Beg_Bal_2: #REF!
Name End_Bal_2: #REF!
Name Extra_Pay_2: #REF!
Name Int_2: #REF!
Name Interest_Rate_2: #REF!
Name Loan_Amount_2: #REF!
Name Loan_Start_2: #REF!
Name Loan_Years_2: #REF!
Name Num_Pmt_Per_Year_2: #REF!
Name Pay_Num_2: #REF!
Name Princ_2: #REF!
Name Sched_Pay_2: #REF!
Name Scheduled_Extra_Payments_2: #REF!
Name Scheduled_Monthly_Payment_2: #REF!
Name Total_Pay_2: #REF!

Sheet Sheet1
A1: Here is the percentage of total household investables ($1,118,616) for each individual asset/fund, based on the target weights and current account balances you provided.
A2: Total Household Investables: $1,118,616 (Crypto + M1 + TSP + Cleveland Clinic 403(b))
A3: Crypto Assets (Total Crypto: $16,700 → 1.49% of household)
A4: BTC: $6,680 → 0.60%
A5: ETH: $3,340 → 0.30%
A6: SOL: $1,670 → 0.15%
A7: BNB: $1,002 → 0.09%
A8: LINK: $1,002 → 0.09%
A9: TAO: $835 → 0.07%
A10: HYPE: $835 → 0.07%
A11: XRP: $501 → 0.04%
A12: TRX: $501 → 0.04%
... A34: Crypto (all 10 assets combined): $16,700 → ~1.5%

Sheet Share Count
A1: Account | B1: Fund / Asset | C1: Shares Owned
A2: TSP Civilian | B2: C Fund | C2: 1996.7504
A3: TSP Civilian | B3: S Fund | C3: 961.81153
A4: TSP Civilian | B4: I Fund | C4: 1367.9801
A5: TSP Uniformed | B5: C Fund | C5: 464.38822
A6: TSP Uniformed | B6: S Fund | C6: 738.12773
A7: Fidelity 403b | B7: VIIIX | C7: 208.278
A8: Fidelity 403b | B8: VTPSX | C8: 1246.571
A9: Fidelity 403b | B9: VEMPX | C9: 141.737
A10: Fidelity 401a | B10: VTPSX | C10: 701.836
A11: M1 Finance | B11: VTI | C11: 51.69695
A12: M1 Finance | B12: QQQM | C12: 33.09859
A13: M1 Finance | B13: AVUV | C13: 238.65392
... A27: Regan Investment | B27: AVES | C27: 20.74981

Sheet Net Worth
A1: Liquid Cash | E1: Total Assets | F1: =SUM($B$7,$B$19,$B$26,$B$31,$B$40) -> 1785117.2 | K1: Proposed | L1: Current | N1: Crypto Deposit | O1: 28500 | Q1: 0.15
A2: Cash On Hand | B2: ='Checking Transaction Log'!G2 -> 180 | C2: =TODAY() -> 46324 | E2: Total Liabilities | F2: =F14 -> 169226.55 | J2: Stocks | K2: 0.75 | L2: =K5/(K5+K6) -> 0.8016265 | N2: Crypto Profit | O2: =B12-O1 -> -4875 | Q2: 1 yr | R2: =E20*(1+$Q$1) -> 1858274.3
A3: PayPal | B3: 0 | C3: =TODAY() -> 46324 | E3: Net Worth | F3: =F1-F2 -> 1615890.7 | J3: Crypto | K3: 0.25 | L3: =K6/(K5+K6) -> 0.1983735 | N3: M1 Deposit | O3: 67870.08 | Q3: 2 yr | R3: =R2*(1+$Q$1) -> 2137015.4
A4: Huntington Checking | B4: 0 | C4: =TODAY() -> 46324 | N4: M1 Profit | O4: =B10-O3 -> 27598.45 | Q4: 3 yr | R4: =R3*(1+$Q$1) -> 2457567.7
A5: PNC Checking | B5: ='Checking Transaction Log'!G1 -> 7573.13 | C5: =TODAY() -> 46324 | E5: Liabilities | J5: M1 Finance | K5: =B10 -> 95468.53 | L5: =K5/F3 -> 0.059081058 | N5: DFS Deposit | Q5: 4 yr | R5: =R4*(1+$Q$1) -> 2826202.9
A6: PNC Savings | B6: ='Savings Transaction Log'!A3 -> 23930.53 | C6: =TODAY() -> 46324 | E6: Rocket Mortgage | F6: 134615.22 | G6: 46310 | J6: Kraken | K6: =B12 -> 23625 | L6: =K6/F3 -> 0.01462042 | N6: DFS Profit | Q6: 5 yr | R6: =R5*(1+$Q$1) -> 3250133.3
A7: Total Liquid Cash | B7: =SUM(B2:B6) -> 31683.66 | C7: =B7/F3 -> 0.019607552 | E7: Lormet - RAV4 | F7: 16806 | G7: 46310 | J7: New Deposit | K7: =IF((B3+B4+B6)>10000,(B3+B4+B6-10000),0) -> 13930.53 | N7: Total Deposit | O7: =O1+O3+O5 -> 96370.08 | Q7: 6 yr | R7: =R6*(1+$Q$1) -> 3737653.3
E8: GM Financial (1 payment left) | F8: 0 | G8: 46310 | J8: Total | K8: =SUM(K5:K7) -> 133024.06 | L8: =K8/F3 -> 0.082322438 | N8: Total Profit | O8: =O2+O4+O6 -> 22723.45 | Q8: 7 yr | R8: =R7*(1+$Q$1) -> 4298301.3
A9: Savings Investments | E9: Wells Fargo - Pool (Aug 11, 2030) | F9: 8840 | G9: 46310 | K9: Deposit | L9: Total | Q9: 8 yr | R9: =R8*(1+$Q$1) -> 4943046.5
A10: Isaac - M1 | B10: 95468.53 | C10: 46312 | E10: Wells Fargo - Deck (Feb 3, 2028) | F10: 8965.33 | G10: 46310 | J10: M1 Finance | K10: =(K8*K2)-K5 -> 4299.515 | L10: =K10+K5 -> 99768.045 | Q10: 9 yr | R10: =R9*(1+$Q$1) -> 5684503.5
A11: Regan-M1 | B11: 13417.66 | C11: 46312 | E11: Lowes - Aug 14, 2026 | F11: 0 | G11: 46310 | J11: BinanceUS | K11: =(K8*K3)-K6 -> 9631.015 | L11: =K11+K6 -> 33256.015 | N11: 12/31 Crypto Bal | O11: 5258.27 | Q11: 10 yr | R11: =R10*(1+$Q$1) -> 6537179
A12: Crypto - Kraken | B12: 23625 | C12: 46312 | E12: Lowes - Dec 15, 2026 | F12: 0 | G12: 46310 | L12: =L11/F3 -> 0.02058061 | N12: 2023 Crypto Deposit | O12: 6000
E13: Lowes - Mar 2027 | F13: 0 | G13: 46310 | N13: 2023 Crypto Withdraw | O13: 0
E14: Total Liabilities | F14: =SUM(F6:F13) -> 169226.55 | N14: Current Crypto Bal | O14: =B18 -> 0
J15: Stocks | K15: =SUM(B10:B11) -> 108886.19 | L15: =K15/F3 -> 0.067384627 | N15: 2023 Crypto Return | O15: =O14-O11-O12 -> -11258.27
E16: Available Cash | F16: =SUM(B7,B10,B18,B13,B12,B17,B15,B16,B14) -> 150777.19 | J16: Crypto | K16: =B12 -> 23625 | L16: =K16/F3 -> 0.01462042
J17: DFS | K17: =SUM(B13) -> 0 | L17: =K17/F3 -> 0
N18: Total Invested | O18: =B19+B26+B31-F6 -> 1532118.3
A19: Total Savings Investments | B19: =SUM(B10:B18) -> 132511.19 | C19: =B19/F3 -> 0.082005047 | E19: Current Net Worth | F19: 2026 Current Gain | G19: 2026 Current Gain | N19: C Fund - US Large Cap | O19: =($B$22+$B$23)*0.5 -> 288756.31 | P19: =O19/$O$18 -> 0.18846867 | Q19: TSP
E20: =F3 -> 1615890.7 | F20: =E20-E22 -> 200888.24 | G20: =(E20-E22)/E22 -> 0.14197024 | J20: Goal | K20: Distance | N20: VIIIX - US Large Cap | O20: =($B$24+$B$25)*0.5 -> 268354.88 | P20: =O20/$O$18 -> 0.17515284 | Q20: Clinic
A21: Retirement Investments | E21: 46023 | F21: 2026 Projected | G21: 2026 Projected Gain | J21: 2000000 | K21: =1-($E$20/J21) -> 0.19205467 | N21: VOO - US Large Cap | O21: =($B$10+$B$11)*0.25 -> 27221.548 | P21: =O21/$O$18 -> 0.017767262 | Q21: M1
A22: TSP Civilian | B22: =-'TSP-401K'!H84 -> 439148.43 | C22: 46312 | E22: 1415002.4 | F22: =((F20/(C2-E21))*365)+E22 -> 1658604.4 | G22: =(F22-E22)/E22 -> 0.17215661 | J22: 3000000 | K22: =1-($E$20/J22) -> 0.46136978 | N22: I Fund - International | O22: =($B$22+$B$23)*0.3 -> 173253.79 | P22: =O22/$O$18 -> 0.1130812 | Q22: TSP
A23: TSP Uniformed Service | B23: =-'TSP-401K'!L84 -> 138364.19 | C23: =C22 -> 46312 | J23: 4000000 | K23: =1-($E$20/J23) -> 0.59602733 | N23: VTPSX - International | O23: =($B$24+$B$25)*0.3 -> 161012.92 | P23: =O23/$O$18 -> 0.1050917 | Q23: Clinic
A24: Cleveland Clinic 403b | B24: =-'TSP-401K'!Q84 -> 411046.01 | C24: =C22 -> 46312 | E24: Asset Type | F24: Net Worth Balance | G24: Net Worth Pct | J24: 5000000 | K24: =1-($E$20/J24) -> 0.67682187 | N24: VEA - International | O24: =($B$10+$B$11)*0.25 -> 27221.548 | P24: =O24/$O$18 -> 0.017767262 | Q24: M1
A25: Cleveland Clinic 401a | B25: =-'TSP-401K'!V84 -> 125663.74 | C25: =C22 -> 46312 | E25: Liquid Cash | F25: =B7 -> 31683.66 | G25: =F25/SUM($F$25:$F$31) -> 0.019393853 | N25: VWO - International | O25: =($B$10+$B$11)*0.25 -> 27221.548 | P25: =O25/$O$18 -> 0.017767262 | Q25: M1
A26: Total Retirement Investments | B26: =SUM(B22:B25) -> 1114222.4 | C26: =B26/F3 -> 0.68954069 | E26: Kids Savings | F26: =(B11) -> 13417.66 | G26: =F26/SUM($F$25:$F$31) -> 0.0082130702 | N26: S Fund - US Small/Mid Cap | O26: =($B$22+$B$23)*0.2 -> 115502.52 | P26: =O26/$O$18 -> 0.075387469 | Q26: TSP
E27: Stock Investments | F27: =B10 -> 95468.53 | G27: =F27/SUM($F$25:$F$31) -> 0.058437145 | N27: VEMPX - US Small/Mid Cap | O27: =($B$24+$B$25)*0.2 -> 107341.95 | P27: =O27/$O$18 -> 0.070061135 | Q27: Clinic
A28: Real Estate | E28: Crypto Investments | F28: =B12 -> 23625 | G28: =F28/SUM($F$25:$F$31) -> 0.014461075 | N28: IVOV - US Small/Mid Cap | O28: =($B$10+$B$11)*0.1 -> 10888.619 | P28: =O28/$O$18 -> 0.0071069047 | Q28: M1
A29: Main Home - Redfin | B29: 315000 | C29: 46305 | E29: Retirement Investments | F29: =B26 -> 1114222.4 | G29: =F29/SUM($F$25:$F$31) -> 0.68202552 | N29: VIOV - US Small/Mid Cap | O29: =($B$10+$B$11)*0.1 -> 10888.619 | P29: =O29/$O$18 -> 0.0071069047 | Q29: M1
A30: Rental Property - Redfin | B30: 105000 | C30: 46305 | E30: Real Estate | F30: =B31-F6 -> 285384.78 | G30: =F30/SUM($F$25:$F$31) -> 0.17468659 | N30: Real Estate | O30: =B31-F6 -> 285384.78 | P30: =O30/$O$18 -> 0.18626811 | Q30: Real
A31: Total Property Values | B31: =SUM(B29:B30) -> 420000 | C31: =(B31-F6)/F3 -> 0.17661144 | E31: Vehicles | F31: =B40-F8-F7 -> 69894 | G31: =F31/SUM($F$25:$F$31) -> 0.042782745 | N31: VNQ - US REIT | O31: =($B$10+$B$11)*0.05 -> 5444.3095 | P31: =O31/$O$18 -> 0.0035534523 | Q31: M1
N32: Crypto | O32: =B12 -> 23625 | P32: =O32/$O$18 -> 0.015419827 | Q32: Kraken
A33: Vehicles
A34: 2019 Chevy Silverado (JAF3923) | B34: 21500 | C34: 46305
A35: 2019 Toyota Rav 4 (JZJ5569) | B35: 20500 | C35: 46305 | N35: US Large Cap | O35: =SUM(O19:O21) -> 584332.73 | P35: =O35/$O$18 -> 0.38138877
A36: 2013 Toyota Corolla (KLM2660) | B36: 9000 | C36: 46305 | N36: International | O36: =SUM(O22:O25) -> 388709.81 | P36: =O36/$O$18 -> 0.25370743
A37: 2003 Toyota Corolla | B37: 2700 | C37: 46305 | N37: US Small/Mid Cap | O37: =SUM(O26:O29) -> 244621.71 | P37: =O37/$O$18 -> 0.15966241
A38: 2005 Gulf Stream Sun Voyager (HEH3760) | B38: 23000 | C38: 46305 | N38: Real Estate | O38: =O30+O31 -> 290829.09 | P38: =O38/$O$18 -> 0.18982156
A39: Custom EZGO TXT | B39: 10000 | C39: 46305 | N39: Crypto | O39: =O32 -> 23625 | P39: =O39/$O$18 -> 0.015419827
A40: Total Vehicle Values | B40: =SUM(B34:B39) -> 86700 | C40: =(B40-F8-F7)/F3 -> 0.043254164 | N40: Totals | O40: =SUM(O35:O39) -> 1532118.3 | P40: =SUM(P35:P39) -> 1
A42: 2003 Toyota Corolla (KFB5773)
A43: 2008 Honda Fit (EJV3194)
A44: 2001 EZGO (KKB6096)

Sheet 50-30-20
B1: Proposed | D1: Actual | H1: Proposed | J1: Actual | N1: Proposed | P1: Actual | T1: Proposed | V1: Actual
A2: Income | B2: =SUM(B4:B7) -> 206163.2 | D2: =SUM(D4:D7) -> 169150.76 | G2: Needs | H2: =SUM(H4:H30) -> 88260 | I2: =H2/B2 -> 0.42810744 | J2: =SUM(J4:J30) -> 74465.425 | K2: =J2/D2 -> 0.4402311 | M2: Wants | N2: =SUM(N4:N19) -> 67740 | O2: =N2/B2 -> 0.32857464 | P2: =SUM(P4:P19) -> 65604.125 | Q2: =P2/D2 -> 0.3878441 | S2: Savings | T2: =SUM(T4:T7) -> 50163.202 | U2: =T2/B2 -> 0.24331792 | V2: =SUM(V4:V7) -> 29081.21 | W2: =V2/D2 -> 0.1719248
A4: Lorri Pay | B4: ='Proposed Budget'!N68 -> 110347.83 | C4: =B4/$B$2 -> 0.53524504 | D4: ='Monthly Breakdown'!E49 -> 87081.64 | E4: =D4/$D$2 -> 0.51481672 | G4: ='Proposed Budget'!C5 -> Groceries/Household | H4: ='Proposed Budget'!F5 -> 14400 | I4: =H4/$B$2 -> 0.069847576 | J4: ='Monthly Breakdown'!E5 -> 10679.77 | K4: =J4/$D$2 -> 0.063137582 | M4: ='Proposed Budget'!C6 -> Dining Out | N4: ='Proposed Budget'!F6 -> 14400 | O4: =N4/$B$2 -> 0.069847576 | P4: ='Monthly Breakdown'!E6 -> 10506.12 | Q4: =P4/$D$2 -> 0.062110983 | S4: ='Proposed Budget'!C46 -> Our Savings | T4: ='Proposed Budget'!F46 -> 49563.202 | U4: =T4/$B$2 -> 0.24040761 | V4: ='Monthly Breakdown'!E46 -> 42892.82 | W4: =V4/$D$2 -> 0.25357746
A5: Isaac Pay | B5: ='Proposed Budget'!N44 -> 71858.371 | C5: =B5/$B$2 -> 0.34855091 | D5: ='Monthly Breakdown'!E50 -> 61728.68 | E5: =D5/$D$2 -> 0.36493292 | G5: ='Proposed Budget'!C7 -> Misc Food | H5: ='Proposed Budget'!F7*0.5 -> 900 | I5: =H5/$B$2 -> 0.0043654735 | J5: ='Monthly Breakdown'!E7*0.5 -> 556.385 | K5: =J5/$D$2 -> 0.0032892847 | M5: ='Proposed Budget'!C7 -> Misc Food | N5: ='Proposed Budget'!F7*0.5 -> 900 | O5: =N5/$B$2 -> 0.0043654735 | P5: ='Monthly Breakdown'!E7*0.5 -> 556.385 | Q5: =P5/$D$2 -> 0.0032892847 | S5: ='Proposed Budget'!C45 -> Kids Savings | T5: ='Proposed Budget'!F45 -> 600 | U5: =T5/$B$2 -> 0.0029103157 | V5: ='Monthly Breakdown'!E45 -> 450 | W5: =V5/$D$2 -> 0.0026603487
A6: Isaac Guard | B6: ='Proposed Budget'!J21 -> 14357 | C6: =B6/$B$2 -> 0.069639004 | D6: ='Monthly Breakdown'!E51 -> 12340.44 | E6: =D6/$D$2 -> 0.072955274 | G6: ='Proposed Budget'!C8 -> Gasoline | H6: ='Proposed Budget'!F8 -> 7200 | I6: =H6/$B$2 -> 0.034923788 | J6: ='Monthly Breakdown'!E8 -> 6416.07 | K6: =J6/$D$2 -> 0.037931074 | M6: ='Proposed Budget'!C9 -> Family Entertainment | N6: ='Proposed Budget'!F9 -> 8400 | O6: =N6/$B$2 -> 0.04074442 | P6: ='Monthly Breakdown'!E9 -> 8009.17 | Q6: =P6/$D$2 -> 0.0473493 | S6: Monthly Difference | V6: ='Budget Breakdown'!T16 -> 5043.65 | W6: =V6/$D$2 -> 0.029817484
A7: Rental | B7: ='Proposed Budget'!J22 -> 9600 | C7: =B7/$B$2 -> 0.046565051 | D7: ='Monthly Breakdown'!E52 -> 8000 | E7: =D7/$D$2 -> 0.047295088 | G7: ='Proposed Budget'!C14 -> Rocket Mortgage | H7: ='Proposed Budget'!F14 -> 15420 | I7: =H7/$B$2 -> 0.074795113 | J7: ='Monthly Breakdown'!E14 -> 12516.2 | K7: =J7/$D$2 -> 0.073994347 | M7: ='Proposed Budget'!C10 -> Miscellaneous Spending | N7: ='Proposed Budget'!F10 -> 10800 | O7: =N7/$B$2 -> 0.052385682 | P7: ='Monthly Breakdown'!E10 -> 8495.71 | Q7: =P7/$D$2 -> 0.050225669 | S7: Variable Savings | V7: ='Savings Transaction Log'!I2+'Savings Transaction Log'!K2+'Savings Transaction Log'!M2+'Savings Transaction Log'!O2+'Savings Transaction Log'!Q2+'Savings Transaction Log'!S2+'Savings Transaction Log'!U2+'Savings Transaction Log'!W2+'Savings Transaction Log'!Y2+'Savings Transaction Log'!AA2+'Savings Transaction Log'!AC2 -> -19305.26 | W7: =V7/$D$2 -> -0.1141305
G8: ='Proposed Budget'!C15 -> EH Roberts | H8: ='Proposed Budget'!F15 -> 240 | I8: =H8/$B$2 -> 0.0011641263 | J8: ='Monthly Breakdown'!E15 -> 161.1 | K8: =J8/$D$2 -> 0.00095240483 | M8: ='Proposed Budget'!C11 -> Department Stores/Clothes | N8: ='Proposed Budget'!F11 -> 4200 | O8: =N8/$B$2 -> 0.02037221 | P8: ='Monthly Breakdown'!E11 -> 2911.15 | Q8: =P8/$D$2 -> 0.017210387
G9: ='Proposed Budget'!C16 -> Verizon Wireless | H9: ='Proposed Budget'!F16 -> 3240 | I9: =H9/$B$2 -> 0.015715705 | J9: ='Monthly Breakdown'!E16 -> 2847.28 | K9: =J9/$D$2 -> 0.016832795 | M9: ='Proposed Budget'!C12 -> Alcohol/Bars | N9: ='Proposed Budget'!F12 -> 8400 | O9: =N9/$B$2 -> 0.04074442 | P9: ='Monthly Breakdown'!E12 -> 7347.57 | Q9: =P9/$D$2 -> 0.043437996
G10: ='Proposed Budget'!C17 -> Spectrum TV/Internet | H10: ='Proposed Budget'!F17*0.5 -> 1230 | I10: =H10/$B$2 -> 0.0059661471 | J10: ='Monthly Breakdown'!E17*0.5 -> 1037.955 | K10: =J10/$D$2 -> 0.0061362716 | M10: ='Proposed Budget'!C17 -> Spectrum TV/Internet | N10: ='Proposed Budget'!F17*0.5 -> 1230 | O10: =N10/$B$2 -> 0.0059661471 | P10: ='Monthly Breakdown'!E17*0.5 -> 1037.955 | Q10: =P10/$D$2 -> 0.0061362716
G11: ='Proposed Budget'!C18 -> First Energy | H11: ='Proposed Budget'!F18 -> 2160 | I11: =H11/$B$2 -> 0.010477136 | J11: ='Monthly Breakdown'!E18 -> 2065.97 | K11: =J11/$D$2 -> 0.012213779 | M11: ='Proposed Budget'!C22 -> Planet Fitness | N11: ='Proposed Budget'!F22 -> 1740 | O11: =N11/$B$2 -> 0.0084399155 | P11: ='Monthly Breakdown'!E22 -> 1639.08 | Q11: =P11/$D$2 -> 0.009690054
G12: ='Proposed Budget'!C19 -> Vivint Home Security | H12: ='Proposed Budget'!F19 -> 1680 | I12: =H12/$B$2 -> 0.0081488839 | J12: ='Monthly Breakdown'!E19 -> 1366.8 | K12: =J12/$D$2 -> 0.0080803657 | M12: ='Proposed Budget'!C23 -> Lowes Rewards | N12: ='Proposed Budget'!F23*0.5 -> 2400 | O12: =N12/$B$2 -> 0.011641263 | P12: ='Monthly Breakdown'!E23*0.5 -> 1000 | Q12: =P12/$D$2 -> 0.0059118859
G13: ='Proposed Budget'!C20 -> Columbia Gas | H13: ='Proposed Budget'!F20 -> 1200 | I13: =H13/$B$2 -> 0.0058206314 | J13: ='Monthly Breakdown'!E20 -> 1071.36 | K13: =J13/$D$2 -> 0.0063337581 | M13: ='Proposed Budget'!C24 -> Wells Fargo - Pool | N13: ='Proposed Budget'!F24 -> 2400 | O13: =N13/$B$2 -> 0.011641263 | P13: ='Monthly Breakdown'!E24 -> 2000 | Q13: =P13/$D$2 -> 0.011823772
G14: ='Proposed Budget'!C21 -> Medical Bills | H14: ='Proposed Budget'!F21 -> 0 | I14: =H14/$B$2 -> 0 | J14: ='Monthly Breakdown'!E21 -> 1898.15 | K14: =J14/$D$2 -> 0.011221646 | M14: ='Proposed Budget'!C25 -> Wells Fargo - Deck | N14: ='Proposed Budget'!F25*0.5 -> 3600 | O14: =N14/$B$2 -> 0.017461894 | P14: ='Monthly Breakdown'!E25*0.5 -> 1800 | Q14: =P14/$D$2 -> 0.010641395
G15: ='Proposed Budget'!C23 -> Lowes Rewards | H15: ='Proposed Budget'!F23*0.5 -> 2400 | I15: =H15/$B$2 -> 0.011641263 | J15: ='Monthly Breakdown'!E23*0.5 -> 1000 | K15: =J15/$D$2 -> 0.0059118859 | M15: ='Proposed Budget'!C26 -> Massage Envy | N15: ='Proposed Budget'!F26 -> 1020 | O15: =N15/$B$2 -> 0.0049475367 | P15: ='Monthly Breakdown'!E26 -> 934.73 | Q15: =P15/$D$2 -> 0.0055260171
G16: ='Proposed Budget'!C25 -> Wells Fargo - Deck | H16: ='Proposed Budget'!F25*0.5 -> 3600 | I16: =H16/$B$2 -> 0.017461894 | J16: ='Monthly Breakdown'!E25*0.5 -> 1800 | K16: =J16/$D$2 -> 0.010641395 | M16: ='Proposed Budget'!C27 -> Streaming/Music | N16: ='Proposed Budget'!F27 -> 1200 | O16: =N16/$B$2 -> 0.0058206314 | P16: ='Monthly Breakdown'!E27 -> 1390.11 | Q16: =P16/$D$2 -> 0.0082181718
G17: ='Proposed Budget'!C28 -> GM Financial/Toyota | H17: ='Proposed Budget'!F28 -> 14400 | I17: =H17/$B$2 -> 0.069847576 | J17: ='Monthly Breakdown'!E28 -> 9148.86 | K17: =J17/$D$2 -> 0.054087017 | M17: ='Proposed Budget'!C38 -> Camping/Vacation | N17: ='Proposed Budget'!F38 -> 4800 | O17: =N17/$B$2 -> 0.023282525 | P17: ='Savings Transaction Log'!R5 -> 6641.09 | Q17: =P17/$D$2 -> 0.039261367
G18: ='Proposed Budget'!C29 -> Ohio Turnpike | H18: ='Proposed Budget'!F29 -> 1440 | I18: =H18/$B$2 -> 0.0069847576 | J18: ='Monthly Breakdown'!E29 -> 1022.5 | K18: =J18/$D$2 -> 0.0060449034 | M18: ='Proposed Budget'!C39 -> Home Maintenance | N18: ='Proposed Budget'!F39*0.5 -> 2250 | O18: =N18/$B$2 -> 0.010913684 | P18: ='Savings Transaction Log'!T5*0.5 -> 11335.055 | Q18: =P18/$D$2 -> 0.067011552
G19: ='Proposed Budget'!C30 -> Water Bill - Main | H19: ='Proposed Budget'!F30 -> 900 | I19: =H19/$B$2 -> 0.0043654735 | J19: ='Monthly Breakdown'!E30 -> 912.12 | K19: =J19/$D$2 -> 0.0053923494
G20: ='Proposed Budget'!C31 -> Water Bill - Rental | H20: ='Proposed Budget'!F31 -> 900 | I20: =H20/$B$2 -> 0.0043654735 | J20: ='Monthly Breakdown'!E31 -> 635.79 | K20: =J20/$D$2 -> 0.003758718
G21: ='Proposed Budget'!C33 -> Vehicle Maintenance | H21: ='Proposed Budget'!F33 -> 4200 | I21: =H21/$B$2 -> 0.02037221 | J21: ='Savings Transaction Log'!H5 -> 1616.64 | K21: =J21/$D$2 -> 0.0095573913
G22: ='Proposed Budget'!C34 -> Car Insurance | H22: ='Proposed Budget'!F34 -> 3840 | I22: =H22/$B$2 -> 0.01862602 | J22: ='Savings Transaction Log'!J5 -> 2159 | K22: =J22/$D$2 -> 0.012763762
G23: ='Proposed Budget'!C35 -> Rental Garbage | H23: ='Proposed Budget'!F35 -> 300 | I23: =H23/$B$2 -> 0.0014551578 | J23: ='Savings Transaction Log'!L5 -> 260.79 | K23: =J23/$D$2 -> 0.0015417607
G24: ='Proposed Budget'!C36 -> Garbage | H24: ='Proposed Budget'!F36 -> 300 | I24: =H24/$B$2 -> 0.0014551578 | J24: ='Savings Transaction Log'!N5 -> 260.79 | K24: =J24/$D$2 -> 0.0015417607
G25: ='Proposed Budget'!C37 -> Sanitation - Main | H25: ='Proposed Budget'!F37 -> 540 | I25: =H25/$B$2 -> 0.0026192841 | J25: ='Savings Transaction Log'!P5 -> 374.28 | K25: =J25/$D$2 -> 0.0022127007
G26: ='Proposed Budget'!C39 -> Home Maintenance | H26: ='Proposed Budget'!F39*0.5 -> 2250 | I26: =H26/$B$2 -> 0.010913684 | J26: ='Savings Transaction Log'!T5*0.5 -> 11335.055 | K26: =J26/$D$2 -> 0.067011552
G27: ='Proposed Budget'!C40 -> Rental Repairs | H27: ='Proposed Budget'!F40 -> 1200 | I27: =H27/$B$2 -> 0.0058206314 | J27: ='Savings Transaction Log'!V5 -> 0 | K27: =J27/$D$2 -> 0
G28: ='Proposed Budget'!C41 -> Rental Insurance | H28: ='Proposed Budget'!F41 -> 1020 | I28: =H28/$B$2 -> 0.0049475367 | J28: ='Savings Transaction Log'!X5 -> 500.5 | K28: =J28/$D$2 -> 0.0029588989
G29: ='Proposed Budget'!C42 -> Rental Property Taxes | H29: ='Proposed Budget'!F42 -> 2760 | I29: =H29/$B$2 -> 0.013387452 | J29: ='Savings Transaction Log'!Z5 -> 2447.78 | K29: =J29/$D$2 -> 0.014470996
G30: ='Proposed Budget'!C43 -> Rental Sanitation | H30: ='Proposed Budget'!F43 -> 540 | I30: =H30/$B$2 -> 0.0026192841 | J30: ='Savings Transaction Log'!AB5 -> 374.28 | K30: =J30/$D$2 -> 0.0022127007

Sheet Proposed Budget
A1: 2026 PROPOSED BUDGET
D2: MONTHLY | E2: % | F2: ANNUAL | G2: WEEKLY | J2: ANNUAL | K2: % | L2: MONTHLY
C3: TOTALS | D3: =SUM(D5:D61) -> 17180.267 | E3: =SUM(E5:E61) -> 1 | F3: =SUM(F5:F61) -> 206163.2 | G3: =F3/52 -> 3964.677 | I3: Gross Pay | J3: =L29+L49 -> 276499.57 | L3: =J3/12 -> 23041.631
A5: D | B5: 1 | C5: Groceries/Household | D5: 1200 | E5: =D5/$O$24 -> 0.069847576 | F5: =D5*12 -> 14400 | G5: =F5/52 -> 276.92308 | I5: Health/Life Insurance | J5: =L31+L53+L54+L55 -> 4120.9 | K5: =J5/J3 -> 0.014903821 | L5: =J5/12 -> 343.40833
A6: D | B6: 2 | C6: Dining Out | D6: 1200 | E6: =D6/$O$24 -> 0.069847576 | F6: =D6*12 -> 14400 | G6: =F6/52 -> 276.92308 | I6: Retirement | J6: =L32+L56 -> 17269.978 | K6: =J6/J3 -> 0.06245933 | L6: =J6/12 -> 1439.1648
A7: D | B7: 3 | C7: Misc Food | D7: 150 | E7: =D7/$O$24 -> 0.008730947 | F7: =D7*12 -> 1800 | G7: =F7/52 -> 34.615385 | I7: Pre-Tax Deductions | J7: =SUM(J5:J6) -> 21390.878 | K7: =J7/J3 -> 0.077363151 | L7: =SUM(L5:L6) -> 1782.5732
A8: D | B8: 4 | C8: Gasoline | D8: 600 | E8: =D8/$O$24 -> 0.034923788 | F8: =D8*12 -> 7200 | G8: =F8/52 -> 138.46154
A9: D | B9: 5 | C9: Family Entertainment | D9: 700 | E9: =D9/$O$24 -> 0.04074442 | F9: =D9*12 -> 8400 | G9: =F9/52 -> 161.53846 | I9: Taxable Pay | J9: =L35+L59 -> 255924.69 | L9: =J9/12 -> 21327.058
A10: D | B10: 6 | C10: Miscellaneous Spending | D10: 900 | E10: =D10/$O$24 -> 0.052385682 | F10: =D10*12 -> 10800 | G10: =F10/52 -> 207.69231
A11: D | B11: 7 | C11: Department Stores/Clothes | D11: 350 | E11: =D11/$O$24 -> 0.02037221 | F11: =D11*12 -> 4200 | G11: =F11/52 -> 80.769231 | I11: Federal Tax | J11: =L37+L61 -> 39427.36 | K11: =J11/J9 -> 0.15405845 | L11: =J11/12 -> 3285.6133
A12: D | B12: 8 | C12: Alcohol/Bars | D12: 700 | E12: =D12/$O$24 -> 0.04074442 | F12: =D12*12 -> 8400 | G12: =F12/52 -> 161.53846 | I12: Ohio Tax | J12: =L38+L62 -> 7415.6 | K12: =J12/J9 -> 0.028975711 | L12: =J12/12 -> 617.96667
I13: Medicare | J13: =L39+L63 -> 3961.2645 | K13: =J13/(J9+J6) -> 0.014499787 | L13: =J13/12 -> 330.10538
A14: F | B14: 9 | C14: Rocket Mortgage | D14: 1285 | E14: =D14/$O$24 -> 0.074795113 | F14: =D14*12 -> 15420 | G14: =F14/52 -> 296.53846 | I14: Social Security | J14: =L40+L64 -> 16938.028 | K14: =J14/(J9+J6) -> 0.061999847 | L14: =J14/12 -> 1411.5023
A15: F | B15: 10 | C15: EH Roberts | D15: 20 | E15: =D15/$O$24 -> 0.0011641263 | F15: =D15*12 -> 240 | G15: =F15/52 -> 4.6153846 | I15: FERS Retirement | J15: =L41 -> 833.9968 | K15: =J15/J3 -> 0.003016268 | L15: =J15/12 -> 69.499733
A16: F | B16: 11 | C16: Verizon Wireless | D16: 270 | E16: =D16/$O$24 -> 0.015715705 | F16: =D16*12 -> 3240 | G16: =F16/52 -> 62.307692 | I16: Cleveland Tax | J16: =L65 -> 4326.24 | K16: =J16/J9 -> 0.016904348 | L16: =J16/12 -> 360.52
A17: F | B17: 12 | C17: Spectrum TV/Internet | D17: 205 | E17: =D17/$O$24 -> 0.011932294 | F17: =D17*12 -> 2460 | G17: =F17/52 -> 47.307692 | I17: Employee Taxes | J17: =SUM(J11:J16) -> 72902.489 | K17: =J17/J3 -> 0.26366222 | L17: =SUM(L11:L16) -> 6075.2074
A18: F | B18: 13 | C18: First Energy | D18: 180 | E18: =D18/$O$24 -> 0.010477136 | F18: =D18*12 -> 2160 | G18: =F18/52 -> 41.538462
A19: F | B19: 14 | C19: Vivint Home Security | D19: 140 | E19: =D19/$O$24 -> 0.0081488839 | F19: =D19*12 -> 1680 | G19: =F19/52 -> 32.307692 | I19: Combined Take Home | J19: =L44+L68 -> 182206.2 | K19: =J19/J3 -> 0.65897463
A20: F | B20: 15 | C20: Columbia Gas | D20: 100 | E20: =D20/$O$24 -> 0.0058206314 | F20: =D20*12 -> 1200 | G20: =F20/52 -> 23.076923
A21: F | B21: 16 | C21: Medical Bills | D21: 0 | E21: =D21/$O$24 -> 0 | F21: =D21*12 -> 0 | G21: =F21/52 -> 0 | I21: Guard Take Home | J21: 14357 | L21: =J21/12 -> 1196.4167
A22: F | B22: 17 | C22: Planet Fitness | D22: 145 | E22: =D22/$O$24 -> 0.0084399155 | F22: =D22*12 -> 1740 | G22: =F22/52 -> 33.461538 | I22: Rental Income | J22: 9600 | L22: =J22/12 -> 800 | M22: =L22-D31-D35-D40-D41-D42-D43 -> 240 | N22: =M22*12 -> 2880
A23: F | B23: 18 | C23: Lowes Rewards | D23: 400 | E23: =D23/$O$24 -> 0.023282525 | F23: =D23*12 -> 4800 | G23: =F23/52 -> 92.307692
A24: F | B24: 19 | C24: Wells Fargo - Pool | D24: 200 | E24: =D24/$O$24 -> 0.011641263 | F24: =D24*12 -> 2400 | G24: =F24/52 -> 46.153846 | I24: Total Take Home | J24: =J19+J22+J21 -> 206163.2 | K24: =(J24+J6)/J3 -> 0.80807786 | L24: =J24/12 -> 17180.267 | N24: =J21+J22+N44+N68 -> 206163.2 | O24: =N24/12 -> 17180.267
A25: F | B25: 20 | C25: Wells Fargo - Deck | D25: 600 | E25: =D25/$O$24 -> 0.034923788 | F25: =D25*12 -> 7200 | G25: =F25/52 -> 138.46154
A26: F | B26: 21 | C26: Massage Envy | D26: 85 | E26: =D26/$O$24 -> 0.0049475367 | F26: =D26*12 -> 1020 | G26: =F26/52 -> 19.615385
A27: F | B27: 22 | C27: Streaming/Music | D27: 100 | E27: =D27/$O$24 -> 0.0058206314 | F27: =D27*12 -> 1200 | G27: =F27/52 -> 23.076923 | I27: ISAAC | J27: 50.12
A28: F | B28: 23 | C28: GM Financial/Toyota | D28: 1200 | E28: =D28/$O$24 -> 0.069847576 | F28: =D28*12 -> 14400 | G28: =F28/52 -> 276.92308 | J28: PAY PERIOD | K28: % | L28: ANNUAL | M28: MONTHLY
A29: F | B29: 24 | C29: Ohio Turnpike | D29: 120 | E29: =D29/$O$24 -> 0.0069847576 | F29: =D29*12 -> 1440 | G29: =F29/52 -> 27.692308 | I29: Gross Pay | J29: =J27*80 -> 4009.6 | L29: =J29*26 -> 104249.6 | M29: =L29/12 -> 8687.4667
A30: F | B30: 42 | C30: Water Bill - Main | D30: 75 | E30: =D30/$O$24 -> 0.0043654735 | F30: =D30*12 -> 900 | G30: =F30/52 -> 17.307692
A31: F | B31: 43 | C31: Water Bill - Rental | D31: 75 | E31: =D31/$O$24 -> 0.0043654735 | F31: =D31*12 -> 900 | G31: =F31/52 -> 17.307692 | I31: Health Ins | J31: 157.97 | K31: =J31/J29 -> 0.039397945 | L31: =J31*26 -> 4107.22 | M31: =L31/12 -> 342.26833
I32: TSP | J32: =K32*J29 -> 200.48 | K32: 0.05 | L32: =J32*26 -> 5212.48 | M32: =L32/12 -> 434.37333
A33: R | B33: 25 | C33: Vehicle Maintenance | D33: 350 | E33: =D33/$O$24 -> 0.02037221 | F33: =D33*12 -> 4200 | G33: =F33/52 -> 80.769231 | I33: Pre-Tax Deductions | J33: =SUM(J31:J32) -> 358.45
A34: R | B34: 26 | C34: Car Insurance | D34: 320 | E34: =D34/$O$24 -> 0.01862602 | F34: =D34*12 -> 3840 | G34: =F34/52 -> 73.846154
A35: R | B35: 27 | C35: Rental Garbage | D35: 25 | E35: =D35/$O$24 -> 0.0014551578 | F35: =D35*12 -> 300 | G35: =F35/52 -> 5.7692308 | I35: Taxable Pay | J35: =J29+J30-J31-J32 -> 3651.15 | K35: =J35/J29 -> 0.91060206 | L35: =J35*26 -> 94929.9 | M35: =L35/12 -> 7910.825
A36: R | B36: 28 | C36: Garbage | D36: 25 | E36: =D36/$O$24 -> 0.0014551578 | F36: =D36*12 -> 300 | G36: =F36/52 -> 5.7692308
A37: R | B37: 29 | C37: Sanitation - Main | D37: 45 | E37: =D37/$O$24 -> 0.0026192841 | F37: =D37*12 -> 540 | G37: =F37/52 -> 10.384615 | I37: Federal Tax | J37: 463.64 | K37: =J37/J35 -> 0.12698465 | L37: =J37*26 -> 12054.64 | M37: =L37/12 -> 1004.5533
A38: R | B38: 30 | C38: Camping/Vacation | D38: 400 | E38: =D38/$O$24 -> 0.023282525 | F38: =D38*12 -> 4800 | G38: =F38/52 -> 92.307692 | I38: Ohio Tax | J38: 97 | K38: =J38/J35 -> 0.026566972 | L38: =J38*26 -> 2522 | M38: =L38/12 -> 210.16667
A39: R | B39: 31 | C39: Home Maintenance | D39: 375 | E39: =D39/$O$24 -> 0.021827368 | F39: =D39*12 -> 4500 | G39: =F39/52 -> 86.538462 | I39: Medicare | J39: =(J35+J32)*K39 -> 55.848635 | K39: 0.0145 | L39: =J39*26 -> 1452.0645 | M39: =L39/12 -> 121.00538
A40: R | B40: 32 | C40: Rental Repairs | D40: 100 | E40: =D40/$O$24 -> 0.0058206314 | F40: =D40*12 -> 1200 | G40: =F40/52 -> 23.076923 | I40: Social Security | J40: =(J35+J32)*K40 -> 238.80106 | K40: 0.062 | L40: =J40*26 -> 6208.8276 | M40: =L40/12 -> 517.4023
A41: R | B41: 33 | C41: Rental Insurance | D41: 85 | E41: =D41/$O$24 -> 0.0049475367 | F41: =D41*12 -> 1020 | G41: =F41/52 -> 19.615385 | I41: FERS Retirement | J41: =K41*J29 -> 32.0768 | K41: 0.008 | L41: =J41*26 -> 833.9968 | M41: =L41/12 -> 69.499733
A42: R | B42: 34 | C42: Rental Property Taxes | D42: 230 | E42: =D42/$O$24 -> 0.013387452 | F42: =D42*12 -> 2760 | G42: =F42/52 -> 53.076923 | I42: Employee Taxes | J42: =SUM(J37:J41) -> 887.36649 | K42: =J42/J29 -> 0.22131048
A43: R | B43: 35 | C43: Rental Sanitation | D43: 45 | E43: =D43/$O$24 -> 0.0026192841 | F43: =D43*12 -> 540 | G43: =F43/52 -> 10.384615
I44: Take Home | J44: =J29-J33-J42 -> 2763.7835 | K44: =(J44+J32)/J29 -> 0.73929158 | L44: =J44*26 -> 71858.371 | M44: =L44/12 -> 5988.1976 | N44: =L44 -> 71858.371 | O44: =N44/26 -> 2763.7835
A45: S | B45: 36 | C45: Kids Savings | D45: =F45/12 -> 50 | E45: =D45/$O$24 -> 0.0029103157 | F45: =50*12 -> 600 | G45: =F45/52 -> 11.538462
A46: S | B46: 37 | C46: Our Savings | D46: =F46/12 -> 4130.2668 | E46: =D46/$O$24 -> 0.24040761 | F46: =(N24-SUM(F5:F45)) -> 49563.202 | G46: =F46/52 -> 953.1385
I47: LORRI | J47: 82.8093
J48: PAY PERIOD | K48: % | L48: ANNUAL | M48: MONTHLY
I49: Gross Pay | J49: =J47*86.67 -> 7177.082 | L49: =J49*24 -> 172249.97 | M49: =L49/12 -> 14354.164
I50: GTL | J50: 34
I51: Gross Earnings | J51: =J49+J50 -> 7211.082
I53: Life Insurance | J53: 9.05 | K53: =J53/J49 -> 0.0012609581 | L53: =J53*24 -> 217.2 | M53: =L53/12 -> 18.1
I54: Dental | J54: 23.67 | K54: =J54/J49 -> 0.0032979977 | L54: =J54*24 -> 568.08 | M54: =L54/12 -> 47.34
I55: PTOTRDN | J55: -32.15 | K55: =J55/J49 -> -0.0044795364 | L55: =J55*24 -> -771.6 | M55: =L55/12 -> -64.3
I56: Retirement | J56: =J49*K56 -> 502.39574 | K56: 0.07 | L56: =J56*24 -> 12057.498 | M56: =L56/12 -> 1004.7915
I57: Pre-Tax Deductions | J57: =SUM(J53:J56) -> 502.96574
I59: Taxable Pay | J59: =J51-J57 -> 6708.1163 | L59: =J59*24 -> 160994.79 | M59: =L59/12 -> 13416.233
I61: Federal Tax | J61: 1140.53 | K61: =J61/J59 -> 0.1700224 | L61: =J61*24 -> 27372.72 | M61: =L61/12 -> 2281.06
I62: Ohio Tax | J62: 203.9 | K62: =J62/J59 -> 0.030396015 | L62: =J62*24 -> 4893.6 | M62: =L62/12 -> 407.8
I63: Medicare | J63: 104.55 | K63: =J63/J51 -> 0.014498518 | L63: =J63*24 -> 2509.2 | M63: =L63/12 -> 209.1
I64: Social Security | J64: 447.05 | K64: =J64/J51 -> 0.061994857 | L64: =J64*24 -> 10729.2 | M64: =L64/12 -> 894.1
I65: Cleveland Tax | J65: 180.26 | K65: =J65/J51 -> 0.024997635 | L65: =J65*24 -> 4326.24 | M65: =L65/12 -> 360.52
I66: Employee Taxes | J66: =SUM(J61:J65) -> 2076.29 | K66: =J66/J49 -> 0.28929445
I68: Take Home | J68: =J49-J57-J66 -> 4597.8263 | K68: =(J68+J56)/J49 -> 0.71062613 | L68: =J68*24 -> 110347.83 | M68: =L68/12 -> 9195.6526 | N68: =L68 -> 110347.83 | O68: =N68/24 -> 4597.8263

Sheet Monthly Breakdown
D1: Monthly | E1: Total | F1: Total | G1: % | H1: Monthly | I1: 46023 | J1: 46053 | K1: 46054 | L1: 46081 | M1: 46082 | N1: 46112 | O1: 46113 | P1: 46142 | Q1: 46143 | R1: 46173 | S1: 46174 | T1: 46203 | U1: 46204 | V1: 46234 | W1: 46235 | X1: 46265 | Y1: 46266 | Z1: 46295 | AA1: 46296 | AB1: 46326 | AC1: 45962 | AD1: 45991 | AE1: 45627 | AF1: 45657
D2: Average | E2: Spent | F2: Difference | G2: Under | H2: Budget | I2: Spent | J2: Difference | K2: Spent | L2: Difference | M2: Spent | N2: Difference | O2: Spent | Q2: Spent | R2: Difference | S2: Spent | T2: Difference | U2: Spent | V2: Difference | W2: Spent | X2: Difference | Y2: Spent | Z2: Difference | AA2: Spent | AB2: Difference | AC2: Spent | AD2: Difference | AE2: Spent | AF2: Difference
A3: ID | C3: TOTALS | E3: =SUM(E5:E46) -> 164107.11 | F3: =SUM(F5:F46) -> 7695.5584 | G3: =1-((E3/SUM(E3:F3))) -> 0.044793008 | H3: =SUM(H5:H67) -> 17180.267 | I3: =SUM(I5:I46) -> 15639.36 | K3: =SUM(K5:K46) -> 16615.62 | M3: =SUM(M5:M46) -> 16971.29 | O3: =SUM(O5:O46) -> 18875.67 | Q3: =SUM(Q5:Q46) -> 14973.2 | S3: =SUM(S5:S46) -> 17750.78 | U3: =SUM(U5:U46) -> 20061.94 | W3: =SUM(W5:W46) -> 17483.15 | Y3: =SUM(Y5:Y46) -> 14978.64 | AA3: =SUM(AA5:AA46) -> 10757.46 | AC3: =SUM(AC5:AC46) -> 0 | AE3: =SUM(AE5:AE46) -> 0
A4: SPEND ACCOUNT
A5: ='Proposed Budget'!A5 -> D | B5: ='Proposed Budget'!B5 -> 1 | C5: ='Proposed Budget'!C5 -> Groceries/Household | D5: =(E5/(TODAY()-$I$1))*30.42 -> 1079.3309 | E5: =I5+K5+M5+O5+Q5+S5+U5+W5+Y5+AA5+AC5+AE5 -> 10679.77 | F5: =J5+L5+N5+P5+R5+T5+V5+X5+Z5+AB5 -> 1320.23 | G5: =1-((E5/SUM(E5:F5))) -> 0.11001917 | H5: ='Proposed Budget'!D5 -> 1200 | I5: =SUMIFS('Checking Transaction Log'!$E:$E,'Checking Transaction Log'!$C:$C,">="&I1,'Checking Transaction Log'!$C:$C,"<="&J1,'Checking Transaction Log'!$A:$A,"D",'Checking Transaction Log'!$B:$B,1) -> 1067.56 | J5: =H5-I5 -> 132.44 | K5: =SUMIFS('Checking Transaction Log'!$E:$E,'Checking Transaction Log'!$C:$C,">="&K1,'Checking Transaction Log'!$C:$C,"<="&L1,'Checking Transaction Log'!$A:$A,"D",'Checking Transaction Log'!$B:$B,1) -> 1033.9 | L5: =H5-K5 -> 166.1 | M5: =SUMIFS('Checking Transaction Log'!$E:$E,'Checking Transaction Log'!$C:$C,">="&M1,'Checking Transaction Log'!$C:$C,"<="&N1,'Checking Transaction Log'!$A:$A,"D",'Checking Transaction Log'!$B:$B,1) -> 1358.86 | N5: =H5-M5 -> -158.86 | O5: =SUMIFS('Checking Transaction Log'!$E:$E,'Checking Transaction Log'!$C:$C,">="&O1,'Checking Transaction Log'!$C:$C,"<="&P1,'Checking Transaction Log'!$A:$A,"D",'Checking Transaction Log'!$B:$B,1) -> 1284.83 | P5: =H5-O5 -> -84.83 | Q5: =SUMIFS('Checking Transaction Log'!$E:$E,'Checking Transaction Log'!$C:$C,">="&Q1,'Checking Transaction Log'!$C:$C,"<="&R1,'Checking Transaction Log'!$A:$A,"D",'Checking Transaction Log'!$B:$B,1) -> 1263.15 | R5: =H5-Q5 -> -63.15 | S5: =SUMIFS('Checking Transaction Log'!$E:$E,'Checking Transaction Log'!$C:$C,">="&S1,'Checking Transaction Log'!$C:$C,"<="&T1,'Checking Transaction Log'!$A:$A,"D",'Checking Transaction Log'!$B:$B,1) -> 1292.96 | T5: =H5-S5 -> -92.96 | U5: =SUMIFS('Checking Transaction Log'!$E:$E,'Checking Transaction Log'!$C:$C,">="&U1,'Checking Transaction Log'!$C:$C,"<="&V1,'Checking Transaction Log'!$A:$A,"D",'Checking Transaction Log'!$B:$B,1) -> 1111.57 | V5: =H5-U5 -> 88.43 | W5: =SUMIFS('Checking Transaction Log'!$E:$E,'Checking Transaction Log'!$C:$C,">="&W1,'Checking Transaction Log'!$C:$C,"<="&X1,'Checking Transaction Log'!$A:$A,"D",'Checking Transaction Log'!$B:$B,1) -> 868.64 | X5: =H5-W5 -> 331.36 | Y5: =SUMIFS('Checking Transaction Log'!$E:$E,'Checking Transaction Log'!$C:$C,">="&Y1,'Checking Transaction Log'!$C:$C,"<="&Z1,'Checking Transaction Log'!$A:$A,"D",'Checking Transaction Log'!$B:$B,1) -> 451.57 | Z5: =H5-Y5 -> 748.43 | AA5: =SUMIFS('Checking Transaction Log'!$E:$E,'Checking Transaction Log'!$C:$C,">="&AA1,'Checking Transaction Log'!$C:$C,"<="&AB1,'Checking Transaction Log'!$A:$A,"D",'Checking Transaction Log'!$B:$B,1) -> 946.73 | AB5: =H5-AA5 -> 253.27 | AC5: =SUMIFS('Checking Transaction Log'!$E:$E,'Checking Transaction Log'!$C:$C,">="&AC1,'Checking Transaction Log'!$C:$C,"<="&AD1,'Checking Transaction Log'!$A:$A,"D",'Checking Transaction Log'!$B:$B,1) -> 0 | AD5: =H5-AC5 -> 1200 | AE5: =SUMIFS('Checking Transaction Log'!$E:$E,'Checking Transaction Log'!$C:$C,">="&AE1,'Checking Transaction Log'!$C:$C,"<="&AF1,'Checking Transaction Log'!$A:$A,"D",'Checking Transaction Log'!$B:$B,1) -> 0 | AF5: =H5-AE5 -> 1200
A6: ='Proposed Budget'!A6 -> D | B6: ='Proposed Budget'!B6 -> 2 | C6: ='Proposed Budget'!C6 -> Dining Out | D6: =(E6/(TODAY()-$I$1))*30.42 -> 1061.7813 | E6: =Q6+S6+U6+W6+Y6+AA6+AC6+AE6+I6+K6+M6+O6 -> 10506.12 | F6: =J6+L6+N6+P6+R6+T6+V6+X6+Z6+AB6 -> 1493.88 | G6: =1-((E6/SUM(E6:F6))) -> 0.12449 | H6: ='Proposed Budget'!D6 -> 1200 | I6: =SUMIFS('Checking Transaction Log'!E:E,'Checking Transaction Log'!C:C,">="&I1,'Checking Transaction Log'!C:C,"<="&J1,'Checking Transaction Log'!A:A,"D",'Checking Transaction Log'!B:B,2) -> 1061.45 | J6: =H6-I6 -> 138.55 | K6: =SUMIFS('Checking Transaction Log'!E:E,'Checking Transaction Log'!C:C,">="&K1,'Checking Transaction Log'!C:C,"<="&L1,'Checking Transaction Log'!A:A,"D",'Checking Transaction Log'!B:B,2) -> 911.68 | L6: =H6-K6 -> 288.32 | M6: =SUMIFS('Checking Transaction Log'!$E:$E,'Checking Transaction Log'!$C:$C,">="&M1,'Checking Transaction Log'!$C:$C,"<="&N1,'Checking Transaction Log'!$A:$A,"D",'Checking Transaction Log'!$B:$B,2) -> 1233.46 | N6: =H6-M6 -> -33.46 | O6: =SUMIFS('Checking Transaction Log'!$E:$E,'Checking Transaction Log'!$C:$C,">="&O1,'Checking Transaction Log'!$C:$C,"<="&P1,'Checking Transaction Log'!$A:$A,"D",'Checking Transaction Log'!$B:$B,2) -> 984.18 | P6: =H6-O6 -> 215.82 | Q6: =SUMIFS('Checking Transaction Log'!$E:$E,'Checking Transaction Log'!$C:$C,">="&Q1,'Checking Transaction Log'!$C:$C,"<="&R1,'Checking Transaction Log'!$A:$A,"D",'Checking Transaction Log'!$B:$B,2) -> 1603.86 | R6: =H6-Q6 -> -403.86 | S6: =SUMIFS('Checking Transaction Log'!$E:$E,'Checking Transaction Log'!$C:$C,">="&S1,'Checking Transaction Log'!$C:$C,"<="&T1,'Checking Transaction Log'!$A:$A,"D",'Checking Transaction Log'!$B:$B,2) -> 985.22 | T6: =H6-S6 -> 214.78 | U6: =SUMIFS('Checking Transaction Log'!$E:$E,'Checking Transaction Log'!$C:$C,">="&U1,'Checking Transaction Log'!$C:$C,"<="&V1,'Checking Transaction Log'!$A:$A,"D",'Checking Transaction Log'!$B:$B,2) -> 1129.6 | V6: =H6-U6 -> 70.4 | W6: =SUMIFS('Checking Transaction Log'!$E:$E,'Checking Transaction Log'!$C:$C,">="&W1,'Checking Transaction Log'!$C:$C,"<="&X1,'Checking Transaction Log'!$A:$A,"D",'Checking Transaction Log'!$B:$B,2) -> 816.74 | X6: =H6-W6 -> 383.26 | Y6: =SUMIFS('Checking Transaction Log'!$E:$E,'Checking Transaction Log'!$C:$C,">="&Y1,'Checking Transaction Log'!$C:$C,"<="&Z1,'Checking Transaction Log'!$A:$A,"D",'Checking Transaction Log'!$B:$B,2) -> 938.07 | Z6: =H6-Y6 -> 261.93 | AA6: =SUMIFS('Checking Transaction Log'!$E:$E,'Checking Transaction Log'!$C:$C,">="&AA1,'Checking Transaction Log'!$C:$C,"<="&AB1,'Checking Transaction Log'!$A:$A,"D",'Checking Transaction Log'!$B:$B,2) -> 841.86 | AB6: =H6-AA6 -> 358.14 | AC6: =SUMIFS('Checking Transaction Log'!$E:$E,'Checking Transaction Log'!$C:$C,">="&AC1,'Checking Transaction Log'!$C:$C,"<="&AD1,'Checking Transaction Log'!$A:$A,"D",'Checking Transaction Log'!$B:$B,2) -> 0 | AD6: =H6-AC6 -> 1200 | AE6: =SUMIFS('Checking Transaction Log'!$E:$E,'Checking Transaction Log'!$C:$C,">="&AE1,'Checking Transaction Log'!$C:$C,"<="&AF1,'Checking Transaction Log'!$A:$A,"D",'Checking Transaction Log'!$B:$B,2) -> 0 | AF6: =H6-AE6 -> 1200
A7: ='Proposed Budget'!A7 -> D | B7: ='Proposed Budget'!B7 -> 3 | C7: ='Proposed Budget'!C7 -> Misc Food | D7: =(E7/(TODAY()-$I$1))*30.42 -> 112.46001 | E7: =Q7+S7+U7+W7+Y7+AA7+AC7+AE7+I7+K7+M7+O7 -> 1112.77 | F7: =J7+L7+N7+P7+R7+T7+V7+X7+Z7+AB7 -> 387.23 | G7: =1-((E7/SUM(E7:F7))) -> 0.25815333 | H7: ='Proposed Budget'!D7 -> 150 | I7: =SUMIFS('Checking Transaction Log'!E:E,'Checking Transaction Log'!C:C,">="&I1,'Checking Transaction Log'!C:C,"<="&J1,'Checking Transaction Log'!A:A,"D",'Checking Transaction Log'!B:B,3) -> 144.51 | J7: =H7-I7 -> 5.49 | K7: =SUMIFS('Checking Transaction Log'!E:E,'Checking Transaction Log'!C:C,">="&K1,'Checking Transaction Log'!C:C,"<="&L1,'Checking Transaction Log'!A:A,"D",'Checking Transaction Log'!B:B,3) -> 90.76 | L7: =H7-K7 -> 59.24 | M7: =SUMIFS('Checking Transaction Log'!$E:$E,'Checking Transaction Log'!$C:$C,">="&M1,'Checking Transaction Log'!$C:$C,"<="&N1,'Checking Transaction Log'!$A:$A,"D",'Checking Transaction Log'!$B:$B,3) -> 173.53 | N7: =H7-M7 -> -23.53 | O7: =SUMIFS('Checking Transaction Log'!$E:$E,'Checking Transaction Log'!$C:$C,">="&O1,'Checking Transaction Log'!$C:$C,"<="&P1,'Checking Transaction Log'!$A:$A,"D",'Checking Transaction Log'!$B:$B,3) -> 91.66 | P7: =H7-O7 -> 58.34 | Q7: =SUMIFS('Checking Transaction Log'!$E:$E,'Checking Transaction Log'!$C:$C,">="&Q1,'Checking Transaction Log'!$C:$C,"<="&R1,'Checking Transaction Log'!$A:$A,"D",'Checking Transaction Log'!$B:$B,3) -> 180.06 | R7: =H7-Q7 -> -30.06 | S7: =SUMIFS('Checking Transaction Log'!$E:$E,'Checking Transaction Log'!$C:$C,">="&S1,'Checking Transaction Log'!$C:$C,"<="&T1,'Checking Transaction Log'!$A:$A,"D",'Checking Transaction Log'!$B:$B,3) -> 73.63 | T7: =H7-S7 -> 76.37 | U7: =SUMIFS('Checking Transaction Log'!$E:$E,'Checking Transaction Log'!$C:$C,">="&U1,'Checking Transaction Log'!$C:$C,"<="&V1,'Checking Transaction Log'!$A:$A,"D",'Checking Transaction Log'!$B:$B,3) -> 167.91 | V7: =H7-U7 -> -17.91 | W7: =SUMIFS('Checking Transaction Log'!$E:$E,'Checking Transaction Log'!$C:$C,">="&W1,'Checking Transaction Log'!$C:$C,"<="&X1,'Checking Transaction Log'!$A:$A,"D",'Checking Transaction Log'!$B:$B,3) -> 15.09 | X7: =H7-W7 -> 134.91 | Y7: =SUMIFS('Checking Transaction Log'!$E:$E,'Checking Transaction Log'!$C:$C,">="&Y1,'Checking Transaction Log'!$C:$C,"<="&Z1,'Checking Transaction Log'!$A:$A,"D",'Checking Transaction Log'!$B:$B,3) -> 110.24 | Z7: =H7-Y7 -> 39.76 | AA7: =SUMIFS('Checking Transaction Log'!$E:$E,'Checking Transaction Log'!$C:$C,">="&AA1,'Checking Transaction Log'!$C:$C,"<="&AB1,'Checking Transaction Log'!$A:$A,"D",'Checking Transaction Log'!$B:$B,3) -> 65.38 | AB7: =H7-AA7 -> 84.62 | AC7: =SUMIFS('Checking Transaction Log'!$E:$E,'Checking Transaction Log'!$C:$C,">="&AC1,'Checking Transaction Log'!$C:$C,"<="&AD1,'Checking Transaction Log'!$A:$A,"D",'Checking Transaction Log'!$B:$B,3) -> 0 | AD7: =H7-AC7 -> 150 | AE7: =SUMIFS('Checking Transaction Log'!$E:$E,'Checking Transaction Log'!$C:$C,">="&AE1,'Checking Transaction Log'!$C:$C,"<="&AF1,'Checking Transaction Log'!$A:$A,"D",'Checking Transaction Log'!$B:$B,3) -> 0 | AF7: =H7-AE7 -> 150
A8: ='Proposed Budget'!A8 -> D | B8: ='Proposed Budget'!B8 -> 4 | C8: ='Proposed Budget'!C8 -> Gasoline | D8: =(E8/(TODAY()-$I$1))*30.42 -> 648.42807 | E8: =Q8+S8+U8+W8+Y8+AA8+AC8+AE8+I8+K8+M8+O8 -> 6416.07 | F8: =J8+L8+N8+P8+R8+T8+V8+X8+Z8+AB8 -> -416.07 | G8: =1-((E8/SUM(E8:F8))) -> -0.069345 | H8: ='Proposed Budget'!D8 -> 600 | I8: =SUMIFS('Checking Transaction Log'!E:E,'Checking Transaction Log'!C:C,">="&I1,'Checking Transaction Log'!C:C,"<="&J1,'Checking Transaction Log'!A:A,"D",'Checking Transaction Log'!B:B,4) -> 561.41 | J8: =H8-I8 -> 38.59 | K8: =SUMIFS('Checking Transaction Log'!E:E,'Checking Transaction Log'!C:C,">="&K1,'Checking Transaction Log'!C:C,"<="&L1,'Checking Transaction Log'!A:A,"D",'Checking Transaction Log'!B:B,4) -> 710.78 | L8: =H8-K8 -> -110.78 | M8: =SUMIFS('Checking Transaction Log'!$E:$E,'Checking Transaction Log'!$C:$C,">="&M1,'Checking Transaction Log'!$C:$C,"<="&N1,'Checking Transaction Log'!$A:$A,"D",'Checking Transaction Log'!$B:$B,4) -> 537.41 | N8: =H8-M8 -> 62.59 | O8: =SUMIFS('Checking Transaction Log'!$E:$E,'Checking Transaction Log'!$C:$C,">="&O1,'Checking Transaction Log'!$C:$C,"<="&P1,'Checking Transaction Log'!$A:$A,"D",'Checking Transaction Log'!$B:$B,4) -> 592.33 | P8: =H8-O8 -> 7.67 | Q8: =SUMIFS('Checking Transaction Log'!$E:$E,'Checking Transaction Log'!$C:$C,">="&Q1,'Checking Transaction Log'!$C:$C,"<="&R1,'Checking Transaction Log'!$A:$A,"D",'Checking Transaction Log'!$B:$B,4) -> 942.96 | R8: =H8-Q8 -> -342.96 | S8: =SUMIFS('Checking Transaction Log'!$E:$E,'Checking Transaction Log'!$C:$C,">="&S1,'Checking Transaction Log'!$C:$C,"<="&T1,'Checking Transaction Log'!$A:$A,"D",'Checking Transaction Log'!$B:$B,4) -> 548.34 | T8: =H8-S8 -> 51.66 | U8: =SUMIFS('Checking Transaction Log'!$E:$E,'Checking Transaction Log'!$C:$C,">="&U1,'Checking Transaction Log'!$C:$C,"<="&V1,'Checking Transaction Log'!$A:$A,"D",'Checking Transaction Log'!$B:$B,4) -> 604.87 | V8: =H8-U8 -> -4.87 | W8: =SUMIFS('Checking Transaction Log'!$E:$E,'Checking Transaction Log'!$C:$C,">="&W1,'Checking Transaction Log'!$C:$C,"<="&X1,'Checking Transaction Log'!$A:$A,"D",'Checking Transaction Log'!$B:$B,4) -> 475.49 | X8: =H8-W8 -> 124.51 | Y8: =SUMIFS('Checking Transaction Log'!$E:$E,'Checking Transaction Log'!$C:$C,">="&Y1,'Checking Transaction Log'!$C:$C,"<="&Z1,'Checking Transaction Log'!$A:$A,"D",'Checking Transaction Log'!$B:$B,4) -> 770.33 | Z8: =H8-Y8 -> -170.33 | AA8: =SUMIFS('Checking Transaction Log'!$E:$E,'Checking Transaction Log'!$C:$C,">="&AA1,'Checking Transaction Log'!$C:$C,"<="&AB1,'Checking Transaction Log'!$A:$A,"D",'Checking Transaction Log'!$B:$B,4) -> 672.15 | AB8: =H8-AA8 -> -72.15 | AC8: =SUMIFS('Checking Transaction Log'!$E:$E,'Checking Transaction Log'!$C:$C,">="&AC1,'Checking Transaction Log'!$C:$C,"<="&AD1,'Checking Transaction Log'!$A:$A,"D",'Checking Transaction Log'!$B:$B,4) -> 0 | AD8: =H8-AC8 -> 600 | AE8: =SUMIFS('Checking Transaction Log'!$E:$E,'Checking Transaction Log'!$C:$C,">="&AE1,'Checking Transaction Log'!$C:$C,"<="&AF1,'Checking Transaction Log'!$A:$A,"D",'Checking Transaction Log'!$B:$B,4) -> 0 | AF8: =H8-AE8 -> 600
A9: ='Proposed Budget'!A9 -> D | B9: ='Proposed Budget'!B9 -> 5 | C9: ='Proposed Budget'!C9 -> Family Entertainment | D9: =(E9/(TODAY()-$I$1))*30.42 -> 809.43173 | E9: =Q9+S9+U9+W9+Y9+AA9+AC9+AE9+I9+K9+M9+O9 -> 8009.17 | F9: =J9+L9+N9+P9+R9+T9+V9+X9+Z9+AB9 -> -1009.17 | G9: =1-((E9/SUM(E9:F9))) -> -0.14416714 | H9: ='Proposed Budget'!D9 -> 700 | I9: =SUMIFS('Checking Transaction Log'!E:E,'Checking Transaction Log'!C:C,">="&I1,'Checking Transaction Log'!C:C,"<="&J1,'Checking Transaction Log'!A:A,"D",'Checking Transaction Log'!B:B,5) -> 717.1 | J9: =H9-I9 -> -17.1 | K9: =SUMIFS('Checking Transaction Log'!E:E,'Checking Transaction Log'!C:C,">="&K1,'Checking Transaction Log'!C:C,"<="&L1,'Checking Transaction Log'!A:A,"D",'Checking Transaction Log'!B:B,5) -> 780.14 | L9: =H9-K9 -> -80.14 | M9: =SUMIFS('Checking Transaction Log'!$E:$E,'Checking Transaction Log'!$C:$C,">="&M1,'Checking Transaction Log'!$C:$C,"<="&N1,'Checking Transaction Log'!$A:$A,"D",'Checking Transaction Log'!$B:$B,5) -> 516.79 | N9: =H9-M9 -> 183.21 | O9: =SUMIFS('Checking Transaction Log'!$E:$E,'Checking Transaction Log'!$C:$C,">="&O1,'Checking Transaction Log'!$C:$C,"<="&P1,'Checking Transaction Log'!$A:$A,"D",'Checking Transaction Log'!$B:$B,5) -> 1673.98 | P9: =H9-O9 -> -973.98 | Q9: =SUMIFS('Checking Transaction Log'!$E:$E,'Checking Transaction Log'!$C:$C,">="&Q1,'Checking Transaction Log'!$C:$C,"<="&R1,'Checking Transaction Log'!$A:$A,"D",'Checking Transaction Log'!$B:$B,5) -> 310.77 | R9: =H9-Q9 -> 389.23 | S9: =SUMIFS('Checking Transaction Log'!$E:$E,'Checking Transaction Log'!$C:$C,">="&S1,'Checking Transaction Log'!$C:$C,"<="&T1,'Checking Transaction Log'!$A:$A,"D",'Checking Transaction Log'!$B:$B,5) -> 236.03 | T9: =H9-S9 -> 463.97 | U9: =SUMIFS('Checking Transaction Log'!$E:$E,'Checking Transaction Log'!$C:$C,">="&U1,'Checking Transaction Log'!$C:$C,"<="&V1,'Checking Transaction Log'!$A:$A,"D",'Checking Transaction Log'!$B:$B,5) -> 530.84 | V9: =H9-U9 -> 169.16 | W9: =SUMIFS('Checking Transaction Log'!$E:$E,'Checking Transaction Log'!$C:$C,">="&W1,'Checking Transaction Log'!$C:$C,"<="&X1,'Checking Transaction Log'!$A:$A,"D",'Checking Transaction Log'!$B:$B,5) -> 377.12 | X9: =H9-W9 -> 322.88 | Y9: =SUMIFS('Checking Transaction Log'!$E:$E,'Checking Transaction Log'!$C:$C,">="&Y1,'Checking Transaction Log'!$C:$C,"<="&Z1,'Checking Transaction Log'!$A:$A,"D",'Checking Transaction Log'!$B:$B,5) -> 1921.67 | Z9: =H9-Y9 -> -1221.67 | AA9: =SUMIFS('Checking Transaction Log'!$E:$E,'Checking Transaction Log'!$C:$C,">="&AA1,'Checking Transaction Log'!$C:$C,"<="&AB1,'Checking Transaction Log'!$A:$A,"D",'Checking Transaction Log'!$B:$B,5) -> 944.73 | AB9: =H9-AA9 -> -244.73 | AC9: =SUMIFS('Checking Transaction Log'!$E:$E,'Checking Transaction Log'!$C:$C,">="&AC1,'Checking Transaction Log'!$C:$C,"<="&AD1,'Checking Transaction Log'!$A:$A,"D",'Checking Transaction Log'!$B:$B,5) -> 0 | AD9: =H9-AC9 -> 700 | AE9: =SUMIFS('Checking Transaction Log'!$E:$E,'Checking Transaction Log'!$C:$C,">="&AE1,'Checking Transaction Log'!$C:$C,"<="&AF1,'Checking Transaction Log'!$A:$A,"D",'Checking Transaction Log'!$B:$B,5) -> 0 | AF9: =H9-AE9 -> 700
A10: ='Proposed Budget'!A10 -> D | B10: ='Proposed Budget'!B10 -> 6 | C10: ='Proposed Budget'!C10 -> Miscellaneous Spending | D10: =(E10/(TODAY()-$I$1))*30.42 -> 858.60298 | E10: =Q10+S10+U10+W10+Y10+AA10+AC10+AE10+I10+K10+M10+O10 -> 8495.71 | F10: =J10+L10+N10+P10+R10+T10+V10+X10+Z10+AB10 -> 504.29 | G10: =1-((E10/SUM(E10:F10))) -> 0.056032222 | H10: ='Proposed Budget'!D10 -> 900 | I10: =SUMIFS('Checking Transaction Log'!E:E,'Checking Transaction Log'!C:C,">="&I1,'Checking Transaction Log'!C:C,"<="&J1,'Checking Transaction Log'!A:A,"D",'Checking Transaction Log'!B:B,6) -> 714.12 | J10: =H10-I10 -> 185.88 | K10: =SUMIFS('Checking Transaction Log'!E:E,'Checking Transaction Log'!C:C,">="&K1,'Checking Transaction Log'!C:C,"<="&L1,'Checking Transaction Log'!A:A,"D",'Checking Transaction Log'!B:B,6) -> 693.08 | L10: =H10-K10 -> 206.92 | M10: =SUMIFS('Checking Transaction Log'!$E:$E,'Checking Transaction Log'!$C:$C,">="&M1,'Checking Transaction Log'!$C:$C,"<="&N1,'Checking Transaction Log'!$A:$A,"D",'Checking Transaction Log'!$B:$B,6) -> 484.7 | N10: =H10-M10 -> 415.3 | O10: =SUMIFS('Checking Transaction Log'!$E:$E,'Checking Transaction Log'!$C:$C,">="&O1,'Checking Transaction Log'!$C:$C,"<="&P1,'Checking Transaction Log'!$A:$A,"D",'Checking Transaction Log'!$B:$B,6) -> 1146.79 | P10: =H10-O10 -> -246.79 | Q10: =SUMIFS('Checking Transaction Log'!$E:$E,'Checking Transaction Log'!$C:$C,">="&Q1,'Checking Transaction Log'!$C:$C,"<="&R1,'Checking Transaction Log'!$A:$A,"D",'Checking Transaction Log'!$B:$B,6) -> 1049.97 | R10: =H10-Q10 -> -149.97 | S10: =SUMIFS('Checking Transaction Log'!$E:$E,'Checking Transaction Log'!$C:$C,">="&S1,'Checking Transaction Log'!$C:$C,"<="&T1,'Checking Transaction Log'!$A:$A,"D",'Checking Transaction Log'!$B:$B,6) -> 717.77 | T10: =H10-S10 -> 182.23 | U10: =SUMIFS('Checking Transaction Log'!$E:$E,'Checking Transaction Log'!$C:$C,">="&U1,'Checking Transaction Log'!$C:$C,"<="&V1,'Checking Transaction Log'!$A:$A,"D",'Checking Transaction Log'!$B:$B,6) -> 707.58 | V10: =H10-U10 -> 192.42 | W10: =SUMIFS('Checking Transaction Log'!$E:$E,'Checking Transaction Log'!$C:$C,">="&W1,'Checking Transaction Log'!$C:$C,"<="&X1,'Checking Transaction Log'!$A:$A,"D",'Checking Transaction Log'!$B:$B,6) -> 777.34 | X10: =H10-W10 -> 122.66 | Y10: =SUMIFS('Checking Transaction Log'!$E:$E,'Checking Transaction Log'!$C:$C,">="&Y1,'Checking Transaction Log'!$C:$C,"<="&Z1,'Checking Transaction Log'!$A:$A,"D",'Checking Transaction Log'!$B:$B,6) -> 1024.61 | Z10: =H10-Y10 -> -124.61 | AA10: =SUMIFS('Checking Transaction Log'!$E:$E,'Checking Transaction Log'!$C:$C,">="&AA1,'Checking Transaction Log'!$C:$C,"<="&AB1,'Checking Transaction Log'!$A:$A,"D",'Checking Transaction Log'!$B:$B,6) -> 1179.75 | AB10: =H10-AA10 -> -279.75 | AC10: =SUMIFS('Checking Transaction Log'!$E:$E,'Checking Transaction Log'!$C:$C,">="&AC1,'Checking Transaction Log'!$C:$C,"<="&AD1,'Checking Transaction Log'!$A:$A,"D",'Checking Transaction Log'!$B:$B,6) -> 0 | AD10: =H10-AC10 -> 900 | AE10: =SUMIFS('Checking Transaction Log'!$E:$E,'Checking Transaction Log'!$C:$C,">="&AE1,'Checking Transaction Log'!$C:$C,"<="&AF1,'Checking Transaction Log'!$A:$A,"D",'Checking Transaction Log'!$B:$B,6) -> 0 | AF10: =H10-AE10 -> 900
A11: ='Proposed Budget'!A11 -> D | B11: ='Proposed Budget'!B11 -> 7 | C11: ='Proposed Budget'!C11 -> Department Stores/Clothes | D11: =(E11/(TODAY()-$I$1))*30.42 -> 294.20991 | E11: =Q11+S11+U11+W11+Y11+AA11+AC11+AE11+I11+K11+M11+O11 -> 2911.15 | F11: =J11+L11+N11+P11+R11+T11+V11+X11+Z11+AB11 -> 588.85 | G11: =1-((E11/SUM(E11:F11))) -> 0.16824286 | H11: ='Proposed Budget'!D11 -> 350 | I11: =SUMIFS('Checking Transaction Log'!E:E,'Checking Transaction Log'!C:C,">="&I1,'Checking Transaction Log'!C:C,"<="&J1,'Checking Transaction Log'!A:A,"D",'Checking Transaction Log'!B:B,7) -> 626.04 | J11: =H11-I11 -> -276.04 | K11: =SUMIFS('Checking Transaction Log'!E:E,'Checking Transaction Log'!C:C,">="&K1,'Checking Transaction Log'!C:C,"<="&L1,'Checking Transaction Log'!A:A,"D",'Checking Transaction Log'!B:B,7) -> 670.18 | L11: =H11-K11 -> -320.18 | M11: =SUMIFS('Checking Transaction Log'!$E:$E,'Checking Transaction Log'!$C:$C,">="&M1,'Checking Transaction Log'!$C:$C,"<="&N1,'Checking Transaction Log'!$A:$A,"D",'Checking Transaction Log'!$B:$B,7) -> 221.65 | N11: =H11-M11 -> 128.35 | O11: =SUMIFS('Checking Transaction Log'!$E:$E,'Checking Transaction Log'!$C:$C,">="&O1,'Checking Transaction Log'!$C:$C,"<="&P1,'Checking Transaction Log'!$A:$A,"D",'Checking Transaction Log'!$B:$B,7) -> 269.88 | P11: =H11-O11 -> 80.12 | Q11: =SUMIFS('Checking Transaction Log'!$E:$E,'Checking Transaction Log'!$C:$C,">="&Q1,'Checking Transaction Log'!$C:$C,"<="&R1,'Checking Transaction Log'!$A:$A,"D",'Checking Transaction Log'!$B:$B,7) -> 376.41 | R11: =H11-Q11 -> -26.41 | S11: =SUMIFS('Checking Transaction Log'!$E:$E,'Checking Transaction Log'!$C:$C,">="&S1,'Checking Transaction Log'!$C:$C,"<="&T1,'Checking Transaction Log'!$A:$A,"D",'Checking Transaction Log'!$B:$B,7) -> 0 | T11: =H11-S11 -> 350 | U11: =SUMIFS('Checking Transaction Log'!$E:$E,'Checking Transaction Log'!$C:$C,">="&U1,'Checking Transaction Log'!$C:$C,"<="&V1,'Checking Transaction Log'!$A:$A,"D",'Checking Transaction Log'!$B:$B,7) -> 0 | V11: =H11-U11 -> 350 | W11: =SUMIFS('Checking Transaction Log'!$E:$E,'Checking Transaction Log'!$C:$C,">="&W1,'Checking Transaction Log'!$C:$C,"<="&X1,'Checking Transaction Log'!$A:$A,"D",'Checking Transaction Log'!$B:$B,7) -> 374.35 | X11: =H11-W11 -> -24.35 | Y11: =SUMIFS('Checking Transaction Log'!$E:$E,'Checking Transaction Log'!$C:$C,">="&Y1,'Checking Transaction Log'!$C:$C,"<="&Z1,'Checking Transaction Log'!$A:$A,"D",'Checking Transaction Log'!$B:$B,7) -> 252.08 | Z11: =H11-Y11 -> 97.92 | AA11: =SUMIFS('Checking Transaction Log'!$E:$E,'Checking Transaction Log'!$C:$C,">="&AA1,'Checking Transaction Log'!$C:$C,"<="&AB1,'Checking Transaction Log'!$A:$A,"D",'Checking Transaction Log'!$B:$B,7) -> 120.56 | AB11: =H11-AA11 -> 229.44 | AC11: =SUMIFS('Checking Transaction Log'!$E:$E,'Checking Transaction Log'!$C:$C,">="&AC1,'Checking Transaction Log'!$C:$C,"<="&AD1,'Checking Transaction Log'!$A:$A,"D",'Checking Transaction Log'!$B:$B,7) -> 0 | AD11: =H11-AC11 -> 350 | AE11: =SUMIFS('Checking Transaction Log'!$E:$E,'Checking Transaction Log'!$C:$C,">="&AE1,'Checking Transaction Log'!$C:$C,"<="&AF1,'Checking Transaction Log'!$A:$A,"D",'Checking Transaction Log'!$B:$B,7) -> 0 | AF11: =H11-AE11 -> 350
A12: ='Proposed Budget'!A12 -> D | B12: ='Proposed Budget'!B12 -> 8 | C12: ='Proposed Budget'!C12 -> Alcohol/Bars | D12: =(E12/(TODAY()-$I$1))*30.42 -> 742.56837 | E12: =Q12+S12+U12+W12+Y12+AA12+AC12+AE12+I12+K12+M12+O12 -> 7347.57 | F12: =J12+L12+N12+P12+R12+T12+V12+X12+Z12+AB12 -> -347.57 | G12: =1-((E12/SUM(E12:F12))) -> -0.049652857 | H12: ='Proposed Budget'!D12 -> 700 | I12: =SUMIFS('Checking Transaction Log'!E:E,'Checking Transaction Log'!C:C,">="&I1,'Checking Transaction Log'!C:C,"<="&J1,'Checking Transaction Log'!A:A,"D",'Checking Transaction Log'!B:B,8) -> 683.49 | J12: =H12-I12 -> 16.51 | K12: =SUMIFS('Checking Transaction Log'!E:E,'Checking Transaction Log'!C:C,">="&K1,'Checking Transaction Log'!C:C,"<="&L1,'Checking Transaction Log'!A:A,"D",'Checking Transaction Log'!B:B,8) -> 979.71 | L12: =H12-K12 -> -279.71 | M12: =SUMIFS('Checking Transaction Log'!$E:$E,'Checking Transaction Log'!$C:$C,">="&M1,'Checking Transaction Log'!$C:$C,"<="&N1,'Checking Transaction Log'!$A:$A,"D",'Checking Transaction Log'!$B:$B,8) -> 640.42 | N12: =H12-M12 -> 59.58 | O12: =SUMIFS('Checking Transaction Log'!$E:$E,'Checking Transaction Log'!$C:$C,">="&O1,'Checking Transaction Log'!$C:$C,"<="&P1,'Checking Transaction Log'!$A:$A,"D",'Checking Transaction Log'!$B:$B,8) -> 654.01 | P12: =H12-O12 -> 45.99 | Q12: =SUMIFS('Checking Transaction Log'!$E:$E,'Checking Transaction Log'!$C:$C,">="&Q1,'Checking Transaction Log'!$C:$C,"<="&R1,'Checking Transaction Log'!$A:$A,"D",'Checking Transaction Log'!$B:$B,8) -> 972.26 | R12: =H12-Q12 -> -272.26 | S12: =SUMIFS('Checking Transaction Log'!$E:$E,'Checking Transaction Log'!$C:$C,">="&S1,'Checking Transaction Log'!$C:$C,"<="&T1,'Checking Transaction Log'!$A:$A,"D",'Checking Transaction Log'!$B:$B,8) -> 617.53 | T12: =H12-S12 -> 82.47 | U12: =SUMIFS('Checking Transaction Log'!$E:$E,'Checking Transaction Log'!$C:$C,">="&U1,'Checking Transaction Log'!$C:$C,"<="&V1,'Checking Transaction Log'!$A:$A,"D",'Checking Transaction Log'!$B:$B,8) -> 925.98 | V12: =H12-U12 -> -225.98 | W12: =SUMIFS('Checking Transaction Log'!$E:$E,'Checking Transaction Log'!$C:$C,">="&W1,'Checking Transaction Log'!$C:$C,"<="&X1,'Checking Transaction Log'!$A:$A,"D",'Checking Transaction Log'!$B:$B,8) -> 796.96 | X12: =H12-W12 -> -96.96 | Y12: =SUMIFS('Checking Transaction Log'!$E:$E,'Checking Transaction Log'!$C:$C,">="&Y1,'Checking Transaction Log'!$C:$C,"<="&Z1,'Checking Transaction Log'!$A:$A,"D",'Checking Transaction Log'!$B:$B,8) -> 464.71 | Z12: =H12-Y12 -> 235.29 | AA12: =SUMIFS('Checking Transaction Log'!$E:$E,'Checking Transaction Log'!$C:$C,">="&AA1,'Checking Transaction Log'!$C:$C,"<="&AB1,'Checking Transaction Log'!$A:$A,"D",'Checking Transaction Log'!$B:$B,8) -> 612.5 | AB12: =H12-AA12 -> 87.5 | AC12: =SUMIFS('Checking Transaction Log'!$E:$E,'Checking Transaction Log'!$C:$C,">="&AC1,'Checking Transaction Log'!$C:$C,"<="&AD1,'Checking Transaction Log'!$A:$A,"D",'Checking Transaction Log'!$B:$B,8) -> 0 | AD12: =H12-AC12 -> 700 | AE12: =SUMIFS('Checking Transaction Log'!$E:$E,'Checking Transaction Log'!$C:$C,">="&AE1,'Checking Transaction Log'!$C:$C,"<="&AF1,'Checking Transaction Log'!$A:$A,"D",'Checking Transaction Log'!$B:$B,8) -> 0 | AF12: =H12-AE12 -> 700
A14: ='Proposed Budget'!A14 -> F | B14: ='Proposed Budget'!B14 -> 9 | C14: ='Proposed Budget'!C14 -> Rocket Mortgage | D14: =(E14/(TODAY()-$I$1))*30.42 -> 1264.9263 | E14: =Q14+S14+U14+W14+Y14+AA14+AC14+AE14+I14+K14+M14+O14 -> 12516.2 | F14: =J14+L14+N14+P14+R14+T14+V14+X14+Z14+AB14 -> 333.8 | G14: =1-((E14/SUM(E14:F14))) -> 0.025976654 | H14: ='Proposed Budget'!D14 -> 1285 | I14: =SUMIFS('Checking Transaction Log'!E:E,'Checking Transaction Log'!C:C,">="&I1,'Checking Transaction Log'!C:C,"<="&J1,'Checking Transaction Log'!A:A,"F",'Checking Transaction Log'!B:B,9) -> 1281.53 | J14: =H14-I14 -> 3.47 | K14: =SUMIFS('Checking Transaction Log'!E:E,'Checking Transaction Log'!C:C,">="&K1,'Checking Transaction Log'!C:C,"<="&L1,'Checking Transaction Log'!A:A,"F",'Checking Transaction Log'!B:B,9) -> 1281.53 | L14: =H14-K14 -> 3.47 | M14: =SUMIFS('Checking Transaction Log'!$E:$E,'Checking Transaction Log'!$C:$C,">="&M1,'Checking Transaction Log'!$C:$C,"<="&N1,'Checking Transaction Log'!$A:$A,"F",'Checking Transaction Log'!$B:$B,9) -> 1281.53 | N14: =H14-M14 -> 3.47 | O14: =SUMIFS('Checking Transaction Log'!$E:$E,'Checking Transaction Log'!$C:$C,">="&O1,'Checking Transaction Log'!$C:$C,"<="&P1,'Checking Transaction Log'!$A:$A,"F",'Checking Transaction Log'!$B:$B,9) -> 1281.53 | P14: =H14-O14 -> 3.47 | Q14: =SUMIFS('Checking Transaction Log'!$E:$E,'Checking Transaction Log'!$C:$C,">="&Q1,'Checking Transaction Log'!$C:$C,"<="&R1,'Checking Transaction Log'!$A:$A,"F",'Checking Transaction Log'!$B:$B,9) -> 1231.68 | R14: =H14-Q14 -> 53.32 | S14: =SUMIFS('Checking Transaction Log'!$E:$E,'Checking Transaction Log'!$C:$C,">="&S1,'Checking Transaction Log'!$C:$C,"<="&T1,'Checking Transaction Log'!$A:$A,"F",'Checking Transaction Log'!$B:$B,9) -> 1231.68 | T14: =H14-S14 -> 53.32 | U14: =SUMIFS('Checking Transaction Log'!$E:$E,'Checking Transaction Log'!$C:$C,">="&U1,'Checking Transaction Log'!$C:$C,"<="&V1,'Checking Transaction Log'!$A:$A,"F",'Checking Transaction Log'!$B:$B,9) -> 1231.68 | V14: =H14-U14 -> 53.32 | W14: =SUMIFS('Checking Transaction Log'!$E:$E,'Checking Transaction Log'!$C:$C,">="&W1,'Checking Transaction Log'!$C:$C,"<="&X1,'Checking Transaction Log'!$A:$A,"F",'Checking Transaction Log'!$B:$B,9) -> 1231.68 | X14: =H14-W14 -> 53.32 | Y14: =SUMIFS('Checking Transaction Log'!$E:$E,'Checking Transaction Log'!$C:$C,">="&Y1,'Checking Transaction Log'!$C:$C,"<="&Z1,'Checking Transaction Log'!$A:$A,"F",'Checking Transaction Log'!$B:$B,9) -> 1231.68 | Z14: =H14-Y14 -> 53.32 | AA14: =SUMIFS('Checking Transaction Log'!$E:$E,'Checking Transaction Log'!$C:$C,">="&AA1,'Checking Transaction Log'!$C:$C,"<="&AB1,'Checking Transaction Log'!$A:$A,"F",'Checking Transaction Log'!$B:$B,9) -> 1231.68 | AB14: =H14-AA14 -> 53.32 | AC14: =SUMIFS('Checking Transaction Log'!$E:$E,'Checking Transaction Log'!$C:$C,">="&AC1,'Checking Transaction Log'!$C:$C,"<="&AD1,'Checking Transaction Log'!$A:$A,"F",'Checking Transaction Log'!$B:$B,9) -> 0 | AD14: =H14-AC14 -> 1285 | AE14: =SUMIFS('Checking Transaction Log'!$E:$E,'Checking Transaction Log'!$C:$C,">="&AE1,'Checking Transaction Log'!$C:$C,"<="&AF1,'Checking Transaction Log'!$A:$A,"F",'Checking Transaction Log'!$B:$B,9) -> 0 | AF14: =H14-AE14 -> 1285
A15: ='Proposed Budget'!A15 -> F | B15: ='Proposed Budget'!B15 -> 10 | C15: ='Proposed Budget'!C15 -> EH Roberts | D15: =(E15/(TODAY()-$I$1))*30.42 -> 16.281269 | E15: =Q15+S15+U15+W15+Y15+AA15+AC15+AE15+I15+K15+M15+O15 -> 161.1 | F15: =J15+L15+N15+P15+R15+T15+V15+X15+Z15+AB15 -> 38.9 | G15: =1-((E15/SUM(E15:F15))) -> 0.1945 | H15: ='Proposed Budget'!D15 -> 20 | I15: =SUMIFS('Checking Transaction Log'!E:E,'Checking Transaction Log'!C:C,">="&I1,'Checking Transaction Log'!C:C,"<="&J1,'Checking Transaction Log'!A:A,"F",'Checking Transaction Log'!B:B,10) -> 17.9 | J15: =H15-I15 -> 2.1 | K15: =SUMIFS('Checking Transaction Log'!E:E,'Checking Transaction Log'!C:C,">="&K1,'Checking Transaction Log'!C:C,"<="&L1,'Checking Transaction Log'!A:A,"F",'Checking Transaction Log'!B:B,10) -> 17.9 | L15: =H15-K15 -> 2.1 | M15: =SUMIFS('Checking Transaction Log'!$E:$E,'Checking Transaction Log'!$C:$C,">="&M1,'Checking Transaction Log'!$C:$C,"<="&N1,'Checking Transaction Log'!$A:$A,"F",'Checking Transaction Log'!$B:$B,10) -> 17.9 | N15: =H15-M15 -> 2.1 | O15: =SUMIFS('Checking Transaction Log'!$E:$E,'Checking Transaction Log'!$C:$C,">="&O1,'Checking Transaction Log'!$C:$C,"<="&P1,'Checking Transaction Log'!$A:$A,"F",'Checking Transaction Log'!$B:$B,10) -> 17.9 | P15: =H15-O15 -> 2.1 | Q15: =SUMIFS('Checking Transaction Log'!$E:$E,'Checking Transaction Log'!$C:$C,">="&Q1,'Checking Transaction Log'!$C:$C,"<="&R1,'Checking Transaction Log'!$A:$A,"F",'Checking Transaction Log'!$B:$B,10) -> 17.9 | R15: =H15-Q15 -> 2.1 | S15: =SUMIFS('Checking Transaction Log'!$E:$E,'Checking Transaction Log'!$C:$C,">="&S1,'Checking Transaction Log'!$C:$C,"<="&T1,'Checking Transaction Log'!$A:$A,"F",'Checking Transaction Log'!$B:$B,10) -> 17.9 | T15: =H15-S15 -> 2.1 | U15: =SUMIFS('Checking Transaction Log'!$E:$E,'Checking Transaction Log'!$C:$C,">="&U1,'Checking Transaction Log'!$C:$C,"<="&V1,'Checking Transaction Log'!$A:$A,"F",'Checking Transaction Log'!$B:$B,10) -> 17.9 | V15: =H15-U15 -> 2.1 | W15: =SUMIFS('Checking Transaction Log'!$E:$E,'Checking Transaction Log'!$C:$C,">="&W1,'Checking Transaction Log'!$C:$C,"<="&X1,'Checking Transaction Log'!$A:$A,"F",'Checking Transaction Log'!$B:$B,10) -> 17.9 | X15: =H15-W15 -> 2.1 | Y15: =SUMIFS('Checking Transaction Log'!$E:$E,'Checking Transaction Log'!$C:$C,">="&Y1,'Checking Transaction Log'!$C:$C,"<="&Z1,'Checking Transaction Log'!$A:$A,"F",'Checking Transaction Log'!$B:$B,10) -> 17.9 | Z15: =H15-Y15 -> 2.1 | AA15: =SUMIFS('Checking Transaction Log'!$E:$E,'Checking Transaction Log'!$C:$C,">="&AA1,'Checking Transaction Log'!$C:$C,"<="&AB1,'Checking Transaction Log'!$A:$A,"F",'Checking Transaction Log'!$B:$B,10) -> 0 | AB15: =H15-AA15 -> 20 | AC15: =SUMIFS('Checking Transaction Log'!$E:$E,'Checking Transaction Log'!$C:$C,">="&AC1,'Checking Transaction Log'!$C:$C,"<="&AD1,'Checking Transaction Log'!$A:$A,"F",'Checking Transaction Log'!$B:$B,10) -> 0 | AD15: =H15-AC15 -> 20 | AE15: =SUMIFS('Checking Transaction Log'!$E:$E,'Checking Transaction Log'!$C:$C,">="&AE1,'Checking Transaction Log'!$C:$C,"<="&AF1,'Checking Transaction Log'!$A:$A,"F",'Checking Transaction Log'!$B:$B,10) -> 0 | AF15: =H15-AE15 -> 20
A16: ='Proposed Budget'!A16 -> F | B16: ='Proposed Budget'!B16 -> 11 | C16: ='Proposed Budget'!C16 -> Verizon Wireless | D16: =(E16/(TODAY()-$I$1))*30.42 -> 287.75501 | E16: =Q16+S16+U16+W16+Y16+AA16+AC16+AE16+I16+K16+M16+O16 -> 2847.28 | F16: =J16+L16+N16+P16+R16+T16+V16+X16+Z16+AB16 -> -147.28 | G16: =1-((E16/SUM(E16:F16))) -> -0.054548148 | H16: ='Proposed Budget'!D16 -> 270 | I16: =SUMIFS('Checking Transaction Log'!E:E,'Checking Transaction Log'!C:C,">="&I1,'Checking Transaction Log'!C:C,"<="&J1,'Checking Transaction Log'!A:A,"F",'Checking Transaction Log'!B:B,11) -> 267.96 | J16: =H16-I16 -> 2.04 | K16: =SUMIFS('Checking Transaction Log'!E:E,'Checking Transaction Log'!C:C,">="&K1,'Checking Transaction Log'!C:C,"<="&L1,'Checking Transaction Log'!A:A,"F",'Checking Transaction Log'!B:B,11) -> 480.91 | L16: =H16-K16 -> -210.91 | M16: =SUMIFS('Checking Transaction Log'!$E:$E,'Checking Transaction Log'!$C:$C,">="&M1,'Checking Transaction Log'!$C:$C,"<="&N1,'Checking Transaction Log'!$A:$A,"F",'Checking Transaction Log'!$B:$B,11) -> 267.91 | N16: =H16-M16 -> 2.09 | O16: =SUMIFS('Checking Transaction Log'!$E:$E,'Checking Transaction Log'!$C:$C,">="&O1,'Checking Transaction Log'!$C:$C,"<="&P1,'Checking Transaction Log'!$A:$A,"F",'Checking Transaction Log'!$B:$B,11) -> 267.91 | P16: =H16-O16 -> 2.09 | Q16: =SUMIFS('Checking Transaction Log'!$E:$E,'Checking Transaction Log'!$C:$C,">="&Q1,'Checking Transaction Log'!$C:$C,"<="&R1,'Checking Transaction Log'!$A:$A,"F",'Checking Transaction Log'!$B:$B,11) -> 267.68 | R16: =H16-Q16 -> 2.32 | S16: =SUMIFS('Checking Transaction Log'!$E:$E,'Checking Transaction Log'!$C:$C,">="&S1,'Checking Transaction Log'!$C:$C,"<="&T1,'Checking Transaction Log'!$A:$A,"F",'Checking Transaction Log'!$B:$B,11) -> 267.75 | T16: =H16-S16 -> 2.25 | U16: =SUMIFS('Checking Transaction Log'!$E:$E,'Checking Transaction Log'!$C:$C,">="&U1,'Checking Transaction Log'!$C:$C,"<="&V1,'Checking Transaction Log'!$A:$A,"F",'Checking Transaction Log'!$B:$B,11) -> 256.64 | V16: =H16-U16 -> 13.36 | W16: =SUMIFS('Checking Transaction Log'!$E:$E,'Checking Transaction Log'!$C:$C,">="&W1,'Checking Transaction Log'!$C:$C,"<="&X1,'Checking Transaction Log'!$A:$A,"F",'Checking Transaction Log'!$B:$B,11) -> 256.84 | X16: =H16-W16 -> 13.16 | Y16: =SUMIFS('Checking Transaction Log'!$E:$E,'Checking Transaction Log'!$C:$C,">="&Y1,'Checking Transaction Log'!$C:$C,"<="&Z1,'Checking Transaction Log'!$A:$A,"F",'Checking Transaction Log'!$B:$B,11) -> 256.84 | Z16: =H16-Y16 -> 13.16 | AA16: =SUMIFS('Checking Transaction Log'!$E:$E,'Checking Transaction Log'!$C:$C,">="&AA1,'Checking Transaction Log'!$C:$C,"<="&AB1,'Checking Transaction Log'!$A:$A,"F",'Checking Transaction Log'!$B:$B,11) -> 256.84 | AB16: =H16-AA16 -> 13.16 | AC16: =SUMIFS('Checking Transaction Log'!$E:$E,'Checking Transaction Log'!$C:$C,">="&AC1,'Checking Transaction Log'!$C:$C,"<="&AD1,'Checking Transaction Log'!$A:$A,"F",'Checking Transaction Log'!$B:$B,11) -> 0 | AD16: =H16-AC16 -> 270 | AE16: =SUMIFS('Checking Transaction Log'!$E:$E,'Checking Transaction Log'!$C:$C,">="&AE1,'Checking Transaction Log'!$C:$C,"<="&AF1,'Checking Transaction Log'!$A:$A,"F",'Checking Transaction Log'!$B:$B,11) -> 0 | AF16: =H16-AE16 -> 270
A17: ='Proposed Budget'!A17 -> F | B17: ='Proposed Budget'!B17 -> 12 | C17: ='Proposed Budget'!C17 -> Spectrum TV/Internet | D17: =(E17/(TODAY()-$I$1))*30.42 -> 209.79795 | E17: =Q17+S17+U17+W17+Y17+AA17+AC17+AE17+I17+K17+M17+O17 -> 2075.91 | F17: =J17+L17+N17+P17+R17+T17+V17+X17+Z17+AB17 -> -25.91 | G17: =1-((E17/SUM(E17:F17))) -> -0.012639024 | H17: ='Proposed Budget'!D17 -> 205 | I17: =SUMIFS('Checking Transaction Log'!E:E,'Checking Transaction Log'!C:C,">="&I1,'Checking Transaction Log'!C:C,"<="&J1,'Checking Transaction Log'!A:A,"F",'Checking Transaction Log'!B:B,12) -> 204.83 | J17: =H17-I17 -> 0.17 | K17: =SUMIFS('Checking Transaction Log'!E:E,'Checking Transaction Log'!C:C,">="&K1,'Checking Transaction Log'!C:C,"<="&L1,'Checking Transaction Log'!A:A,"F",'Checking Transaction Log'!B:B,12) -> 204.47 | L17: =H17-K17 -> 0.53 | M17: =SUMIFS('Checking Transaction Log'!$E:$E,'Checking Transaction Log'!$C:$C,">="&M1,'Checking Transaction Log'!$C:$C,"<="&N1,'Checking Transaction Log'!$A:$A,"F",'Checking Transaction Log'!$B:$B,12) -> 204.47 | N17: =H17-M17 -> 0.53 | O17: =SUMIFS('Checking Transaction Log'!$E:$E,'Checking Transaction Log'!$C:$C,">="&O1,'Checking Transaction Log'!$C:$C,"<="&P1,'Checking Transaction Log'!$A:$A,"F",'Checking Transaction Log'!$B:$B,12) -> 214.74 | P17: =H17-O17 -> -9.74 | Q17: =SUMIFS('Checking Transaction Log'!$E:$E,'Checking Transaction Log'!$C:$C,">="&Q1,'Checking Transaction Log'!$C:$C,"<="&R1,'Checking Transaction Log'!$A:$A,"F",'Checking Transaction Log'!$B:$B,12) -> 204.48 | R17: =H17-Q17 -> 0.52 | S17: =SUMIFS('Checking Transaction Log'!$E:$E,'Checking Transaction Log'!$C:$C,">="&S1,'Checking Transaction Log'!$C:$C,"<="&T1,'Checking Transaction Log'!$A:$A,"F",'Checking Transaction Log'!$B:$B,12) -> 204.48 | T17: =H17-S17 -> 0.52 | U17: =SUMIFS('Checking Transaction Log'!$E:$E,'Checking Transaction Log'!$C:$C,">="&U1,'Checking Transaction Log'!$C:$C,"<="&V1,'Checking Transaction Log'!$A:$A,"F",'Checking Transaction Log'!$B:$B,12) -> 204.48 | V17: =H17-U17 -> 0.52 | W17: =SUMIFS('Checking Transaction Log'!$E:$E,'Checking Transaction Log'!$C:$C,">="&W1,'Checking Transaction Log'!$C:$C,"<="&X1,'Checking Transaction Log'!$A:$A,"F",'Checking Transaction Log'!$B:$B,12) -> 225 | X17: =H17-W17 -> -20 | Y17: =SUMIFS('Checking Transaction Log'!$E:$E,'Checking Transaction Log'!$C:$C,">="&Y1,'Checking Transaction Log'!$C:$C,"<="&Z1,'Checking Transaction Log'!$A:$A,"F",'Checking Transaction Log'!$B:$B,12) -> 204.48 | Z17: =H17-Y17 -> 0.52 | AA17: =SUMIFS('Checking Transaction Log'!$E:$E,'Checking Transaction Log'!$C:$C,">="&AA1,'Checking Transaction Log'!$C:$C,"<="&AB1,'Checking Transaction Log'!$A:$A,"F",'Checking Transaction Log'!$B:$B,12) -> 204.48 | AB17: =H17-AA17 -> 0.52 | AC17: =SUMIFS('Checking Transaction Log'!$E:$E,'Checking Transaction Log'!$C:$C,">="&AC1,'Checking Transaction Log'!$C:$C,"<="&AD1,'Checking Transaction Log'!$A:$A,"F",'Checking Transaction Log'!$B:$B,12) -> 0 | AD17: =H17-AC17 -> 205 | AE17: =SUMIFS('Checking Transaction Log'!$E:$E,'Checking Transaction Log'!$C:$C,">="&AE1,'Checking Transaction Log'!$C:$C,"<="&AF1,'Checking Transaction Log'!$A:$A,"F",'Checking Transaction Log'!$B:$B,12) -> 0 | AF17: =H17-AE17 -> 205
A18: ='Proposed Budget'!A18 -> F | B18: ='Proposed Budget'!B18 -> 13 | C18: ='Proposed Budget'!C18 -> First Energy | D18: =(E18/(TODAY()-$I$1))*30.42 -> 208.79338 | E18: =Q18+S18+U18+W18+Y18+AA18+AC18+AE18+I18+K18+M18+O18 -> 2065.97 | F18: =J18+L18+N18+P18+R18+T18+V18+X18+Z18+AB18 -> -265.97 | G18: =1-((E18/SUM(E18:F18))) -> -0.14776111 | H18: ='Proposed Budget'!D18 -> 180 | I18: =SUMIFS('Checking Transaction Log'!E:E,'Checking Transaction Log'!C:C,">="&I1,'Checking Transaction Log'!C:C,"<="&J1,'Checking Transaction Log'!A:A,"F",'Checking Transaction Log'!B:B,13) -> 167.42 | J18: =H18-I18 -> 12.58 | K18: =SUMIFS('Checking Transaction Log'!E:E,'Checking Transaction Log'!C:C,">="&K1,'Checking Transaction Log'!C:C,"<="&L1,'Checking Transaction Log'!A:A,"F",'Checking Transaction Log'!B:B,13) -> 159.35 | L18: =H18-K18 -> 20.65 | M18: =SUMIFS('Checking Transaction Log'!$E:$E,'Checking Transaction Log'!$C:$C,">="&M1,'Checking Transaction Log'!$C:$C,"<="&N1,'Checking Transaction Log'!$A:$A,"F",'Checking Transaction Log'!$B:$B,13) -> 134.93 | N18: =H18-M18 -> 45.07 | O18: =SUMIFS('Checking Transaction Log'!$E:$E,'Checking Transaction Log'!$C:$C,">="&O1,'Checking Transaction Log'!$C:$C,"<="&P1,'Checking Transaction Log'!$A:$A,"F",'Checking Transaction Log'!$B:$B,13) -> 104.98 | P18: =H18-O18 -> 75.02 | Q18: =SUMIFS('Checking Transaction Log'!$E:$E,'Checking Transaction Log'!$C:$C,">="&Q1,'Checking Transaction Log'!$C:$C,"<="&R1,'Checking Transaction Log'!$A:$A,"F",'Checking Transaction Log'!$B:$B,13) -> 122.18 | R18: =H18-Q18 -> 57.82 | S18: =SUMIFS('Checking Transaction Log'!$E:$E,'Checking Transaction Log'!$C:$C,">="&S1,'Checking Transaction Log'!$C:$C,"<="&T1,'Checking Transaction Log'!$A:$A,"F",'Checking Transaction Log'!$B:$B,13) -> 122.46 | T18: =H18-S18 -> 57.54 | U18: =SUMIFS('Checking Transaction Log'!$E:$E,'Checking Transaction Log'!$C:$C,">="&U1,'Checking Transaction Log'!$C:$C,"<="&V1,'Checking Transaction Log'!$A:$A,"F",'Checking Transaction Log'!$B:$B,13) -> 218.33 | V18: =H18-U18 -> -38.33 | W18: =SUMIFS('Checking Transaction Log'!$E:$E,'Checking Transaction Log'!$C:$C,">="&W1,'Checking Transaction Log'!$C:$C,"<="&X1,'Checking Transaction Log'!$A:$A,"F",'Checking Transaction Log'!$B:$B,13) -> 331.81 | X18: =H18-W18 -> -151.81 | Y18: =SUMIFS('Checking Transaction Log'!$E:$E,'Checking Transaction Log'!$C:$C,">="&Y1,'Checking Transaction Log'!$C:$C,"<="&Z1,'Checking Transaction Log'!$A:$A,"F",'Checking Transaction Log'!$B:$B,13) -> 344.23 | Z18: =H18-Y18 -> -164.23 | AA18: =SUMIFS('Checking Transaction Log'!$E:$E,'Checking Transaction Log'!$C:$C,">="&AA1,'Checking Transaction Log'!$C:$C,"<="&AB1,'Checking Transaction Log'!$A:$A,"F",'Checking Transaction Log'!$B:$B,13) -> 360.28 | AB18: =H18-AA18 -> -180.28 | AC18: =SUMIFS('Checking Transaction Log'!$E:$E,'Checking Transaction Log'!$C:$C,">="&AC1,'Checking Transaction Log'!$C:$C,"<="&AD1,'Checking Transaction Log'!$A:$A,"F",'Checking Transaction Log'!$B:$B,13) -> 0 | AD18: =H18-AC18 -> 180 | AE18: =SUMIFS('Checking Transaction Log'!$E:$E,'Checking Transaction Log'!$C:$C,">="&AE1,'Checking Transaction Log'!$C:$C,"<="&AF1,'Checking Transaction Log'!$A:$A,"F",'Checking Transaction Log'!$B:$B,13) -> 0 | AF18: =H18-AE18 -> 180
A19: ='Proposed Budget'!A19 -> F | B19: ='Proposed Budget'!B19 -> 14 | C19: ='Proposed Budget'!C19 -> Vivint Home Security | D19: =(E19/(TODAY()-$I$1))*30.42 -> 138.13308 | E19: =Q19+S19+U19+W19+Y19+AA19+AC19+AE19+I19+K19+M19+O19 -> 1366.8 | F19: =J19+L19+N19+P19+R19+T19+V19+X19+Z19+AB19 -> 33.2 | G19: =1-((E19/SUM(E19:F19))) -> 0.023714286 | H19: ='Proposed Budget'!D19 -> 140 | I19: =SUMIFS('Checking Transaction Log'!E:E,'Checking Transaction Log'!C:C,">="&I1,'Checking Transaction Log'!C:C,"<="&J1,'Checking Transaction Log'!A:A,"F",'Checking Transaction Log'!B:B,14) -> 135.41 | J19: =H19-I19 -> 4.59 | K19: =SUMIFS('Checking Transaction Log'!E:E,'Checking Transaction Log'!C:C,">="&K1,'Checking Transaction Log'!C:C,"<="&L1,'Checking Transaction Log'!A:A,"F",'Checking Transaction Log'!B:B,14) -> 135.41 | L19: =H19-K19 -> 4.59 | M19: =SUMIFS('Checking Transaction Log'!$E:$E,'Checking Transaction Log'!$C:$C,">="&M1,'Checking Transaction Log'!$C:$C,"<="&N1,'Checking Transaction Log'!$A:$A,"F",'Checking Transaction Log'!$B:$B,14) -> 135.41 | N19: =H19-M19 -> 4.59 | O19: =SUMIFS('Checking Transaction Log'!$E:$E,'Checking Transaction Log'!$C:$C,">="&O1,'Checking Transaction Log'!$C:$C,"<="&P1,'Checking Transaction Log'!$A:$A,"F",'Checking Transaction Log'!$B:$B,14) -> 136.92 | P19: =H19-O19 -> 3.08 | Q19: =SUMIFS('Checking Transaction Log'!$E:$E,'Checking Transaction Log'!$C:$C,">="&Q1,'Checking Transaction Log'!$C:$C,"<="&R1,'Checking Transaction Log'!$A:$A,"F",'Checking Transaction Log'!$B:$B,14) -> 136.92 | R19: =H19-Q19 -> 3.08 | S19: =SUMIFS('Checking Transaction Log'!$E:$E,'Checking Transaction Log'!$C:$C,">="&S1,'Checking Transaction Log'!$C:$C,"<="&T1,'Checking Transaction Log'!$A:$A,"F",'Checking Transaction Log'!$B:$B,14) -> 136.92 | T19: =H19-S19 -> 3.08 | U19: =SUMIFS('Checking Transaction Log'!$E:$E,'Checking Transaction Log'!$C:$C,">="&U1,'Checking Transaction Log'!$C:$C,"<="&V1,'Checking Transaction Log'!$A:$A,"F",'Checking Transaction Log'!$B:$B,14) -> 136.92 | V19: =H19-U19 -> 3.08 | W19: =SUMIFS('Checking Transaction Log'!$E:$E,'Checking Transaction Log'!$C:$C,">="&W1,'Checking Transaction Log'!$C:$C,"<="&X1,'Checking Transaction Log'!$A:$A,"F",'Checking Transaction Log'!$B:$B,14) -> 136.92 | X19: =H19-W19 -> 3.08 | Y19: =SUMIFS('Checking Transaction Log'!$E:$E,'Checking Transaction Log'!$C:$C,">="&Y1,'Checking Transaction Log'!$C:$C,"<="&Z1,'Checking Transaction Log'!$A:$A,"F",'Checking Transaction Log'!$B:$B,14) -> 136.92 | Z19: =H19-Y19 -> 3.08 | AA19: =SUMIFS('Checking Transaction Log'!$E:$E,'Checking Transaction Log'!$C:$C,">="&AA1,'Checking Transaction Log'!$C:$C,"<="&AB1,'Checking Transaction Log'!$A:$A,"F",'Checking Transaction Log'!$B:$B,14) -> 139.05 | AB19: =H19-AA19 -> 0.95 | AC19: =SUMIFS('Checking Transaction Log'!$E:$E,'Checking Transaction Log'!$C:$C,">="&AC1,'Checking Transaction Log'!$C:$C,"<="&AD1,'Checking Transaction Log'!$A:$A,"F",'Checking Transaction Log'!$B:$B,14) -> 0 | AD19: =H19-AC19 -> 140 | AE19: =SUMIFS('Checking Transaction Log'!$E:$E,'Checking Transaction Log'!$C:$C,">="&AE1,'Checking Transaction Log'!$C:$C,"<="&AF1,'Checking Transaction Log'!$A:$A,"F",'Checking Transaction Log'!$B:$B,14) -> 0 | AF19: =H19-AE19 -> 140
A20: ='Proposed Budget'!A20 -> F | B20: ='Proposed Budget'!B20 -> 15 | C20: ='Proposed Budget'!C20 -> Columbia Gas | D20: =(E20/(TODAY()-$I$1))*30.42 -> 108.27499 | E20: =Q20+S20+U20+W20+Y20+AA20+AC20+AE20+I20+K20+M20+O20 -> 1071.36 | F20: =J20+L20+N20+P20+R20+T20+V20+X20+Z20+AB20 -> -71.36 | G20: =1-((E20/SUM(E20:F20))) -> -0.07136 | H20: ='Proposed Budget'!D20 -> 100 | I20: =SUMIFS('Checking Transaction Log'!E:E,'Checking Transaction Log'!C:C,">="&I1,'Checking Transaction Log'!C:C,"<="&J1,'Checking Transaction Log'!A:A,"F",'Checking Transaction Log'!B:B,15) -> 132.4 | J20: =H20-I20 -> -32.4 | K20: =SUMIFS('Checking Transaction Log'!E:E,'Checking Transaction Log'!C:C,">="&K1,'Checking Transaction Log'!C:C,"<="&L1,'Checking Transaction Log'!A:A,"F",'Checking Transaction Log'!B:B,15) -> 188.16 | L20: =H20-K20 -> -88.16 | M20: =SUMIFS('Checking Transaction Log'!$E:$E,'Checking Transaction Log'!$C:$C,">="&M1,'Checking Transaction Log'!$C:$C,"<="&N1,'Checking Transaction Log'!$A:$A,"F",'Checking Transaction Log'!$B:$B,15) -> 175.09 | N20: =H20-M20 -> -75.09 | O20: =SUMIFS('Checking Transaction Log'!$E:$E,'Checking Transaction Log'!$C:$C,">="&O1,'Checking Transaction Log'!$C:$C,"<="&P1,'Checking Transaction Log'!$A:$A,"F",'Checking Transaction Log'!$B:$B,15) -> 131.23 | P20: =H20-O20 -> -31.23 | Q20: =SUMIFS('Checking Transaction Log'!$E:$E,'Checking Transaction Log'!$C:$C,">="&Q1,'Checking Transaction Log'!$C:$C,"<="&R1,'Checking Transaction Log'!$A:$A,"F",'Checking Transaction Log'!$B:$B,15) -> 101.37 | R20: =H20-Q20 -> -1.37 | S20: =SUMIFS('Checking Transaction Log'!$E:$E,'Checking Transaction Log'!$C:$C,">="&S1,'Checking Transaction Log'!$C:$C,"<="&T1,'Checking Transaction Log'!$A:$A,"F",'Checking Transaction Log'!$B:$B,15) -> 87.41 | T20: =H20-S20 -> 12.59 | U20: =SUMIFS('Checking Transaction Log'!$E:$E,'Checking Transaction Log'!$C:$C,">="&U1,'Checking Transaction Log'!$C:$C,"<="&V1,'Checking Transaction Log'!$A:$A,"F",'Checking Transaction Log'!$B:$B,15) -> 64.05 | V20: =H20-U20 -> 35.95 | W20: =SUMIFS('Checking Transaction Log'!$E:$E,'Checking Transaction Log'!$C:$C,">="&W1,'Checking Transaction Log'!$C:$C,"<="&X1,'Checking Transaction Log'!$A:$A,"F",'Checking Transaction Log'!$B:$B,15) -> 64.28 | X20: =H20-W20 -> 35.72 | Y20: =SUMIFS('Checking Transaction Log'!$E:$E,'Checking Transaction Log'!$C:$C,">="&Y1,'Checking Transaction Log'!$C:$C,"<="&Z1,'Checking Transaction Log'!$A:$A,"F",'Checking Transaction Log'!$B:$B,15) -> 63.69 | Z20: =H20-Y20 -> 36.31 | AA20: =SUMIFS('Checking Transaction Log'!$E:$E,'Checking Transaction Log'!$C:$C,">="&AA1,'Checking Transaction Log'!$C:$C,"<="&AB1,'Checking Transaction Log'!$A:$A,"F",'Checking Transaction Log'!$B:$B,15) -> 63.68 | AB20: =H20-AA20 -> 36.32 | AC20: =SUMIFS('Checking Transaction Log'!$E:$E,'Checking Transaction Log'!$C:$C,">="&AC1,'Checking Transaction Log'!$C:$C,"<="&AD1,'Checking Transaction Log'!$A:$A,"F",'Checking Transaction Log'!$B:$B,15) -> 0 | AD20: =H20-AC20 -> 100 | AE20: =SUMIFS('Checking Transaction Log'!$E:$E,'Checking Transaction Log'!$C:$C,">="&AE1,'Checking Transaction Log'!$C:$C,"<="&AF1,'Checking Transaction Log'!$A:$A,"F",'Checking Transaction Log'!$B:$B,15) -> 0 | AF20: =H20-AE20 -> 100
A21: ='Proposed Budget'!A21 -> F | B21: ='Proposed Budget'!B21 -> 16 | C21: ='Proposed Budget'!C21 -> Medical Bills | D21: =(E21/(TODAY()-$I$1))*30.42 -> 191.83297 | E21: =Q21+S21+U21+W21+Y21+AA21+AC21+AE21+I21+K21+M21+O21 -> 1898.15 | F21: =J21+L21+N21+P21+R21+T21+V21+X21+Z21+AB21 -> -1898.15 | G21: =1-((E21/SUM(E21:F21))) -> #DIV/0! | H21: ='Proposed Budget'!D21 -> 0 | I21: =SUMIFS('Checking Transaction Log'!E:E,'Checking Transaction Log'!C:C,">="&I1,'Checking Transaction Log'!C:C,"<="&J1,'Checking Transaction Log'!A:A,"F",'Checking Transaction Log'!B:B,16) -> 0 | J21: =H21-I21 -> 0 | K21: =SUMIFS('Checking Transaction Log'!E:E,'Checking Transaction Log'!C:C,">="&K1,'Checking Transaction Log'!C:C,"<="&L1,'Checking Transaction Log'!A:A,"F",'Checking Transaction Log'!B:B,16) -> 0 | L21: =H21-K21 -> 0 | M21: =SUMIFS('Checking Transaction Log'!$E:$E,'Checking Transaction Log'!$C:$C,">="&M1,'Checking Transaction Log'!$C:$C,"<="&N1,'Checking Transaction Log'!$A:$A,"F",'Checking Transaction Log'!$B:$B,16) -> 820.06 | N21: =H21-M21 -> -820.06 | O21: =SUMIFS('Checking Transaction Log'!$E:$E,'Checking Transaction Log'!$C:$C,">="&O1,'Checking Transaction Log'!$C:$C,"<="&P1,'Checking Transaction Log'!$A:$A,"F",'Checking Transaction Log'!$B:$B,16) -> 15 | P21: =H21-O21 -> -15 | Q21: =SUMIFS('Checking Transaction Log'!$E:$E,'Checking Transaction Log'!$C:$C,">="&Q1,'Checking Transaction Log'!$C:$C,"<="&R1,'Checking Transaction Log'!$A:$A,"F",'Checking Transaction Log'!$B:$B,16) -> 0 | R21: =H21-Q21 -> 0 | S21: =SUMIFS('Checking Transaction Log'!$E:$E,'Checking Transaction Log'!$C:$C,">="&S1,'Checking Transaction Log'!$C:$C,"<="&T1,'Checking Transaction Log'!$A:$A,"F",'Checking Transaction Log'!$B:$B,16) -> 62.31 | T21: =H21-S21 -> -62.31 | U21: =SUMIFS('Checking Transaction Log'!$E:$E,'Checking Transaction Log'!$C:$C,">="&U1,'Checking Transaction Log'!$C:$C,"<="&V1,'Checking Transaction Log'!$A:$A,"F",'Checking Transaction Log'!$B:$B,16) -> 0 | V21: =H21-U21 -> 0 | W21: =SUMIFS('Checking Transaction Log'!$E:$E,'Checking Transaction Log'!$C:$C,">="&W1,'Checking Transaction Log'!$C:$C,"<="&X1,'Checking Transaction Log'!$A:$A,"F",'Checking Transaction Log'!$B:$B,16) -> 0 | X21: =H21-W21 -> 0 | Y21: =SUMIFS('Checking Transaction Log'!$E:$E,'Checking Transaction Log'!$C:$C,">="&Y1,'Checking Transaction Log'!$C:$C,"<="&Z1,'Checking Transaction Log'!$A:$A,"F",'Checking Transaction Log'!$B:$B,16) -> 0 | Z21: =H21-Y21 -> 0 | AA21: =SUMIFS('Checking Transaction Log'!$E:$E,'Checking Transaction Log'!$C:$C,">="&AA1,'Checking Transaction Log'!$C:$C,"<="&AB1,'Checking Transaction Log'!$A:$A,"F",'Checking Transaction Log'!$B:$B,16) -> 1000.78 | AB21: =H21-AA21 -> -1000.78 | AC21: =SUMIFS('Checking Transaction Log'!$E:$E,'Checking Transaction Log'!$C:$C,">="&AC1,'Checking Transaction Log'!$C:$C,"<="&AD1,'Checking Transaction Log'!$A:$A,"F",'Checking Transaction Log'!$B:$B,16) -> 0 | AD21: =H21-AC21 -> 0 | AE21: =SUMIFS('Checking Transaction Log'!$E:$E,'Checking Transaction Log'!$C:$C,">="&AE1,'Checking Transaction Log'!$C:$C,"<="&AF1,'Checking Transaction Log'!$A:$A,"F",'Checking Transaction Log'!$B:$B,16) -> 0 | AF21: =H21-AE21 -> 0
A22: ='Proposed Budget'!A22 -> F | B22: ='Proposed Budget'!B22 -> 17 | C22: ='Proposed Budget'!C22 -> Planet Fitness | D22: =(E22/(TODAY()-$I$1))*30.42 -> 165.65054 | E22: =Q22+S22+U22+W22+Y22+AA22+AC22+AE22+I22+K22+M22+O22 -> 1639.08 | F22: =J22+L22+N22+P22+R22+T22+V22+X22+Z22+AB22 -> -189.08 | G22: =1-((E22/SUM(E22:F22))) -> -0.1304 | H22: ='Proposed Budget'!D22 -> 145 | I22: =SUMIFS('Checking Transaction Log'!E:E,'Checking Transaction Log'!C:C,">="&I1,'Checking Transaction Log'!C:C,"<="&J1,'Checking Transaction Log'!A:A,"F",'Checking Transaction Log'!B:B,17) -> 281.25 | J22: =H22-I22 -> -136.25 | K22: =SUMIFS('Checking Transaction Log'!E:E,'Checking Transaction Log'!C:C,">="&K1,'Checking Transaction Log'!C:C,"<="&L1,'Checking Transaction Log'!A:A,"F",'Checking Transaction Log'!B:B,17) -> 183.19 | L22: =H22-K22 -> -38.19 | M22: =SUMIFS('Checking Transaction Log'!$E:$E,'Checking Transaction Log'!$C:$C,">="&M1,'Checking Transaction Log'!$C:$C,"<="&N1,'Checking Transaction Log'!$A:$A,"F",'Checking Transaction Log'!$B:$B,17) -> 183.09 | N22: =H22-M22 -> -38.09 | O22: =SUMIFS('Checking Transaction Log'!$E:$E,'Checking Transaction Log'!$C:$C,">="&O1,'Checking Transaction Log'!$C:$C,"<="&P1,'Checking Transaction Log'!$A:$A,"F",'Checking Transaction Log'!$B:$B,17) -> 141.65 | P22: =H22-O22 -> 3.35 | Q22: =SUMIFS('Checking Transaction Log'!$E:$E,'Checking Transaction Log'!$C:$C,">="&Q1,'Checking Transaction Log'!$C:$C,"<="&R1,'Checking Transaction Log'!$A:$A,"F",'Checking Transaction Log'!$B:$B,17) -> 141.65 | R22: =H22-Q22 -> 3.35 | S22: =SUMIFS('Checking Transaction Log'!$E:$E,'Checking Transaction Log'!$C:$C,">="&S1,'Checking Transaction Log'!$C:$C,"<="&T1,'Checking Transaction Log'!$A:$A,"F",'Checking Transaction Log'!$B:$B,17) -> 141.65 | T22: =H22-S22 -> 3.35 | U22: =SUMIFS('Checking Transaction Log'!$E:$E,'Checking Transaction Log'!$C:$C,">="&U1,'Checking Transaction Log'!$C:$C,"<="&V1,'Checking Transaction Log'!$A:$A,"F",'Checking Transaction Log'!$B:$B,17) -> 141.65 | V22: =H22-U22 -> 3.35 | W22: =SUMIFS('Checking Transaction Log'!$E:$E,'Checking Transaction Log'!$C:$C,">="&W1,'Checking Transaction Log'!$C:$C,"<="&X1,'Checking Transaction Log'!$A:$A,"F",'Checking Transaction Log'!$B:$B,17) -> 141.65 | X22: =H22-W22 -> 3.35 | Y22: =SUMIFS('Checking Transaction Log'!$E:$E,'Checking Transaction Log'!$C:$C,">="&Y1,'Checking Transaction Log'!$C:$C,"<="&Z1,'Checking Transaction Log'!$A:$A,"F",'Checking Transaction Log'!$B:$B,17) -> 141.65 | Z22: =H22-Y22 -> 3.35 | AA22: =SUMIFS('Checking Transaction Log'!$E:$E,'Checking Transaction Log'!$C:$C,">="&AA1,'Checking Transaction Log'!$C:$C,"<="&AB1,'Checking Transaction Log'!$A:$A,"F",'Checking Transaction Log'!$B:$B,17) -> 141.65 | AB22: =H22-AA22 -> 3.35 | AC22: =SUMIFS('Checking Transaction Log'!$E:$E,'Checking Transaction Log'!$C:$C,">="&AC1,'Checking Transaction Log'!$C:$C,"<="&AD1,'Checking Transaction Log'!$A:$A,"F",'Checking Transaction Log'!$B:$B,17) -> 0 | AD22: =H22-AC22 -> 145 | AE22: =SUMIFS('Checking Transaction Log'!$E:$E,'Checking Transaction Log'!$C:$C,">="&AE1,'Checking Transaction Log'!$C:$C,"<="&AF1,'Checking Transaction Log'!$A:$A,"F",'Checking Transaction Log'!$B:$B,17) -> 0 | AF22: =H22-AE22 -> 145
A23: ='Proposed Budget'!A23 -> F | B23: ='Proposed Budget'!B23 -> 18 | C23: ='Proposed Budget'!C23 -> Lowes Rewards | D23: =(E23/(TODAY()-$I$1))*30.42 -> 202.12625 | E23: =Q23+S23+U23+W23+Y23+AA23+AC23+AE23+I23+K23+M23+O23 -> 2000 | F23: =J23+L23+N23+P23+R23+T23+V23+X23+Z23+AB23 -> 2000 | G23: =1-((E23/SUM(E23:F23))) -> 0.5 | H23: ='Proposed Budget'!D23 -> 400 | I23: =SUMIFS('Checking Transaction Log'!E:E,'Checking Transaction Log'!C:C,">="&I1,'Checking Transaction Log'!C:C,"<="&J1,'Checking Transaction Log'!A:A,"F",'Checking Transaction Log'!B:B,18) -> 400 | J23: =H23-I23 -> 0 | K23: =SUMIFS('Checking Transaction Log'!E:E,'Checking Transaction Log'!C:C,">="&K1,'Checking Transaction Log'!C:C,"<="&L1,'Checking Transaction Log'!A:A,"F",'Checking Transaction Log'!B:B,18) -> 400 | L23: =H23-K23 -> 0 | M23: =SUMIFS('Checking Transaction Log'!$E:$E,'Checking Transaction Log'!$C:$C,">="&M1,'Checking Transaction Log'!$C:$C,"<="&N1,'Checking Transaction Log'!$A:$A,"F",'Checking Transaction Log'!$B:$B,18) -> 400 | N23: =H23-M23 -> 0 | O23: =SUMIFS('Checking Transaction Log'!$E:$E,'Checking Transaction Log'!$C:$C,">="&O1,'Checking Transaction Log'!$C:$C,"<="&P1,'Checking Transaction Log'!$A:$A,"F",'Checking Transaction Log'!$B:$B,18) -> 400 | P23: =H23-O23 -> 0 | Q23: =SUMIFS('Checking Transaction Log'!$E:$E,'Checking Transaction Log'!$C:$C,">="&Q1,'Checking Transaction Log'!$C:$C,"<="&R1,'Checking Transaction Log'!$A:$A,"F",'Checking Transaction Log'!$B:$B,18) -> 400 | R23: =H23-Q23 -> 0 | S23: =SUMIFS('Checking Transaction Log'!$E:$E,'Checking Transaction Log'!$C:$C,">="&S1,'Checking Transaction Log'!$C:$C,"<="&T1,'Checking Transaction Log'!$A:$A,"F",'Checking Transaction Log'!$B:$B,18) -> 0 | T23: =H23-S23 -> 400 | U23: =SUMIFS('Checking Transaction Log'!$E:$E,'Checking Transaction Log'!$C:$C,">="&U1,'Checking Transaction Log'!$C:$C,"<="&V1,'Checking Transaction Log'!$A:$A,"F",'Checking Transaction Log'!$B:$B,18) -> 0 | V23: =H23-U23 -> 400 | W23: =SUMIFS('Checking Transaction Log'!$E:$E,'Checking Transaction Log'!$C:$C,">="&W1,'Checking Transaction Log'!$C:$C,"<="&X1,'Checking Transaction Log'!$A:$A,"F",'Checking Transaction Log'!$B:$B,18) -> 0 | X23: =H23-W23 -> 400 | Y23: =SUMIFS('Checking Transaction Log'!$E:$E,'Checking Transaction Log'!$C:$C,">="&Y1,'Checking Transaction Log'!$C:$C,"<="&Z1,'Checking Transaction Log'!$A:$A,"F",'Checking Transaction Log'!$B:$B,18) -> 0 | Z23: =H23-Y23 -> 400 | AA23: =SUMIFS('Checking Transaction Log'!$E:$E,'Checking Transaction Log'!$C:$C,">="&AA1,'Checking Transaction Log'!$C:$C,"<="&AB1,'Checking Transaction Log'!$A:$A,"F",'Checking Transaction Log'!$B:$B,18) -> 0 | AB23: =H23-AA23 -> 400 | AC23: =SUMIFS('Checking Transaction Log'!$E:$E,'Checking Transaction Log'!$C:$C,">="&AC1,'Checking Transaction Log'!$C:$C,"<="&AD1,'Checking Transaction Log'!$A:$A,"F",'Checking Transaction Log'!$B:$B,18) -> 0 | AD23: =H23-AC23 -> 400 | AE23: =SUMIFS('Checking Transaction Log'!$E:$E,'Checking Transaction Log'!$C:$C,">="&AE1,'Checking Transaction Log'!$C:$C,"<="&AF1,'Checking Transaction Log'!$A:$A,"F",'Checking Transaction Log'!$B:$B,18) -> 0 | AF23: =H23-AE23 -> 400
A24: ='Proposed Budget'!A24 -> F | B24: ='Proposed Budget'!B24 -> 19 | C24: ='Proposed Budget'!C24 -> Wells Fargo - Pool | D24: =(E24/(TODAY()-$I$1))*30.42 -> 202.12625 | E24: =Q24+S24+U24+W24+Y24+AA24+AC24+AE24+I24+K24+M24+O24 -> 2000 | F24: =J24+L24+N24+P24+R24+T24+V24+X24+Z24+AB24 -> 0 | G24: =1-((E24/SUM(E24:F24))) -> 0 | H24: ='Proposed Budget'!D24 -> 200 | I24: =SUMIFS('Checking Transaction Log'!E:E,'Checking Transaction Log'!C:C,">="&I1,'Checking Transaction Log'!C:C,"<="&J1,'Checking Transaction Log'!A:A,"F",'Checking Transaction Log'!B:B,19) -> 200 | J24: =H24-I24 -> 0 | K24: =SUMIFS('Checking Transaction Log'!E:E,'Checking Transaction Log'!C:C,">="&K1,'Checking Transaction Log'!C:C,"<="&L1,'Checking Transaction Log'!A:A,"F",'Checking Transaction Log'!B:B,19) -> 200 | L24: =H24-K24 -> 0 | M24: =SUMIFS('Checking Transaction Log'!$E:$E,'Checking Transaction Log'!$C:$C,">="&M1,'Checking Transaction Log'!$C:$C,"<="&N1,'Checking Transaction Log'!$A:$A,"F",'Checking Transaction Log'!$B:$B,19) -> 200 | N24: =H24-M24 -> 0 | O24: =SUMIFS('Checking Transaction Log'!$E:$E,'Checking Transaction Log'!$C:$C,">="&O1,'Checking Transaction Log'!$C:$C,"<="&P1,'Checking Transaction Log'!$A:$A,"F",'Checking Transaction Log'!$B:$B,19) -> 200 | P24: =H24-O24 -> 0 | Q24: =SUMIFS('Checking Transaction Log'!$E:$E,'Checking Transaction Log'!$C:$C,">="&Q1,'Checking Transaction Log'!$C:$C,"<="&R1,'Checking Transaction Log'!$A:$A,"F",'Checking Transaction Log'!$B:$B,19) -> 200 | R24: =H24-Q24 -> 0 | S24: =SUMIFS('Checking Transaction Log'!$E:$E,'Checking Transaction Log'!$C:$C,">="&S1,'Checking Transaction Log'!$C:$C,"<="&T1,'Checking Transaction Log'!$A:$A,"F",'Checking Transaction Log'!$B:$B,19) -> 200 | T24: =H24-S24 -> 0 | U24: =SUMIFS('Checking Transaction Log'!$E:$E,'Checking Transaction Log'!$C:$C,">="&U1,'Checking Transaction Log'!$C:$C,"<="&V1,'Checking Transaction Log'!$A:$A,"F",'Checking Transaction Log'!$B:$B,19) -> 200 | V24: =H24-U24 -> 0 | W24: =SUMIFS('Checking Transaction Log'!$E:$E,'Checking Transaction Log'!$C:$C,">="&W1,'Checking Transaction Log'!$C:$C,"<="&X1,'Checking Transaction Log'!$A:$A,"F",'Checking Transaction Log'!$B:$B,19) -> 200 | X24: =H24-W24 -> 0 | Y24: =SUMIFS('Checking Transaction Log'!$E:$E,'Checking Transaction Log'!$C:$C,">="&Y1,'Checking Transaction Log'!$C:$C,"<="&Z1,'Checking Transaction Log'!$A:$A,"F",'Checking Transaction Log'!$B:$B,19) -> 200 | Z24: =H24-Y24 -> 0 | AA24: =SUMIFS('Checking Transaction Log'!$E:$E,'Checking Transaction Log'!$C:$C,">="&AA1,'Checking Transaction Log'!$C:$C,"<="&AB1,'Checking Transaction Log'!$A:$A,"F",'Checking Transaction Log'!$B:$B,19) -> 200 | AB24: =H24-AA24 -> 0 | AC24: =SUMIFS('Checking Transaction Log'!$E:$E,'Checking Transaction Log'!$C:$C,">="&AC1,'Checking Transaction Log'!$C:$C,"<="&AD1,'Checking Transaction Log'!$A:$A,"F",'Checking Transaction Log'!$B:$B,19) -> 0 | AD24: =H24-AC24 -> 200 | AE24: =SUMIFS('Checking Transaction Log'!$E:$E,'Checking Transaction Log'!$C:$C,">="&AE1,'Checking Transaction Log'!$C:$C,"<="&AF1,'Checking Transaction Log'!$A:$A,"F",'Checking Transaction Log'!$B:$B,19) -> 0 | AF24: =H24-AE24 -> 200
A25: ='Proposed Budget'!A25 -> F | B25: ='Proposed Budget'!B25 -> 20 | C25: ='Proposed Budget'!C25 -> Wells Fargo - Deck | D25: =(E25/(TODAY()-$I$1))*30.42 -> 363.82724 | E25: =Q25+S25+U25+W25+Y25+AA25+AC25+AE25+I25+K25+M25+O25 -> 3600 | F25: =J25+L25+N25+P25+R25+T25+V25+X25+Z25+AB25 -> 2400 | G25: =1-((E25/SUM(E25:F25))) -> 0.4 | H25: ='Proposed Budget'!D25 -> 600 | I25: =SUMIFS('Checking Transaction Log'!E:E,'Checking Transaction Log'!C:C,">="&I1,'Checking Transaction Log'!C:C,"<="&J1,'Checking Transaction Log'!A:A,"F",'Checking Transaction Log'!B:B,20) -> 0 | J25: =H25-I25 -> 600 | K25: =SUMIFS('Checking Transaction Log'!E:E,'Checking Transaction Log'!C:C,">="&K1,'Checking Transaction Log'!C:C,"<="&L1,'Checking Transaction Log'!A:A,"F",'Checking Transaction Log'!B:B,20) -> 0 | L25: =H25-K25 -> 600 | M25: =SUMIFS('Checking Transaction Log'!$E:$E,'Checking Transaction Log'!$C:$C,">="&M1,'Checking Transaction Log'!$C:$C,"<="&N1,'Checking Transaction Log'!$A:$A,"F",'Checking Transaction Log'!$B:$B,20) -> 0 | N25: =H25-M25 -> 600 | O25: =SUMIFS('Checking Transaction Log'!$E:$E,'Checking Transaction Log'!$C:$C,">="&O1,'Checking Transaction Log'!$C:$C,"<="&P1,'Checking Transaction Log'!$A:$A,"F",'Checking Transaction Log'!$B:$B,20) -> 0 | P25: =H25-O25 -> 600 | Q25: =SUMIFS('Checking Transaction Log'!$E:$E,'Checking Transaction Log'!$C:$C,">="&Q1,'Checking Transaction Log'!$C:$C,"<="&R1,'Checking Transaction Log'!$A:$A,"F",'Checking Transaction Log'!$B:$B,20) -> 600 | R25: =H25-Q25 -> 0 | S25: =SUMIFS('Checking Transaction Log'!$E:$E,'Checking Transaction Log'!$C:$C,">="&S1,'Checking Transaction Log'!$C:$C,"<="&T1,'Checking Transaction Log'!$A:$A,"F",'Checking Transaction Log'!$B:$B,20) -> 600 | T25: =H25-S25 -> 0 | U25: =SUMIFS('Checking Transaction Log'!$E:$E,'Checking Transaction Log'!$C:$C,">="&U1,'Checking Transaction Log'!$C:$C,"<="&V1,'Checking Transaction Log'!$A:$A,"F",'Checking Transaction Log'!$B:$B,20) -> 600 | V25: =H25-U25 -> 0 | W25: =SUMIFS('Checking Transaction Log'!$E:$E,'Checking Transaction Log'!$C:$C,">="&W1,'Checking Transaction Log'!$C:$C,"<="&X1,'Checking Transaction Log'!$A:$A,"F",'Checking Transaction Log'!$B:$B,20) -> 600 | X25: =H25-W25 -> 0 | Y25: =SUMIFS('Checking Transaction Log'!$E:$E,'Checking Transaction Log'!$C:$C,">="&Y1,'Checking Transaction Log'!$C:$C,"<="&Z1,'Checking Transaction Log'!$A:$A,"F",'Checking Transaction Log'!$B:$B,20) -> 600 | Z25: =H25-Y25 -> 0 | AA25: =SUMIFS('Checking Transaction Log'!$E:$E,'Checking Transaction Log'!$C:$C,">="&AA1,'Checking Transaction Log'!$C:$C,"<="&AB1,'Checking Transaction Log'!$A:$A,"F",'Checking Transaction Log'!$B:$B,20) -> 600 | AB25: =H25-AA25 -> 0 | AC25: =SUMIFS('Checking Transaction Log'!$E:$E,'Checking Transaction Log'!$C:$C,">="&AC1,'Checking Transaction Log'!$C:$C,"<="&AD1,'Checking Transaction Log'!$A:$A,"F",'Checking Transaction Log'!$B:$B,20) -> 0 | AD25: =H25-AC25 -> 600 | AE25: =SUMIFS('Checking Transaction Log'!$E:$E,'Checking Transaction Log'!$C:$C,">="&AE1,'Checking Transaction Log'!$C:$C,"<="&AF1,'Checking Transaction Log'!$A:$A,"F",'Checking Transaction Log'!$B:$B,20) -> 0 | AF25: =H25-AE25 -> 600
A26: ='Proposed Budget'!A26 -> F | B26: ='Proposed Budget'!B26 -> 21 | C26: ='Proposed Budget'!C26 -> Massage Envy | D26: =(E26/(TODAY()-$I$1))*30.42 -> 94.466733 | E26: =Q26+S26+U26+W26+Y26+AA26+AC26+AE26+I26+K26+M26+O26 -> 934.73 | F26: =J26+L26+N26+P26+R26+T26+V26+X26+Z26+AB26 -> -84.73 | G26: =1-((E26/SUM(E26:F26))) -> -0.099682353 | H26: ='Proposed Budget'!D26 -> 85 | I26: =SUMIFS('Checking Transaction Log'!E:E,'Checking Transaction Log'!C:C,">="&I1,'Checking Transaction Log'!C:C,"<="&J1,'Checking Transaction Log'!A:A,"F",'Checking Transaction Log'!B:B,21) -> 100.79 | J26: =H26-I26 -> -15.79 | K26: =SUMIFS('Checking Transaction Log'!E:E,'Checking Transaction Log'!C:C,">="&K1,'Checking Transaction Log'!C:C,"<="&L1,'Checking Transaction Log'!A:A,"F",'Checking Transaction Log'!B:B,21) -> 108.35 | L26: =H26-K26 -> -23.35 | M26: =SUMIFS('Checking Transaction Log'!$E:$E,'Checking Transaction Log'!$C:$C,">="&M1,'Checking Transaction Log'!$C:$C,"<="&N1,'Checking Transaction Log'!$A:$A,"F",'Checking Transaction Log'!$B:$B,21) -> 116.32 | N26: =H26-M26 -> -31.32 | O26: =SUMIFS('Checking Transaction Log'!$E:$E,'Checking Transaction Log'!$C:$C,">="&O1,'Checking Transaction Log'!$C:$C,"<="&P1,'Checking Transaction Log'!$A:$A,"F",'Checking Transaction Log'!$B:$B,21) -> 75.6 | P26: =H26-O26 -> 9.4 | Q26: =SUMIFS('Checking Transaction Log'!$E:$E,'Checking Transaction Log'!$C:$C,">="&Q1,'Checking Transaction Log'!$C:$C,"<="&R1,'Checking Transaction Log'!$A:$A,"F",'Checking Transaction Log'!$B:$B,21) -> 81 | R26: =H26-Q26 -> 4 | S26: =SUMIFS('Checking Transaction Log'!$E:$E,'Checking Transaction Log'!$C:$C,">="&S1,'Checking Transaction Log'!$C:$C,"<="&T1,'Checking Transaction Log'!$A:$A,"F",'Checking Transaction Log'!$B:$B,21) -> 81 | T26: =H26-S26 -> 4 | U26: =SUMIFS('Checking Transaction Log'!$E:$E,'Checking Transaction Log'!$C:$C,">="&U1,'Checking Transaction Log'!$C:$C,"<="&V1,'Checking Transaction Log'!$A:$A,"F",'Checking Transaction Log'!$B:$B,21) -> 128.67 | V26: =H26-U26 -> -43.67 | W26: =SUMIFS('Checking Transaction Log'!$E:$E,'Checking Transaction Log'!$C:$C,">="&W1,'Checking Transaction Log'!$C:$C,"<="&X1,'Checking Transaction Log'!$A:$A,"F",'Checking Transaction Log'!$B:$B,21) -> 81 | X26: =H26-W26 -> 4 | Y26: =SUMIFS('Checking Transaction Log'!$E:$E,'Checking Transaction Log'!$C:$C,">="&Y1,'Checking Transaction Log'!$C:$C,"<="&Z1,'Checking Transaction Log'!$A:$A,"F",'Checking Transaction Log'!$B:$B,21) -> 81 | Z26: =H26-Y26 -> 4 | AA26: =SUMIFS('Checking Transaction Log'!$E:$E,'Checking Transaction Log'!$C:$C,">="&AA1,'Checking Transaction Log'!$C:$C,"<="&AB1,'Checking Transaction Log'!$A:$A,"F",'Checking Transaction Log'!$B:$B,21) -> 81 | AB26: =H26-AA26 -> 4 | AC26: =SUMIFS('Checking Transaction Log'!$E:$E,'Checking Transaction Log'!$C:$C,">="&AC1,'Checking Transaction Log'!$C:$C,"<="&AD1,'Checking Transaction Log'!$A:$A,"F",'Checking Transaction Log'!$B:$B,21) -> 0 | AD26: =H26-AC26 -> 85 | AE26: =SUMIFS('Checking Transaction Log'!$E:$E,'Checking Transaction Log'!$C:$C,">="&AE1,'Checking Transaction Log'!$C:$C,"<="&AF1,'Checking Transaction Log'!$A:$A,"F",'Checking Transaction Log'!$B:$B,21) -> 0 | AF26: =H26-AE26 -> 85
A27: ='Proposed Budget'!A27 -> F | B27: ='Proposed Budget'!B27 -> 22 | C27: ='Proposed Budget'!C27 -> Streaming/Music | D27: =(E27/(TODAY()-$I$1))*30.42 -> 140.48886 | E27: =Q27+S27+U27+W27+Y27+AA27+AC27+AE27+I27+K27+M27+O27 -> 1390.11 | F27: =J27+L27+N27+P27+R27+T27+V27+X27+Z27+AB27 -> -390.11 | G27: =1-((E27/SUM(E27:F27))) -> -0.39011 | H27: ='Proposed Budget'!D27 -> 100 | I27: =SUMIFS('Checking Transaction Log'!E:E,'Checking Transaction Log'!C:C,">="&I1,'Checking Transaction Log'!C:C,"<="&J1,'Checking Transaction Log'!A:A,"F",'Checking Transaction Log'!B:B,22) -> 218.27 | J27: =H27-I27 -> -118.27 | K27: =SUMIFS('Checking Transaction Log'!E:E,'Checking Transaction Log'!C:C,">="&K1,'Checking Transaction Log'!C:C,"<="&L1,'Checking Transaction Log'!A:A,"F",'Checking Transaction Log'!B:B,22) -> 67.05 | L27: =H27-K27 -> 32.95 | M27: =SUMIFS('Checking Transaction Log'!$E:$E,'Checking Transaction Log'!$C:$C,">="&M1,'Checking Transaction Log'!$C:$C,"<="&N1,'Checking Transaction Log'!$A:$A,"F",'Checking Transaction Log'!$B:$B,22) -> 79.82 | N27: =H27-M27 -> 20.18 | O27: =SUMIFS('Checking Transaction Log'!$E:$E,'Checking Transaction Log'!$C:$C,">="&O1,'Checking Transaction Log'!$C:$C,"<="&P1,'Checking Transaction Log'!$A:$A,"F",'Checking Transaction Log'!$B:$B,22) -> 76.62 | P27: =H27-O27 -> 23.38 | Q27: =SUMIFS('Checking Transaction Log'!$E:$E,'Checking Transaction Log'!$C:$C,">="&Q1,'Checking Transaction Log'!$C:$C,"<="&R1,'Checking Transaction Log'!$A:$A,"F",'Checking Transaction Log'!$B:$B,22) -> 122.37 | R27: =H27-Q27 -> -22.37 | S27: =SUMIFS('Checking Transaction Log'!$E:$E,'Checking Transaction Log'!$C:$C,">="&S1,'Checking Transaction Log'!$C:$C,"<="&T1,'Checking Transaction Log'!$A:$A,"F",'Checking Transaction Log'!$B:$B,22) -> 103.22 | T27: =H27-S27 -> -3.22 | U27: =SUMIFS('Checking Transaction Log'!$E:$E,'Checking Transaction Log'!$C:$C,">="&U1,'Checking Transaction Log'!$C:$C,"<="&V1,'Checking Transaction Log'!$A:$A,"F",'Checking Transaction Log'!$B:$B,22) -> 103.22 | V27: =H27-U27 -> -3.22 | W27: =SUMIFS('Checking Transaction Log'!$E:$E,'Checking Transaction Log'!$C:$C,">="&W1,'Checking Transaction Log'!$C:$C,"<="&X1,'Checking Transaction Log'!$A:$A,"F",'Checking Transaction Log'!$B:$B,22) -> 90.46 | X27: =H27-W27 -> 9.54 | Y27: =SUMIFS('Checking Transaction Log'!$E:$E,'Checking Transaction Log'!$C:$C,">="&Y1,'Checking Transaction Log'!$C:$C,"<="&Z1,'Checking Transaction Log'!$A:$A,"F",'Checking Transaction Log'!$B:$B,22) -> 154.3 | Z27: =H27-Y27 -> -54.3 | AA27: =SUMIFS('Checking Transaction Log'!$E:$E,'Checking Transaction Log'!$C:$C,">="&AA1,'Checking Transaction Log'!$C:$C,"<="&AB1,'Checking Transaction Log'!$A:$A,"F",'Checking Transaction Log'!$B:$B,22) -> 374.78 | AB27: =H27-AA27 -> -274.78 | AC27: =SUMIFS('Checking Transaction Log'!$E:$E,'Checking Transaction Log'!$C:$C,">="&AC1,'Checking Transaction Log'!$C:$C,"<="&AD1,'Checking Transaction Log'!$A:$A,"F",'Checking Transaction Log'!$B:$B,22) -> 0 | AD27: =H27-AC27 -> 100 | AE27: =SUMIFS('Checking Transaction Log'!$E:$E,'Checking Transaction Log'!$C:$C,">="&AE1,'Checking Transaction Log'!$C:$C,"<="&AF1,'Checking Transaction Log'!$A:$A,"F",'Checking Transaction Log'!$B:$B,22) -> 0 | AF27: =H27-AE27 -> 100
A28: ='Proposed Budget'!A28 -> F | B28: ='Proposed Budget'!B28 -> 23 | C28: ='Proposed Budget'!C28 -> GM Financial/Toyota | D28: =(E28/(TODAY()-$I$1))*30.42 -> 924.61236 | E28: =Q28+S28+U28+W28+Y28+AA28+AC28+AE28+I28+K28+M28+O28 -> 9148.86 | F28: =J28+L28+N28+P28+R28+T28+V28+X28+Z28+AB28 -> 2851.14 | G28: =1-((E28/SUM(E28:F28))) -> 0.237595 | H28: ='Proposed Budget'!D28 -> 1200 | I28: =SUMIFS('Checking Transaction Log'!E:E,'Checking Transaction Log'!C:C,">="&I1,'Checking Transaction Log'!C:C,"<="&J1,'Checking Transaction Log'!A:A,"F",'Checking Transaction Log'!B:B,23) -> 1180.34 | J28: =H28-I28 -> 19.66 | K28: =SUMIFS('Checking Transaction Log'!E:E,'Checking Transaction Log'!C:C,">="&K1,'Checking Transaction Log'!C:C,"<="&L1,'Checking Transaction Log'!A:A,"F",'Checking Transaction Log'!B:B,23) -> 1180.34 | L28: =H28-K28 -> 19.66 | M28: =SUMIFS('Checking Transaction Log'!$E:$E,'Checking Transaction Log'!$C:$C,">="&M1,'Checking Transaction Log'!$C:$C,"<="&N1,'Checking Transaction Log'!$A:$A,"F",'Checking Transaction Log'!$B:$B,23) -> 1180.34 | N28: =H28-M28 -> 19.66 | O28: =SUMIFS('Checking Transaction Log'!$E:$E,'Checking Transaction Log'!$C:$C,">="&O1,'Checking Transaction Log'!$C:$C,"<="&P1,'Checking Transaction Log'!$A:$A,"F",'Checking Transaction Log'!$B:$B,23) -> 1180.34 | P28: =H28-O28 -> 19.66 | Q28: =SUMIFS('Checking Transaction Log'!$E:$E,'Checking Transaction Log'!$C:$C,">="&Q1,'Checking Transaction Log'!$C:$C,"<="&R1,'Checking Transaction Log'!$A:$A,"F",'Checking Transaction Log'!$B:$B,23) -> 1180.34 | R28: =H28-Q28 -> 19.66 | S28: =SUMIFS('Checking Transaction Log'!$E:$E,'Checking Transaction Log'!$C:$C,">="&S1,'Checking Transaction Log'!$C:$C,"<="&T1,'Checking Transaction Log'!$A:$A,"F",'Checking Transaction Log'!$B:$B,23) -> 1129.32 | T28: =H28-S28 -> 70.68 | U28: =SUMIFS('Checking Transaction Log'!$E:$E,'Checking Transaction Log'!$C:$C,">="&U1,'Checking Transaction Log'!$C:$C,"<="&V1,'Checking Transaction Log'!$A:$A,"F",'Checking Transaction Log'!$B:$B,23) -> 529.46 | V28: =H28-U28 -> 670.54 | W28: =SUMIFS('Checking Transaction Log'!$E:$E,'Checking Transaction Log'!$C:$C,">="&W1,'Checking Transaction Log'!$C:$C,"<="&X1,'Checking Transaction Log'!$A:$A,"F",'Checking Transaction Log'!$B:$B,23) -> 529.46 | X28: =H28-W28 -> 670.54 | Y28: =SUMIFS('Checking Transaction Log'!$E:$E,'Checking Transaction Log'!$C:$C,">="&Y1,'Checking Transaction Log'!$C:$C,"<="&Z1,'Checking Transaction Log'!$A:$A,"F",'Checking Transaction Log'!$B:$B,23) -> 529.46 | Z28: =H28-Y28 -> 670.54 | AA28: =SUMIFS('Checking Transaction Log'!$E:$E,'Checking Transaction Log'!$C:$C,">="&AA1,'Checking Transaction Log'!$C:$C,"<="&AB1,'Checking Transaction Log'!$A:$A,"F",'Checking Transaction Log'!$B:$B,23) -> 529.46 | AB28: =H28-AA28 -> 670.54 | AC28: =SUMIFS('Checking Transaction Log'!$E:$E,'Checking Transaction Log'!$C:$C,">="&AC1,'Checking Transaction Log'!$C:$C,"<="&AD1,'Checking Transaction Log'!$A:$A,"F",'Checking Transaction Log'!$B:$B,23) -> 0 | AD28: =H28-AC28 -> 1200 | AE28: =SUMIFS('Checking Transaction Log'!$E:$E,'Checking Transaction Log'!$C:$C,">="&AE1,'Checking Transaction Log'!$C:$C,"<="&AF1,'Checking Transaction Log'!$A:$A,"F",'Checking Transaction Log'!$B:$B,23) -> 0 | AF28: =H28-AE28 -> 1200
A29: ='Proposed Budget'!A29 -> F | B29: ='Proposed Budget'!B29 -> 24 | C29: ='Proposed Budget'!C29 -> Ohio Turnpike | D29: =(E29/(TODAY()-$I$1))*30.42 -> 103.33704 | E29: =Q29+S29+U29+W29+Y29+AA29+AC29+AE29+I29+K29+M29+O29 -> 1022.5 | F29: =J29+L29+N29+P29+R29+T29+V29+X29+Z29+AB29 -> 177.5 | G29: =1-((E29/SUM(E29:F29))) -> 0.14791667 | H29: ='Proposed Budget'!D29 -> 120 | I29: =SUMIFS('Checking Transaction Log'!E:E,'Checking Transaction Log'!C:C,">="&I1,'Checking Transaction Log'!C:C,"<="&J1,'Checking Transaction Log'!A:A,"F",'Checking Transaction Log'!B:B,24) -> 83.42 | J29: =H29-I29 -> 36.58 | K29: =SUMIFS('Checking Transaction Log'!E:E,'Checking Transaction Log'!C:C,">="&K1,'Checking Transaction Log'!C:C,"<="&L1,'Checking Transaction Log'!A:A,"F",'Checking Transaction Log'!B:B,24) -> 168.41 | L29: =H29-K29 -> -48.41 | M29: =SUMIFS('Checking Transaction Log'!$E:$E,'Checking Transaction Log'!$C:$C,">="&M1,'Checking Transaction Log'!$C:$C,"<="&N1,'Checking Transaction Log'!$A:$A,"F",'Checking Transaction Log'!$B:$B,24) -> 86.58 | N29: =H29-M29 -> 33.42 | O29: =SUMIFS('Checking Transaction Log'!$E:$E,'Checking Transaction Log'!$C:$C,">="&O1,'Checking Transaction Log'!$C:$C,"<="&P1,'Checking Transaction Log'!$A:$A,"F",'Checking Transaction Log'!$B:$B,24) -> 105.33 | P29: =H29-O29 -> 14.67 | Q29: =SUMIFS('Checking Transaction Log'!$E:$E,'Checking Transaction Log'!$C:$C,">="&Q1,'Checking Transaction Log'!$C:$C,"<="&R1,'Checking Transaction Log'!$A:$A,"F",'Checking Transaction Log'!$B:$B,24) -> 109.92 | R29: =H29-Q29 -> 10.08 | S29: =SUMIFS('Checking Transaction Log'!$E:$E,'Checking Transaction Log'!$C:$C,">="&S1,'Checking Transaction Log'!$C:$C,"<="&T1,'Checking Transaction Log'!$A:$A,"F",'Checking Transaction Log'!$B:$B,24) -> 109.5 | T29: =H29-S29 -> 10.5 | U29: =SUMIFS('Checking Transaction Log'!$E:$E,'Checking Transaction Log'!$C:$C,">="&U1,'Checking Transaction Log'!$C:$C,"<="&V1,'Checking Transaction Log'!$A:$A,"F",'Checking Transaction Log'!$B:$B,24) -> 92.25 | V29: =H29-U29 -> 27.75 | W29: =SUMIFS('Checking Transaction Log'!$E:$E,'Checking Transaction Log'!$C:$C,">="&W1,'Checking Transaction Log'!$C:$C,"<="&X1,'Checking Transaction Log'!$A:$A,"F",'Checking Transaction Log'!$B:$B,24) -> 83.5 | X29: =H29-W29 -> 36.5 | Y29: =SUMIFS('Checking Transaction Log'!$E:$E,'Checking Transaction Log'!$C:$C,">="&Y1,'Checking Transaction Log'!$C:$C,"<="&Z1,'Checking Transaction Log'!$A:$A,"F",'Checking Transaction Log'!$B:$B,24) -> 88.17 | Z29: =H29-Y29 -> 31.83 | AA29: =SUMIFS('Checking Transaction Log'!$E:$E,'Checking Transaction Log'!$C:$C,">="&AA1,'Checking Transaction Log'!$C:$C,"<="&AB1,'Checking Transaction Log'!$A:$A,"F",'Checking Transaction Log'!$B:$B,24) -> 95.42 | AB29: =H29-AA29 -> 24.58 | AC29: =SUMIFS('Checking Transaction Log'!$E:$E,'Checking Transaction Log'!$C:$C,">="&AC1,'Checking Transaction Log'!$C:$C,"<="&AD1,'Checking Transaction Log'!$A:$A,"F",'Checking Transaction Log'!$B:$B,24) -> 0 | AD29: =H29-AC29 -> 120 | AE29: =SUMIFS('Checking Transaction Log'!$E:$E,'Checking Transaction Log'!$C:$C,">="&AE1,'Checking Transaction Log'!$C:$C,"<="&AF1,'Checking Transaction Log'!$A:$A,"F",'Checking Transaction Log'!$B:$B,24) -> 0 | AF29: =H29-AE29 -> 120
A30: ='Proposed Budget'!A30 -> F | B30: ='Proposed Budget'!B30 -> 42 | C30: ='Proposed Budget'!C30 -> Water Bill - Main | D30: =(E30/(TODAY()-$I$1))*30.42 -> 92.181696 | E30: =Q30+S30+U30+W30+Y30+AA30+AC30+AE30+I30+K30+M30+O30 -> 912.12 | F30: =J30+L30+N30+P30+R30+T30+V30+X30+Z30+AB30 -> -162.12 | G30: =1-((E30/SUM(E30:F30))) -> -0.21616 | H30: ='Proposed Budget'!D30 -> 75 | I30: =SUMIFS('Checking Transaction Log'!E:E,'Checking Transaction Log'!C:C,">="&I1,'Checking Transaction Log'!C:C,"<="&J1,'Checking Transaction Log'!A:A,"F",'Checking Transaction Log'!B:B,42) -> 80.99 | J30: =H30-I30 -> -5.99 | K30: =SUMIFS('Checking Transaction Log'!E:E,'Checking Transaction Log'!C:C,">="&K1,'Checking Transaction Log'!C:C,"<="&L1,'Checking Transaction Log'!A:A,"F",'Checking Transaction Log'!B:B,42) -> 88.44 | L30: =H30-K30 -> -13.44 | M30: =SUMIFS('Checking Transaction Log'!$E:$E,'Checking Transaction Log'!$C:$C,">="&M1,'Checking Transaction Log'!$C:$C,"<="&N1,'Checking Transaction Log'!$A:$A,"F",'Checking Transaction Log'!$B:$B,42) -> 96.25 | N30: =H30-M30 -> -21.25 | O30: =SUMIFS('Checking Transaction Log'!$E:$E,'Checking Transaction Log'!$C:$C,">="&O1,'Checking Transaction Log'!$C:$C,"<="&P1,'Checking Transaction Log'!$A:$A,"F",'Checking Transaction Log'!$B:$B,42) -> 88.17 | P30: =H30-O30 -> -13.17 | Q30: =SUMIFS('Checking Transaction Log'!$E:$E,'Checking Transaction Log'!$C:$C,">="&Q1,'Checking Transaction Log'!$C:$C,"<="&R1,'Checking Transaction Log'!$A:$A,"F",'Checking Transaction Log'!$B:$B,42) -> 80.72 | R30: =H30-Q30 -> -5.72 | S30: =SUMIFS('Checking Transaction Log'!$E:$E,'Checking Transaction Log'!$C:$C,">="&S1,'Checking Transaction Log'!$C:$C,"<="&T1,'Checking Transaction Log'!$A:$A,"F",'Checking Transaction Log'!$B:$B,42) -> 173.9 | T30: =H30-S30 -> -98.9 | U30: =SUMIFS('Checking Transaction Log'!$E:$E,'Checking Transaction Log'!$C:$C,">="&U1,'Checking Transaction Log'!$C:$C,"<="&V1,'Checking Transaction Log'!$A:$A,"F",'Checking Transaction Log'!$B:$B,42) -> 88.8 | V30: =H30-U30 -> -13.8 | W30: =SUMIFS('Checking Transaction Log'!$E:$E,'Checking Transaction Log'!$C:$C,">="&W1,'Checking Transaction Log'!$C:$C,"<="&X1,'Checking Transaction Log'!$A:$A,"F",'Checking Transaction Log'!$B:$B,42) -> 81.35 | X30: =H30-W30 -> -6.35 | Y30: =SUMIFS('Checking Transaction Log'!$E:$E,'Checking Transaction Log'!$C:$C,">="&Y1,'Checking Transaction Log'!$C:$C,"<="&Z1,'Checking Transaction Log'!$A:$A,"F",'Checking Transaction Log'!$B:$B,42) -> 111.15 | Z30: =H30-Y30 -> -36.15 | AA30: =SUMIFS('Checking Transaction Log'!$E:$E,'Checking Transaction Log'!$C:$C,">="&AA1,'Checking Transaction Log'!$C:$C,"<="&AB1,'Checking Transaction Log'!$A:$A,"F",'Checking Transaction Log'!$B:$B,42) -> 22.35 | AB30: =H30-AA30 -> 52.65 | AC30: =SUMIFS('Checking Transaction Log'!$E:$E,'Checking Transaction Log'!$C:$C,">="&AC1,'Checking Transaction Log'!$C:$C,"<="&AD1,'Checking Transaction Log'!$A:$A,"F",'Checking Transaction Log'!$B:$B,42) -> 0 | AD30: =H30-AC30 -> 75 | AE30: =SUMIFS('Checking Transaction Log'!$E:$E,'Checking Transaction Log'!$C:$C,">="&AE1,'Checking Transaction Log'!$C:$C,"<="&AF1,'Checking Transaction Log'!$A:$A,"F",'Checking Transaction Log'!$B:$B,42) -> 0 | AF30: =H30-AE30 -> 75
A31: ='Proposed Budget'!A31 -> F | B31: ='Proposed Budget'!B31 -> 43 | C31: ='Proposed Budget'!C31 -> Water Bill - Rental | D31: =(E31/(TODAY()-$I$1))*30.42 -> 64.254923 | E31: =Q31+S31+U31+W31+Y31+AA31+AC31+AE31+I31+K31+M31+O31 -> 635.79 | F31: =J31+L31+N31+P31+R31+T31+V31+X31+Z31+AB31 -> 114.21 | G31: =1-((E31/SUM(E31:F31))) -> 0.15228 | H31: ='Proposed Budget'!D31 -> 75 | I31: =SUMIFS('Checking Transaction Log'!E:E,'Checking Transaction Log'!C:C,">="&I1,'Checking Transaction Log'!C:C,"<="&J1,'Checking Transaction Log'!A:A,"F",'Checking Transaction Log'!B:B,43) -> 66.53 | J31: =H31-I31 -> 8.47 | K31: =SUMIFS('Checking Transaction Log'!E:E,'Checking Transaction Log'!C:C,">="&K1,'Checking Transaction Log'!C:C,"<="&L1,'Checking Transaction Log'!A:A,"F",'Checking Transaction Log'!B:B,43) -> 66.97 | L31: =H31-K31 -> 8.03 | M31: =SUMIFS('Checking Transaction Log'!$E:$E,'Checking Transaction Log'!$C:$C,">="&M1,'Checking Transaction Log'!$C:$C,"<="&N1,'Checking Transaction Log'!$A:$A,"F",'Checking Transaction Log'!$B:$B,43) -> 65.19 | N31: =H31-M31 -> 9.81 | O31: =SUMIFS('Checking Transaction Log'!$E:$E,'Checking Transaction Log'!$C:$C,">="&O1,'Checking Transaction Log'!$C:$C,"<="&P1,'Checking Transaction Log'!$A:$A,"F",'Checking Transaction Log'!$B:$B,43) -> 73.27 | P31: =H31-O31 -> 1.73 | Q31: =SUMIFS('Checking Transaction Log'!$E:$E,'Checking Transaction Log'!$C:$C,">="&Q1,'Checking Transaction Log'!$C:$C,"<="&R1,'Checking Transaction Log'!$A:$A,"F",'Checking Transaction Log'!$B:$B,43) -> 65.19 | R31: =H31-Q31 -> 9.81 | S31: =SUMIFS('Checking Transaction Log'!$E:$E,'Checking Transaction Log'!$C:$C,">="&S1,'Checking Transaction Log'!$C:$C,"<="&T1,'Checking Transaction Log'!$A:$A,"F",'Checking Transaction Log'!$B:$B,43) -> 72.64 | T31: =H31-S31 -> 2.36 | U31: =SUMIFS('Checking Transaction Log'!$E:$E,'Checking Transaction Log'!$C:$C,">="&U1,'Checking Transaction Log'!$C:$C,"<="&V1,'Checking Transaction Log'!$A:$A,"F",'Checking Transaction Log'!$B:$B,43) -> 73.27 | V31: =H31-U31 -> 1.73 | W31: =SUMIFS('Checking Transaction Log'!$E:$E,'Checking Transaction Log'!$C:$C,">="&W1,'Checking Transaction Log'!$C:$C,"<="&X1,'Checking Transaction Log'!$A:$A,"F",'Checking Transaction Log'!$B:$B,43) -> 65.19 | X31: =H31-W31 -> 9.81 | Y31: =SUMIFS('Checking Transaction Log'!$E:$E,'Checking Transaction Log'!$C:$C,">="&Y1,'Checking Transaction Log'!$C:$C,"<="&Z1,'Checking Transaction Log'!$A:$A,"F",'Checking Transaction Log'!$B:$B,43) -> 65.19 | Z31: =H31-Y31 -> 9.81 | AA31: =SUMIFS('Checking Transaction Log'!$E:$E,'Checking Transaction Log'!$C:$C,">="&AA1,'Checking Transaction Log'!$C:$C,"<="&AB1,'Checking Transaction Log'!$A:$A,"F",'Checking Transaction Log'!$B:$B,43) -> 22.35 | AB31: =H31-AA31 -> 52.65 | AC31: =SUMIFS('Checking Transaction Log'!$E:$E,'Checking Transaction Log'!$C:$C,">="&AC1,'Checking Transaction Log'!$C:$C,"<="&AD1,'Checking Transaction Log'!$A:$A,"F",'Checking Transaction Log'!$B:$B,43) -> 0 | AD31: =H31-AC31 -> 75 | AE31: =SUMIFS('Checking Transaction Log'!$E:$E,'Checking Transaction Log'!$C:$C,">="&AE1,'Checking Transaction Log'!$C:$C,"<="&AF1,'Checking Transaction Log'!$A:$A,"F",'Checking Transaction Log'!$B:$B,43) -> 0 | AF31: =H31-AE31 -> 75
A33: ='Proposed Budget'!A33 -> R | B33: ='Proposed Budget'!B33 -> 25 | C33: ='Proposed Budget'!C33 -> Vehicle Maintenance | D33: =(E33/(TODAY()-$I$1))*30.42 -> 318.34884 | E33: =Q33+S33+U33+W33+Y33+AA33+AC33+AE33+I33+K33+M33+O33 -> 3150 | F33: =J33+L33+N33+P33+R33+T33+V33+X33+Z33+AB33 -> 350 | G33: =1-((E33/SUM(E33:F33))) -> 0.1 | H33: ='Proposed Budget'!D33 -> 350 | I33: =SUMIFS('Checking Transaction Log'!$E:$E,'Checking Transaction Log'!$C:$C,">="&I1,'Checking Transaction Log'!$C:$C,"<="&J1,'Checking Transaction Log'!$A:$A,"R",'Checking Transaction Log'!$B:$B,25) -> 350 | J33: =H33-I33 -> 0 | K33: =SUMIFS('Checking Transaction Log'!$E:$E,'Checking Transaction Log'!$C:$C,">="&K1,'Checking Transaction Log'!$C:$C,"<="&L1,'Checking Transaction Log'!$A:$A,"R",'Checking Transaction Log'!$B:$B,25) -> 350 | L33: =H33-K33 -> 0 | M33: =SUMIFS('Checking Transaction Log'!$E:$E,'Checking Transaction Log'!$C:$C,">="&M1,'Checking Transaction Log'!$C:$C,"<="&N1,'Checking Transaction Log'!$A:$A,"R",'Checking Transaction Log'!$B:$B,25) -> 350 | N33: =H33-M33 -> 0 | O33: =SUMIFS('Checking Transaction Log'!$E:$E,'Checking Transaction Log'!$C:$C,">="&O1,'Checking Transaction Log'!$C:$C,"<="&P1,'Checking Transaction Log'!$A:$A,"R",'Checking Transaction Log'!$B:$B,25) -> 350 | P33: =H33-O33 -> 0 | Q33: =SUMIFS('Checking Transaction Log'!$E:$E,'Checking Transaction Log'!$C:$C,">="&Q1,'Checking Transaction Log'!$C:$C,"<="&R1,'Checking Transaction Log'!$A:$A,"R",'Checking Transaction Log'!$B:$B,25) -> 350 | R33: =H33-Q33 -> 0 | S33: =SUMIFS('Checking Transaction Log'!$E:$E,'Checking Transaction Log'!$C:$C,">="&S1,'Checking Transaction Log'!$C:$C,"<="&T1,'Checking Transaction Log'!$A:$A,"R",'Checking Transaction Log'!$B:$B,25) -> 350 | T33: =H33-S33 -> 0 | U33: =SUMIFS('Checking Transaction Log'!$E:$E,'Checking Transaction Log'!$C:$C,">="&U1,'Checking Transaction Log'!$C:$C,"<="&V1,'Checking Transaction Log'!$A:$A,"R",'Checking Transaction Log'!$B:$B,25) -> 350 | V33: =H33-U33 -> 0 | W33: =SUMIFS('Checking Transaction Log'!$E:$E,'Checking Transaction Log'!$C:$C,">="&W1,'Checking Transaction Log'!$C:$C,"<="&X1,'Checking Transaction Log'!$A:$A,"R",'Checking Transaction Log'!$B:$B,25) -> 350 | X33: =H33-W33 -> 0 | Y33: =SUMIFS('Checking Transaction Log'!$E:$E,'Checking Transaction Log'!$C:$C,">="&Y1,'Checking Transaction Log'!$C:$C,"<="&Z1,'Checking Transaction Log'!$A:$A,"R",'Checking Transaction Log'!$B:$B,25) -> 350 | Z33: =H33-Y33 -> 0 | AA33: =SUMIFS('Checking Transaction Log'!$E:$E,'Checking Transaction Log'!$C:$C,">="&AA1,'Checking Transaction Log'!$C:$C,"<="&AB1,'Checking Transaction Log'!$A:$A,"R",'Checking Transaction Log'!$B:$B,25) -> 0 | AB33: =H33-AA33 -> 350 | AC33: =SUMIFS('Checking Transaction Log'!$E:$E,'Checking Transaction Log'!$C:$C,">="&AC1,'Checking Transaction Log'!$C:$C,"<="&AD1,'Checking Transaction Log'!$A:$A,"R",'Checking Transaction Log'!$B:$B,25) -> 0 | AD33: =H33-AC33 -> 350 | AE33: =SUMIFS('Checking Transaction Log'!$E:$E,'Checking Transaction Log'!$C:$C,">="&AE1,'Checking Transaction Log'!$C:$C,"<="&AF1,'Checking Transaction Log'!$A:$A,"R",'Checking Transaction Log'!$B:$B,25) -> 0 | AF33: =H33-AE33 -> 350
A34: ='Proposed Budget'!A34 -> R | B34: ='Proposed Budget'!B34 -> 26 | C34: ='Proposed Budget'!C34 -> Car Insurance | D34: =(E34/(TODAY()-$I$1))*30.42 -> 291.06179 | E34: =Q34+S34+U34+W34+Y34+AA34+AC34+AE34+I34+K34+M34+O34 -> 2880 | F34: =J34+L34+N34+P34+R34+T34+V34+X34+Z34+AB34 -> 320 | G34: =1-((E34/SUM(E34:F34))) -> 0.1 | H34: ='Proposed Budget'!D34 -> 320 | I34: =SUMIFS('Checking Transaction Log'!E:E,'Checking Transaction Log'!C:C,">="&I1,'Checking Transaction Log'!C:C,"<="&J1,'Checking Transaction Log'!A:A,"R",'Checking Transaction Log'!B:B,26) -> 320 | J34: =H34-I34 -> 0 | K34: =SUMIFS('Checking Transaction Log'!$E:$E,'Checking Transaction Log'!$C:$C,">="&K1,'Checking Transaction Log'!$C:$C,"<="&L1,'Checking Transaction Log'!$A:$A,"R",'Checking Transaction Log'!$B:$B,26) -> 320 | L34: =H34-K34 -> 0 | M34: =SUMIFS('Checking Transaction Log'!$E:$E,'Checking Transaction Log'!$C:$C,">="&M1,'Checking Transaction Log'!$C:$C,"<="&N1,'Checking Transaction Log'!$A:$A,"R",'Checking Transaction Log'!$B:$B,26) -> 320 | N34: =H34-M34 -> 0 | O34: =SUMIFS('Checking Transaction Log'!$E:$E,'Checking Transaction Log'!$C:$C,">="&O1,'Checking Transaction Log'!$C:$C,"<="&P1,'Checking Transaction Log'!$A:$A,"R",'Checking Transaction Log'!$B:$B,26) -> 320 | P34: =H34-O34 -> 0 | Q34: =SUMIFS('Checking Transaction Log'!$E:$E,'Checking Transaction Log'!$C:$C,">="&Q1,'Checking Transaction Log'!$C:$C,"<="&R1,'Checking Transaction Log'!$A:$A,"R",'Checking Transaction Log'!$B:$B,26) -> 320 | R34: =H34-Q34 -> 0 | S34: =SUMIFS('Checking Transaction Log'!$E:$E,'Checking Transaction Log'!$C:$C,">="&S1,'Checking Transaction Log'!$C:$C,"<="&T1,'Checking Transaction Log'!$A:$A,"R",'Checking Transaction Log'!$B:$B,26) -> 320 | T34: =H34-S34 -> 0 | U34: =SUMIFS('Checking Transaction Log'!$E:$E,'Checking Transaction Log'!$C:$C,">="&U1,'Checking Transaction Log'!$C:$C,"<="&V1,'Checking Transaction Log'!$A:$A,"R",'Checking Transaction Log'!$B:$B,26) -> 320 | V34: =H34-U34 -> 0 | W34: =SUMIFS('Checking Transaction Log'!$E:$E,'Checking Transaction Log'!$C:$C,">="&W1,'Checking Transaction Log'!$C:$C,"<="&X1,'Checking Transaction Log'!$A:$A,"R",'Checking Transaction Log'!$B:$B,26) -> 320 | X34: =H34-W34 -> 0 | Y34: =SUMIFS('Checking Transaction Log'!$E:$E,'Checking Transaction Log'!$C:$C,">="&Y1,'Checking Transaction Log'!$C:$C,"<="&Z1,'Checking Transaction Log'!$A:$A,"R",'Checking Transaction Log'!$B:$B,26) -> 320 | Z34: =H34-Y34 -> 0 | AA34: =SUMIFS('Checking Transaction Log'!$E:$E,'Checking Transaction Log'!$C:$C,">="&AA1,'Checking Transaction Log'!$C:$C,"<="&AB1,'Checking Transaction Log'!$A:$A,"R",'Checking Transaction Log'!$B:$B,26) -> 0 | AB34: =H34-AA34 -> 320 | AC34: =SUMIFS('Checking Transaction Log'!$E:$E,'Checking Transaction Log'!$C:$C,">="&AC1,'Checking Transaction Log'!$C:$C,"<="&AD1,'Checking Transaction Log'!$A:$A,"R",'Checking Transaction Log'!$B:$B,26) -> 0 | AD34: =H34-AC34 -> 320 | AE34: =SUMIFS('Checking Transaction Log'!$E:$E,'Checking Transaction Log'!$C:$C,">="&AE1,'Checking Transaction Log'!$C:$C,"<="&AF1,'Checking Transaction Log'!$A:$A,"R",'Checking Transaction Log'!$B:$B,26) -> 0 | AF34: =H34-AE34 -> 320
A35: ='Proposed Budget'!A35 -> R | B35: ='Proposed Budget'!B35 -> 27 | C35: ='Proposed Budget'!C35 -> Rental Garbage | D35: =(E35/(TODAY()-$I$1))*30.42 -> 22.739203 | E35: =Q35+S35+U35+W35+Y35+AA35+AC35+AE35+I35+K35+M35+O35 -> 225 | F35: =J35+L35+N35+P35+R35+T35+V35+X35+Z35+AB35 -> 25 | G35: =1-((E35/SUM(E35:F35))) -> 0.1 | H35: ='Proposed Budget'!D35 -> 25 | I35: =SUMIFS('Checking Transaction Log'!E:E,'Checking Transaction Log'!C:C,">="&I1,'Checking Transaction Log'!C:C,"<="&J1,'Checking Transaction Log'!A:A,"R",'Checking Transaction Log'!B:B,27) -> 25 | J35: =H35-I35 -> 0 | K35: =SUMIFS('Checking Transaction Log'!$E:$E,'Checking Transaction Log'!$C:$C,">="&K1,'Checking Transaction Log'!$C:$C,"<="&L1,'Checking Transaction Log'!$A:$A,"R",'Checking Transaction Log'!$B:$B,27) -> 25 | L35: =H35-K35 -> 0 | M35: =SUMIFS('Checking Transaction Log'!$E:$E,'Checking Transaction Log'!$C:$C,">="&M1,'Checking Transaction Log'!$C:$C,"<="&N1,'Checking Transaction Log'!$A:$A,"R",'Checking Transaction Log'!$B:$B,27) -> 25 | N35: =H35-M35 -> 0 | O35: =SUMIFS('Checking Transaction Log'!$E:$E,'Checking Transaction Log'!$C:$C,">="&O1,'Checking Transaction Log'!$C:$C,"<="&P1,'Checking Transaction Log'!$A:$A,"R",'Checking Transaction Log'!$B:$B,27) -> 25 | P35: =H35-O35 -> 0 | Q35: =SUMIFS('Checking Transaction Log'!$E:$E,'Checking Transaction Log'!$C:$C,">="&Q1,'Checking Transaction Log'!$C:$C,"<="&R1,'Checking Transaction Log'!$A:$A,"R",'Checking Transaction Log'!$B:$B,27) -> 25 | R35: =H35-Q35 -> 0 | S35: =SUMIFS('Checking Transaction Log'!$E:$E,'Checking Transaction Log'!$C:$C,">="&S1,'Checking Transaction Log'!$C:$C,"<="&T1,'Checking Transaction Log'!$A:$A,"R",'Checking Transaction Log'!$B:$B,27) -> 25 | T35: =H35-S35 -> 0 | U35: =SUMIFS('Checking Transaction Log'!$E:$E,'Checking Transaction Log'!$C:$C,">="&U1,'Checking Transaction Log'!$C:$C,"<="&V1,'Checking Transaction Log'!$A:$A,"R",'Checking Transaction Log'!$B:$B,27) -> 25 | V35: =H35-U35 -> 0 | W35: =SUMIFS('Checking Transaction Log'!$E:$E,'Checking Transaction Log'!$C:$C,">="&W1,'Checking Transaction Log'!$C:$C,"<="&X1,'Checking Transaction Log'!$A:$A,"R",'Checking Transaction Log'!$B:$B,27) -> 25 | X35: =H35-W35 -> 0 | Y35: =SUMIFS('Checking Transaction Log'!$E:$E,'Checking Transaction Log'!$C:$C,">="&Y1,'Checking Transaction Log'!$C:$C,"<="&Z1,'Checking Transaction Log'!$A:$A,"R",'Checking Transaction Log'!$B:$B,27) -> 25 | Z35: =H35-Y35 -> 0 | AA35: =SUMIFS('Checking Transaction Log'!$E:$E,'Checking Transaction Log'!$C:$C,">="&AA1,'Checking Transaction Log'!$C:$C,"<="&AB1,'Checking Transaction Log'!$A:$A,"R",'Checking Transaction Log'!$B:$B,27) -> 0 | AB35: =H35-AA35 -> 25 | AC35: =SUMIFS('Checking Transaction Log'!$E:$E,'Checking Transaction Log'!$C:$C,">="&AC1,'Checking Transaction Log'!$C:$C,"<="&AD1,'Checking Transaction Log'!$A:$A,"R",'Checking Transaction Log'!$B:$B,27) -> 0 | AD35: =H35-AC35 -> 25 | AE35: =SUMIFS('Checking Transaction Log'!$E:$E,'Checking Transaction Log'!$C:$C,">="&AE1,'Checking Transaction Log'!$C:$C,"<="&AF1,'Checking Transaction Log'!$A:$A,"R",'Checking Transaction Log'!$B:$B,27) -> 0 | AF35: =H35-AE35 -> 25
A36: ='Proposed Budget'!A36 -> R | B36: ='Proposed Budget'!B36 -> 28 | C36: ='Proposed Budget'!C36 -> Garbage | D36: =(E36/(TODAY()-$I$1))*30.42 -> 22.739203 | E36: =Q36+S36+U36+W36+Y36+AA36+AC36+AE36+I36+K36+M36+O36 -> 225 | F36: =J36+L36+N36+P36+R36+T36+V36+X36+Z36+AB36 -> 25 | G36: =1-((E36/SUM(E36:F36))) -> 0.1 | H36: ='Proposed Budget'!D36 -> 25 | I36: =SUMIFS('Checking Transaction Log'!E:E,'Checking Transaction Log'!C:C,">="&I1,'Checking Transaction Log'!C:C,"<="&J1,'Checking Transaction Log'!A:A,"R",'Checking Transaction Log'!B:B,28) -> 25 | J36: =H36-I36 -> 0 | K36: =SUMIFS('Checking Transaction Log'!$E:$E,'Checking Transaction Log'!$C:$C,">="&K1,'Checking Transaction Log'!$C:$C,"<="&L1,'Checking Transaction Log'!$A:$A,"R",'Checking Transaction Log'!$B:$B,28) -> 25 | L36: =H36-K36 -> 0 | M36: =SUMIFS('Checking Transaction Log'!$E:$E,'Checking Transaction Log'!$C:$C,">="&M1,'Checking Transaction Log'!$C:$C,"<="&N1,'Checking Transaction Log'!$A:$A,"R",'Checking Transaction Log'!$B:$B,28) -> 25 | N36: =H36-M36 -> 0 | O36: =SUMIFS('Checking Transaction Log'!$E:$E,'Checking Transaction Log'!$C:$C,">="&O1,'Checking Transaction Log'!$C:$C,"<="&P1,'Checking Transaction Log'!$A:$A,"R",'Checking Transaction Log'!$B:$B,28) -> 25 | P36: =H36-O36 -> 0 | Q36: =SUMIFS('Checking Transaction Log'!$E:$E,'Checking Transaction Log'!$C:$C,">="&Q1,'Checking Transaction Log'!$C:$C,"<="&R1,'Checking Transaction Log'!$A:$A,"R",'Checking Transaction Log'!$B:$B,28) -> 25 | R36: =H36-Q36 -> 0 | S36: =SUMIFS('Checking Transaction Log'!$E:$E,'Checking Transaction Log'!$C:$C,">="&S1,'Checking Transaction Log'!$C:$C,"<="&T1,'Checking Transaction Log'!$A:$A,"R",'Checking Transaction Log'!$B:$B,28) -> 25 | T36: =H36-S36 -> 0 | U36: =SUMIFS('Checking Transaction Log'!$E:$E,'Checking Transaction Log'!$C:$C,">="&U1,'Checking Transaction Log'!$C:$C,"<="&V1,'Checking Transaction Log'!$A:$A,"R",'Checking Transaction Log'!$B:$B,28) -> 25 | V36: =H36-U36 -> 0 | W36: =SUMIFS('Checking Transaction Log'!$E:$E,'Checking Transaction Log'!$C:$C,">="&W1,'Checking Transaction Log'!$C:$C,"<="&X1,'Checking Transaction Log'!$A:$A,"R",'Checking Transaction Log'!$B:$B,28) -> 25 | X36: =H36-W36 -> 0 | Y36: =SUMIFS('Checking Transaction Log'!$E:$E,'Checking Transaction Log'!$C:$C,">="&Y1,'Checking Transaction Log'!$C:$C,"<="&Z1,'Checking Transaction Log'!$A:$A,"R",'Checking Transaction Log'!$B:$B,28) -> 25 | Z36: =H36-Y36 -> 0 | AA36: =SUMIFS('Checking Transaction Log'!$E:$E,'Checking Transaction Log'!$C:$C,">="&AA1,'Checking Transaction Log'!$C:$C,"<="&AB1,'Checking Transaction Log'!$A:$A,"R",'Checking Transaction Log'!$B:$B,28) -> 0 | AB36: =H36-AA36 -> 25 | AC36: =SUMIFS('Checking Transaction Log'!$E:$E,'Checking Transaction Log'!$C:$C,">="&AC1,'Checking Transaction Log'!$C:$C,"<="&AD1,'Checking Transaction Log'!$A:$A,"R",'Checking Transaction Log'!$B:$B,28) -> 0 | AD36: =H36-AC36 -> 25 | AE36: =SUMIFS('Checking Transaction Log'!$E:$E,'Checking Transaction Log'!$C:$C,">="&AE1,'Checking Transaction Log'!$C:$C,"<="&AF1,'Checking Transaction Log'!$A:$A,"R",'Checking Transaction Log'!$B:$B,28) -> 0 | AF36: =H36-AE36 -> 25
A37: ='Proposed Budget'!A37 -> R | B37: ='Proposed Budget'!B37 -> 29 | C37: ='Proposed Budget'!C37 -> Sanitation - Main | D37: =(E37/(TODAY()-$I$1))*30.42 -> 40.930565 | E37: =Q37+S37+U37+W37+Y37+AA37+AC37+AE37+I37+K37+M37+O37 -> 405 | F37: =J37+L37+N37+P37+R37+T37+V37+X37+Z37+AB37 -> 45 | G37: =1-((E37/SUM(E37:F37))) -> 0.1 | H37: ='Proposed Budget'!D37 -> 45 | I37: =SUMIFS('Checking Transaction Log'!E:E,'Checking Transaction Log'!C:C,">="&I1,'Checking Transaction Log'!C:C,"<="&J1,'Checking Transaction Log'!A:A,"R",'Checking Transaction Log'!B:B,29) -> 45 | J37: =H37-I37 -> 0 | K37: =SUMIFS('Checking Transaction Log'!$E:$E,'Checking Transaction Log'!$C:$C,">="&K1,'Checking Transaction Log'!$C:$C,"<="&L1,'Checking Transaction Log'!$A:$A,"R",'Checking Transaction Log'!$B:$B,29) -> 45 | L37: =H37-K37 -> 0 | M37: =SUMIFS('Checking Transaction Log'!$E:$E,'Checking Transaction Log'!$C:$C,">="&M1,'Checking Transaction Log'!$C:$C,"<="&N1,'Checking Transaction Log'!$A:$A,"R",'Checking Transaction Log'!$B:$B,29) -> 45 | N37: =H37-M37 -> 0 | O37: =SUMIFS('Checking Transaction Log'!$E:$E,'Checking Transaction Log'!$C:$C,">="&O1,'Checking Transaction Log'!$C:$C,"<="&P1,'Checking Transaction Log'!$A:$A,"R",'Checking Transaction Log'!$B:$B,29) -> 45 | P37: =H37-O37 -> 0 | Q37: =SUMIFS('Checking Transaction Log'!$E:$E,'Checking Transaction Log'!$C:$C,">="&Q1,'Checking Transaction Log'!$C:$C,"<="&R1,'Checking Transaction Log'!$A:$A,"R",'Checking Transaction Log'!$B:$B,29) -> 45 | R37: =H37-Q37 -> 0 | S37: =SUMIFS('Checking Transaction Log'!$E:$E,'Checking Transaction Log'!$C:$C,">="&S1,'Checking Transaction Log'!$C:$C,"<="&T1,'Checking Transaction Log'!$A:$A,"R",'Checking Transaction Log'!$B:$B,29) -> 45 | T37: =H37-S37 -> 0 | U37: =SUMIFS('Checking Transaction Log'!$E:$E,'Checking Transaction Log'!$C:$C,">="&U1,'Checking Transaction Log'!$C:$C,"<="&V1,'Checking Transaction Log'!$A:$A,"R",'Checking Transaction Log'!$B:$B,29) -> 45 | V37: =H37-U37 -> 0 | W37: =SUMIFS('Checking Transaction Log'!$E:$E,'Checking Transaction Log'!$C:$C,">="&W1,'Checking Transaction Log'!$C:$C,"<="&X1,'Checking Transaction Log'!$A:$A,"R",'Checking Transaction Log'!$B:$B,29) -> 45 | X37: =H37-W37 -> 0 | Y37: =SUMIFS('Checking Transaction Log'!$E:$E,'Checking Transaction Log'!$C:$C,">="&Y1,'Checking Transaction Log'!$C:$C,"<="&Z1,'Checking Transaction Log'!$A:$A,"R",'Checking Transaction Log'!$B:$B,29) -> 45 | Z37: =H37-Y37 -> 0 | AA37: =SUMIFS('Checking Transaction Log'!$E:$E,'Checking Transaction Log'!$C:$C,">="&AA1,'Checking Transaction Log'!$C:$C,"<="&AB1,'Checking Transaction Log'!$A:$A,"R",'Checking Transaction Log'!$B:$B,29) -> 0 | AB37: =H37-AA37 -> 45 | AC37: =SUMIFS('Checking Transaction Log'!$E:$E,'Checking Transaction Log'!$C:$C,">="&AC1,'Checking Transaction Log'!$C:$C,"<="&AD1,'Checking Transaction Log'!$A:$A,"R",'Checking Transaction Log'!$B:$B,29) -> 0 | AD37: =H37-AC37 -> 45 | AE37: =SUMIFS('Checking Transaction Log'!$E:$E,'Checking Transaction Log'!$C:$C,">="&AE1,'Checking Transaction Log'!$C:$C,"<="&AF1,'Checking Transaction Log'!$A:$A,"R",'Checking Transaction Log'!$B:$B,29) -> 0 | AF37: =H37-AE37 -> 45
A38: ='Proposed Budget'!A38 -> R | B38: ='Proposed Budget'!B38 -> 30 | C38: ='Proposed Budget'!C38 -> Camping/Vacation | D38: =(E38/(TODAY()-$I$1))*30.42 -> 363.82724 | E38: =Q38+S38+U38+W38+Y38+AA38+AC38+AE38+I38+K38+M38+O38 -> 3600 | F38: =J38+L38+N38+P38+R38+T38+V38+X38+Z38+AB38 -> 400 | G38: =1-((E38/SUM(E38:F38))) -> 0.1 | H38: ='Proposed Budget'!D38 -> 400 | I38: =SUMIFS('Checking Transaction Log'!E:E,'Checking Transaction Log'!C:C,">="&I1,'Checking Transaction Log'!C:C,"<="&J1,'Checking Transaction Log'!A:A,"R",'Checking Transaction Log'!B:B,30) -> 400 | J38: =H38-I38 -> 0 | K38: =SUMIFS('Checking Transaction Log'!$E:$E,'Checking Transaction Log'!$C:$C,">="&K1,'Checking Transaction Log'!$C:$C,"<="&L1,'Checking Transaction Log'!$A:$A,"R",'Checking Transaction Log'!$B:$B,30) -> 400 | L38: =H38-K38 -> 0 | M38: =SUMIFS('Checking Transaction Log'!$E:$E,'Checking Transaction Log'!$C:$C,">="&M1,'Checking Transaction Log'!$C:$C,"<="&N1,'Checking Transaction Log'!$A:$A,"R",'Checking Transaction Log'!$B:$B,30) -> 400 | N38: =H38-M38 -> 0 | O38: =SUMIFS('Checking Transaction Log'!$E:$E,'Checking Transaction Log'!$C:$C,">="&O1,'Checking Transaction Log'!$C:$C,"<="&P1,'Checking Transaction Log'!$A:$A,"R",'Checking Transaction Log'!$B:$B,30) -> 400 | P38: =H38-O38 -> 0 | Q38: =SUMIFS('Checking Transaction Log'!$E:$E,'Checking Transaction Log'!$C:$C,">="&Q1,'Checking Transaction Log'!$C:$C,"<="&R1,'Checking Transaction Log'!$A:$A,"R",'Checking Transaction Log'!$B:$B,30) -> 400 | R38: =H38-Q38 -> 0 | S38: =SUMIFS('Checking Transaction Log'!$E:$E,'Checking Transaction Log'!$C:$C,">="&S1,'Checking Transaction Log'!$C:$C,"<="&T1,'Checking Transaction Log'!$A:$A,"R",'Checking Transaction Log'!$B:$B,30) -> 400 | T38: =H38-S38 -> 0 | U38: =SUMIFS('Checking Transaction Log'!$E:$E,'Checking Transaction Log'!$C:$C,">="&U1,'Checking Transaction Log'!$C:$C,"<="&V1,'Checking Transaction Log'!$A:$A,"R",'Checking Transaction Log'!$B:$B,30) -> 400 | V38: =H38-U38 -> 0 | W38: =SUMIFS('Checking Transaction Log'!$E:$E,'Checking Transaction Log'!$C:$C,">="&W1,'Checking Transaction Log'!$C:$C,"<="&X1,'Checking Transaction Log'!$A:$A,"R",'Checking Transaction Log'!$B:$B,30) -> 400 | X38: =H38-W38 -> 0 | Y38: =SUMIFS('Checking Transaction Log'!$E:$E,'Checking Transaction Log'!$C:$C,">="&Y1,'Checking Transaction Log'!$C:$C,"<="&Z1,'Checking Transaction Log'!$A:$A,"R",'Checking Transaction Log'!$B:$B,30) -> 400 | Z38: =H38-Y38 -> 0 | AA38: =SUMIFS('Checking Transaction Log'!$E:$E,'Checking Transaction Log'!$C:$C,">="&AA1,'Checking Transaction Log'!$C:$C,"<="&AB1,'Checking Transaction Log'!$A:$A,"R",'Checking Transaction Log'!$B:$B,30) -> 0 | AB38: =H38-AA38 -> 400 | AC38: =SUMIFS('Checking Transaction Log'!$E:$E,'Checking Transaction Log'!$C:$C,">="&AC1,'Checking Transaction Log'!$C:$C,"<="&AD1,'Checking Transaction Log'!$A:$A,"R",'Checking Transaction Log'!$B:$B,30) -> 0 | AD38: =H38-AC38 -> 400 | AE38: =SUMIFS('Checking Transaction Log'!$E:$E,'Checking Transaction Log'!$C:$C,">="&AE1,'Checking Transaction Log'!$C:$C,"<="&AF1,'Checking Transaction Log'!$A:$A,"R",'Checking Transaction Log'!$B:$B,30) -> 0 | AF38: =H38-AE38 -> 400
A39: ='Proposed Budget'!A39 -> R | B39: ='Proposed Budget'!B39 -> 31 | C39: ='Proposed Budget'!C39 -> Home Maintenance | D39: =(E39/(TODAY()-$I$1))*30.42 -> 341.08804 | E39: =Q39+S39+U39+W39+Y39+AA39+AC39+AE39+I39+K39+M39+O39 -> 3375 | F39: =J39+L39+N39+P39+R39+T39+V39+X39+Z39+AB39 -> 375 | G39: =1-((E39/SUM(E39:F39))) -> 0.1 | H39: ='Proposed Budget'!D39 -> 375 | I39: =SUMIFS('Checking Transaction Log'!E:E,'Checking Transaction Log'!C:C,">="&I1,'Checking Transaction Log'!C:C,"<="&J1,'Checking Transaction Log'!A:A,"R",'Checking Transaction Log'!B:B,31) -> 375 | J39: =H39-I39 -> 0 | K39: =SUMIFS('Checking Transaction Log'!$E:$E,'Checking Transaction Log'!$C:$C,">="&K1,'Checking Transaction Log'!$C:$C,"<="&L1,'Checking Transaction Log'!$A:$A,"R",'Checking Transaction Log'!$B:$B,31) -> 375 | L39: =H39-K39 -> 0 | M39: =SUMIFS('Checking Transaction Log'!$E:$E,'Checking Transaction Log'!$C:$C,">="&M1,'Checking Transaction Log'!$C:$C,"<="&N1,'Checking Transaction Log'!$A:$A,"R",'Checking Transaction Log'!$B:$B,31) -> 375 | N39: =H39-M39 -> 0 | O39: =SUMIFS('Checking Transaction Log'!$E:$E,'Checking Transaction Log'!$C:$C,">="&O1,'Checking Transaction Log'!$C:$C,"<="&P1,'Checking Transaction Log'!$A:$A,"R",'Checking Transaction Log'!$B:$B,31) -> 375 | P39: =H39-O39 -> 0 | Q39: =SUMIFS('Checking Transaction Log'!$E:$E,'Checking Transaction Log'!$C:$C,">="&Q1,'Checking Transaction Log'!$C:$C,"<="&R1,'Checking Transaction Log'!$A:$A,"R",'Checking Transaction Log'!$B:$B,31) -> 375 | R39: =H39-Q39 -> 0 | S39: =SUMIFS('Checking Transaction Log'!$E:$E,'Checking Transaction Log'!$C:$C,">="&S1,'Checking Transaction Log'!$C:$C,"<="&T1,'Checking Transaction Log'!$A:$A,"R",'Checking Transaction Log'!$B:$B,31) -> 375 | T39: =H39-S39 -> 0 | U39: =SUMIFS('Checking Transaction Log'!$E:$E,'Checking Transaction Log'!$C:$C,">="&U1,'Checking Transaction Log'!$C:$C,"<="&V1,'Checking Transaction Log'!$A:$A,"R",'Checking Transaction Log'!$B:$B,31) -> 375 | V39: =H39-U39 -> 0 | W39: =SUMIFS('Checking Transaction Log'!$E:$E,'Checking Transaction Log'!$C:$C,">="&W1,'Checking Transaction Log'!$C:$C,"<="&X1,'Checking Transaction Log'!$A:$A,"R",'Checking Transaction Log'!$B:$B,31) -> 375 | X39: =H39-W39 -> 0 | Y39: =SUMIFS('Checking Transaction Log'!$E:$E,'Checking Transaction Log'!$C:$C,">="&Y1,'Checking Transaction Log'!$C:$C,"<="&Z1,'Checking Transaction Log'!$A:$A,"R",'Checking Transaction Log'!$B:$B,31) -> 375 | Z39: =H39-Y39 -> 0 | AA39: =SUMIFS('Checking Transaction Log'!$E:$E,'Checking Transaction Log'!$C:$C,">="&AA1,'Checking Transaction Log'!$C:$C,"<="&AB1,'Checking Transaction Log'!$A:$A,"R",'Checking Transaction Log'!$B:$B,31) -> 0 | AB39: =H39-AA39 -> 375 | AC39: =SUMIFS('Checking Transaction Log'!$E:$E,'Checking Transaction Log'!$C:$C,">="&AC1,'Checking Transaction Log'!$C:$C,"<="&AD1,'Checking Transaction Log'!$A:$A,"R",'Checking Transaction Log'!$B:$B,31) -> 0 | AD39: =H39-AC39 -> 375 | AE39: =SUMIFS('Checking Transaction Log'!$E:$E,'Checking Transaction Log'!$C:$C,">="&AE1,'Checking Transaction Log'!$C:$C,"<="&AF1,'Checking Transaction Log'!$A:$A,"R",'Checking Transaction Log'!$B:$B,31) -> 0 | AF39: =H39-AE39 -> 375
A40: ='Proposed Budget'!A40 -> R | B40: ='Proposed Budget'!B40 -> 32 | C40: ='Proposed Budget'!C40 -> Rental Repairs | D40: =(E40/(TODAY()-$I$1))*30.42 -> 90.956811 | E40: =Q40+S40+U40+W40+Y40+AA40+AC40+AE40+I40+K40+M40+O40 -> 900 | F40: =J40+L40+N40+P40+R40+T40+V40+X40+Z40+AB40 -> 100 | G40: =1-((E40/SUM(E40:F40))) -> 0.1 | H40: ='Proposed Budget'!D40 -> 100 | I40: =SUMIFS('Checking Transaction Log'!E:E,'Checking Transaction Log'!C:C,">="&I1,'Checking Transaction Log'!C:C,"<="&J1,'Checking Transaction Log'!A:A,"R",'Checking Transaction Log'!B:B,32) -> 100 | J40: =H40-I40 -> 0 | K40: =SUMIFS('Checking Transaction Log'!$E:$E,'Checking Transaction Log'!$C:$C,">="&K1,'Checking Transaction Log'!$C:$C,"<="&L1,'Checking Transaction Log'!$A:$A,"R",'Checking Transaction Log'!$B:$B,32) -> 100 | L40: =H40-K40 -> 0 | M40: =SUMIFS('Checking Transaction Log'!$E:$E,'Checking Transaction Log'!$C:$C,">="&M1,'Checking Transaction Log'!$C:$C,"<="&N1,'Checking Transaction Log'!$A:$A,"R",'Checking Transaction Log'!$B:$B,32) -> 100 | N40: =H40-M40 -> 0 | O40: =SUMIFS('Checking Transaction Log'!$E:$E,'Checking Transaction Log'!$C:$C,">="&O1,'Checking Transaction Log'!$C:$C,"<="&P1,'Checking Transaction Log'!$A:$A,"R",'Checking Transaction Log'!$B:$B,32) -> 100 | P40: =H40-O40 -> 0 | Q40: =SUMIFS('Checking Transaction Log'!$E:$E,'Checking Transaction Log'!$C:$C,">="&Q1,'Checking Transaction Log'!$C:$C,"<="&R1,'Checking Transaction Log'!$A:$A,"R",'Checking Transaction Log'!$B:$B,32) -> 100 | R40: =H40-Q40 -> 0 | S40: =SUMIFS('Checking Transaction Log'!$E:$E,'Checking Transaction Log'!$C:$C,">="&S1,'Checking Transaction Log'!$C:$C,"<="&T1,'Checking Transaction Log'!$A:$A,"R",'Checking Transaction Log'!$B:$B,32) -> 100 | T40: =H40-S40 -> 0 | U40: =SUMIFS('Checking Transaction Log'!$E:$E,'Checking Transaction Log'!$C:$C,">="&U1,'Checking Transaction Log'!$C:$C,"<="&V1,'Checking Transaction Log'!$A:$A,"R",'Checking Transaction Log'!$B:$B,32) -> 100 | V40: =H40-U40 -> 0 | W40: =SUMIFS('Checking Transaction Log'!$E:$E,'Checking Transaction Log'!$C:$C,">="&W1,'Checking Transaction Log'!$C:$C,"<="&X1,'Checking Transaction Log'!$A:$A,"R",'Checking Transaction Log'!$B:$B,32) -> 100 | X40: =H40-W40 -> 0 | Y40: =SUMIFS('Checking Transaction Log'!$E:$E,'Checking Transaction Log'!$C:$C,">="&Y1,'Checking Transaction Log'!$C:$C,"<="&Z1,'Checking Transaction Log'!$A:$A,"R",'Checking Transaction Log'!$B:$B,32) -> 100 | Z40: =H40-Y40 -> 0 | AA40: =SUMIFS('Checking Transaction Log'!$E:$E,'Checking Transaction Log'!$C:$C,">="&AA1,'Checking Transaction Log'!$C:$C,"<="&AB1,'Checking Transaction Log'!$A:$A,"R",'Checking Transaction Log'!$B:$B,32) -> 0 | AB40: =H40-AA40 -> 100 | AC40: =SUMIFS('Checking Transaction Log'!$E:$E,'Checking Transaction Log'!$C:$C,">="&AC1,'Checking Transaction Log'!$C:$C,"<="&AD1,'Checking Transaction Log'!$A:$A,"R",'Checking Transaction Log'!$B:$B,32) -> 0 | AD40: =H40-AC40 -> 100 | AE40: =SUMIFS('Checking Transaction Log'!$E:$E,'Checking Transaction Log'!$C:$C,">="&AE1,'Checking Transaction Log'!$C:$C,"<="&AF1,'Checking Transaction Log'!$A:$A,"R",'Checking Transaction Log'!$B:$B,32) -> 0 | AF40: =H40-AE40 -> 100
A41: ='Proposed Budget'!A41 -> R | B41: ='Proposed Budget'!B41 -> 33 | C41: ='Proposed Budget'!C41 -> Rental Insurance | D41: =(E41/(TODAY()-$I$1))*30.42 -> 77.313289 | E41: =Q41+S41+U41+W41+Y41+AA41+AC41+AE41+I41+K41+M41+O41 -> 765 | F41: =J41+L41+N41+P41+R41+T41+V41+X41+Z41+AB41 -> 85 | G41: =1-((E41/SUM(E41:F41))) -> 0.1 | H41: ='Proposed Budget'!D41 -> 85 | I41: =SUMIFS('Checking Transaction Log'!E:E,'Checking Transaction Log'!C:C,">="&I1,'Checking Transaction Log'!C:C,"<="&J1,'Checking Transaction Log'!A:A,"R",'Checking Transaction Log'!B:B,33) -> 85 | J41: =H41-I41 -> 0 | K41: =SUMIFS('Checking Transaction Log'!$E:$E,'Checking Transaction Log'!$C:$C,">="&K1,'Checking Transaction Log'!$C:$C,"<="&L1,'Checking Transaction Log'!$A:$A,"R",'Checking Transaction Log'!$B:$B,33) -> 85 | L41: =H41-K41 -> 0 | M41: =SUMIFS('Checking Transaction Log'!$E:$E,'Checking Transaction Log'!$C:$C,">="&M1,'Checking Transaction Log'!$C:$C,"<="&N1,'Checking Transaction Log'!$A:$A,"R",'Checking Transaction Log'!$B:$B,33) -> 85 | N41: =H41-M41 -> 0 | O41: =SUMIFS('Checking Transaction Log'!$E:$E,'Checking Transaction Log'!$C:$C,">="&O1,'Checking Transaction Log'!$C:$C,"<="&P1,'Checking Transaction Log'!$A:$A,"R",'Checking Transaction Log'!$B:$B,33) -> 85 | P41: =H41-O41 -> 0 | Q41: =SUMIFS('Checking Transaction Log'!$E:$E,'Checking Transaction Log'!$C:$C,">="&Q1,'Checking Transaction Log'!$C:$C,"<="&R1,'Checking Transaction Log'!$A:$A,"R",'Checking Transaction Log'!$B:$B,33) -> 85 | R41: =H41-Q41 -> 0 | S41: =SUMIFS('Checking Transaction Log'!$E:$E,'Checking Transaction Log'!$C:$C,">="&S1,'Checking Transaction Log'!$C:$C,"<="&T1,'Checking Transaction Log'!$A:$A,"R",'Checking Transaction Log'!$B:$B,33) -> 85 | T41: =H41-S41 -> 0 | U41: =SUMIFS('Checking Transaction Log'!$E:$E,'Checking Transaction Log'!$C:$C,">="&U1,'Checking Transaction Log'!$C:$C,"<="&V1,'Checking Transaction Log'!$A:$A,"R",'Checking Transaction Log'!$B:$B,33) -> 85 | V41: =H41-U41 -> 0 | W41: =SUMIFS('Checking Transaction Log'!$E:$E,'Checking Transaction Log'!$C:$C,">="&W1,'Checking Transaction Log'!$C:$C,"<="&X1,'Checking Transaction Log'!$A:$A,"R",'Checking Transaction Log'!$B:$B,33) -> 85 | X41: =H41-W41 -> 0 | Y41: =SUMIFS('Checking Transaction Log'!$E:$E,'Checking Transaction Log'!$C:$C,">="&Y1,'Checking Transaction Log'!$C:$C,"<="&Z1,'Checking Transaction Log'!$A:$A,"R",'Checking Transaction Log'!$B:$B,33) -> 85 | Z41: =H41-Y41 -> 0 | AA41: =SUMIFS('Checking Transaction Log'!$E:$E,'Checking Transaction Log'!$C:$C,">="&AA1,'Checking Transaction Log'!$C:$C,"<="&AB1,'Checking Transaction Log'!$A:$A,"R",'Checking Transaction Log'!$B:$B,33) -> 0 | AB41: =H41-AA41 -> 85 | AC41: =SUMIFS('Checking Transaction Log'!$E:$E,'Checking Transaction Log'!$C:$C,">="&AC1,'Checking Transaction Log'!$C:$C,"<="&AD1,'Checking Transaction Log'!$A:$A,"R",'Checking Transaction Log'!$B:$B,33) -> 0 | AD41: =H41-AC41 -> 85 | AE41: =SUMIFS('Checking Transaction Log'!$E:$E,'Checking Transaction Log'!$C:$C,">="&AE1,'Checking Transaction Log'!$C:$C,"<="&AF1,'Checking Transaction Log'!$A:$A,"R",'Checking Transaction Log'!$B:$B,33) -> 0 | AF41: =H41-AE41 -> 85
A42: ='Proposed Budget'!A42 -> R | B42: ='Proposed Budget'!B42 -> 34 | C42: ='Proposed Budget'!C42 -> Rental Property Taxes | D42: =(E42/(TODAY()-$I$1))*30.42 -> 209.20066 | E42: =Q42+S42+U42+W42+Y42+AA42+AC42+AE42+I42+K42+M42+O42 -> 2070 | F42: =J42+L42+N42+P42+R42+T42+V42+X42+Z42+AB42 -> 230 | G42: =1-((E42/SUM(E42:F42))) -> 0.1 | H42: ='Proposed Budget'!D42 -> 230 | I42: =SUMIFS('Checking Transaction Log'!E:E,'Checking Transaction Log'!C:C,">="&I1,'Checking Transaction Log'!C:C,"<="&J1,'Checking Transaction Log'!A:A,"R",'Checking Transaction Log'!B:B,34) -> 230 | J42: =H42-I42 -> 0 | K42: =SUMIFS('Checking Transaction Log'!$E:$E,'Checking Transaction Log'!$C:$C,">="&K1,'Checking Transaction Log'!$C:$C,"<="&L1,'Checking Transaction Log'!$A:$A,"R",'Checking Transaction Log'!$B:$B,34) -> 230 | L42: =H42-K42 -> 0 | M42: =SUMIFS('Checking Transaction Log'!$E:$E,'Checking Transaction Log'!$C:$C,">="&M1,'Checking Transaction Log'!$C:$C,"<="&N1,'Checking Transaction Log'!$A:$A,"R",'Checking Transaction Log'!$B:$B,34) -> 230 | N42: =H42-M42 -> 0 | O42: =SUMIFS('Checking Transaction Log'!$E:$E,'Checking Transaction Log'!$C:$C,">="&O1,'Checking Transaction Log'!$C:$C,"<="&P1,'Checking Transaction Log'!$A:$A,"R",'Checking Transaction Log'!$B:$B,34) -> 230 | P42: =H42-O42 -> 0 | Q42: =SUMIFS('Checking Transaction Log'!$E:$E,'Checking Transaction Log'!$C:$C,">="&Q1,'Checking Transaction Log'!$C:$C,"<="&R1,'Checking Transaction Log'!$A:$A,"R",'Checking Transaction Log'!$B:$B,34) -> 230 | R42: =H42-Q42 -> 0 | S42: =SUMIFS('Checking Transaction Log'!$E:$E,'Checking Transaction Log'!$C:$C,">="&S1,'Checking Transaction Log'!$C:$C,"<="&T1,'Checking Transaction Log'!$A:$A,"R",'Checking Transaction Log'!$B:$B,34) -> 230 | T42: =H42-S42 -> 0 | U42: =SUMIFS('Checking Transaction Log'!$E:$E,'Checking Transaction Log'!$C:$C,">="&U1,'Checking Transaction Log'!$C:$C,"<="&V1,'Checking Transaction Log'!$A:$A,"R",'Checking Transaction Log'!$B:$B,34) -> 230 | V42: =H42-U42 -> 0 | W42: =SUMIFS('Checking Transaction Log'!$E:$E,'Checking Transaction Log'!$C:$C,">="&W1,'Checking Transaction Log'!$C:$C,"<="&X1,'Checking Transaction Log'!$A:$A,"R",'Checking Transaction Log'!$B:$B,34) -> 230 | X42: =H42-W42 -> 0 | Y42: =SUMIFS('Checking Transaction Log'!$E:$E,'Checking Transaction Log'!$C:$C,">="&Y1,'Checking Transaction Log'!$C:$C,"<="&Z1,'Checking Transaction Log'!$A:$A,"R",'Checking Transaction Log'!$B:$B,34) -> 230 | Z42: =H42-Y42 -> 0 | AA42: =SUMIFS('Checking Transaction Log'!$E:$E,'Checking Transaction Log'!$C:$C,">="&AA1,'Checking Transaction Log'!$C:$C,"<="&AB1,'Checking Transaction Log'!$A:$A,"R",'Checking Transaction Log'!$B:$B,34) -> 0 | AB42: =H42-AA42 -> 230 | AC42: =SUMIFS('Checking Transaction Log'!$E:$E,'Checking Transaction Log'!$C:$C,">="&AC1,'Checking Transaction Log'!$C:$C,"<="&AD1,'Checking Transaction Log'!$A:$A,"R",'Checking Transaction Log'!$B:$B,34) -> 0 | AD42: =H42-AC42 -> 230 | AE42: =SUMIFS('Checking Transaction Log'!$E:$E,'Checking Transaction Log'!$C:$C,">="&AE1,'Checking Transaction Log'!$C:$C,"<="&AF1,'Checking Transaction Log'!$A:$A,"R",'Checking Transaction Log'!$B:$B,34) -> 0 | AF42: =H42-AE42 -> 230
A43: ='Proposed Budget'!A43 -> R | B43: ='Proposed Budget'!B43 -> 35 | C43: ='Proposed Budget'!C43 -> Rental Sanitation | D43: =(E43/(TODAY()-$I$1))*30.42 -> 40.930565 | E43: =Q43+S43+U43+W43+Y43+AA43+AC43+AE43+I43+K43+M43+O43 -> 405 | F43: =J43+L43+N43+P43+R43+T43+V43+X43+Z43+AB43 -> 45 | G43: =1-((E43/SUM(E43:F43))) -> 0.1 | H43: ='Proposed Budget'!D43 -> 45 | I43: =SUMIFS('Checking Transaction Log'!E:E,'Checking Transaction Log'!C:C,">="&I1,'Checking Transaction Log'!C:C,"<="&J1,'Checking Transaction Log'!A:A,"R",'Checking Transaction Log'!B:B,35) -> 45 | J43: =H43-I43 -> 0 | K43: =SUMIFS('Checking Transaction Log'!$E:$E,'Checking Transaction Log'!$C:$C,">="&K1,'Checking Transaction Log'!$C:$C,"<="&L1,'Checking Transaction Log'!$A:$A,"R",'Checking Transaction Log'!$B:$B,35) -> 45 | L43: =H43-K43 -> 0 | M43: =SUMIFS('Checking Transaction Log'!$E:$E,'Checking Transaction Log'!$C:$C,">="&M1,'Checking Transaction Log'!$C:$C,"<="&N1,'Checking Transaction Log'!$A:$A,"R",'Checking Transaction Log'!$B:$B,35) -> 45 | N43: =H43-M43 -> 0 | O43: =SUMIFS('Checking Transaction Log'!$E:$E,'Checking Transaction Log'!$C:$C,">="&O1,'Checking Transaction Log'!$C:$C,"<="&P1,'Checking Transaction Log'!$A:$A,"R",'Checking Transaction Log'!$B:$B,35) -> 45 | P43: =H43-O43 -> 0 | Q43: =SUMIFS('Checking Transaction Log'!$E:$E,'Checking Transaction Log'!$C:$C,">="&Q1,'Checking Transaction Log'!$C:$C,"<="&R1,'Checking Transaction Log'!$A:$A,"R",'Checking Transaction Log'!$B:$B,35) -> 45 | R43: =H43-Q43 -> 0 | S43: =SUMIFS('Checking Transaction Log'!$E:$E,'Checking Transaction Log'!$C:$C,">="&S1,'Checking Transaction Log'!$C:$C,"<="&T1,'Checking Transaction Log'!$A:$A,"R",'Checking Transaction Log'!$B:$B,35) -> 45 | T43: =H43-S43 -> 0 | U43: =SUMIFS('Checking Transaction Log'!$E:$E,'Checking Transaction Log'!$C:$C,">="&U1,'Checking Transaction Log'!$C:$C,"<="&V1,'Checking Transaction Log'!$A:$A,"R",'Checking Transaction Log'!$B:$B,35) -> 45 | V43: =H43-U43 -> 0 | W43: =SUMIFS('Checking Transaction Log'!$E:$E,'Checking Transaction Log'!$C:$C,">="&W1,'Checking Transaction Log'!$C:$C,"<="&X1,'Checking Transaction Log'!$A:$A,"R",'Checking Transaction Log'!$B:$B,35) -> 45 | X43: =H43-W43 -> 0 | Y43: =SUMIFS('Checking Transaction Log'!$E:$E,'Checking Transaction Log'!$C:$C,">="&Y1,'Checking Transaction Log'!$C:$C,"<="&Z1,'Checking Transaction Log'!$A:$A,"R",'Checking Transaction Log'!$B:$B,35) -> 45 | Z43: =H43-Y43 -> 0 | AA43: =SUMIFS('Checking Transaction Log'!$E:$E,'Checking Transaction Log'!$C:$C,">="&AA1,'Checking Transaction Log'!$C:$C,"<="&AB1,'Checking Transaction Log'!$A:$A,"R",'Checking Transaction Log'!$B:$B,35) -> 0 | AB43: =H43-AA43 -> 45 | AC43: =SUMIFS('Checking Transaction Log'!$E:$E,'Checking Transaction Log'!$C:$C,">="&AC1,'Checking Transaction Log'!$C:$C,"<="&AD1,'Checking Transaction Log'!$A:$A,"R",'Checking Transaction Log'!$B:$B,35) -> 0 | AD43: =H43-AC43 -> 45 | AE43: =SUMIFS('Checking Transaction Log'!$E:$E,'Checking Transaction Log'!$C:$C,">="&AE1,'Checking Transaction Log'!$C:$C,"<="&AF1,'Checking Transaction Log'!$A:$A,"R",'Checking Transaction Log'!$B:$B,35) -> 0 | AF43: =H43-AE43 -> 45
A45: ='Proposed Budget'!A45 -> S | B45: ='Proposed Budget'!B45 -> 36 | C45: ='Proposed Budget'!C45 -> Kids Savings | D45: =(E45/(TODAY()-$I$1))*30.42 -> 45.478405 | E45: =Q45+S45+U45+W45+Y45+AA45+AC45+AE45+I45+K45+M45+O45 -> 450 | F45: =J45+L45+N45+P45+R45+T45+V45+X45+Z45+AB45 -> 50 | G45: =1-((E45/SUM(E45:F45))) -> 0.1 | H45: ='Proposed Budget'!D45 -> 50 | I45: =SUMIFS('Checking Transaction Log'!E:E,'Checking Transaction Log'!C:C,">="&I1,'Checking Transaction Log'!C:C,"<="&J1,'Checking Transaction Log'!A:A,"S",'Checking Transaction Log'!B:B,36) -> 50 | J45: =H45-I45 -> 0 | K45: =SUMIFS('Checking Transaction Log'!E:E,'Checking Transaction Log'!C:C,">="&K1,'Checking Transaction Log'!C:C,"<="&L1,'Checking Transaction Log'!A:A,"S",'Checking Transaction Log'!B:B,36) -> 50 | L45: =H45-K45 -> 0 | M45: =SUMIFS('Checking Transaction Log'!$E:$E,'Checking Transaction Log'!$C:$C,">="&M1,'Checking Transaction Log'!$C:$C,"<="&N1,'Checking Transaction Log'!$A:$A,"s",'Checking Transaction Log'!$B:$B,36) -> 50 | N45: =H45-M45 -> 0 | O45: =SUMIFS('Checking Transaction Log'!$E:$E,'Checking Transaction Log'!$C:$C,">="&O1,'Checking Transaction Log'!$C:$C,"<="&P1,'Checking Transaction Log'!$A:$A,"s",'Checking Transaction Log'!$B:$B,36) -> 50 | P45: =H45-O45 -> 0 | Q45: =SUMIFS('Checking Transaction Log'!$E:$E,'Checking Transaction Log'!$C:$C,">="&Q1,'Checking Transaction Log'!$C:$C,"<="&R1,'Checking Transaction Log'!$A:$A,"s",'Checking Transaction Log'!$B:$B,36) -> 50 | R45: =H45-Q45 -> 0 | S45: =SUMIFS('Checking Transaction Log'!$E:$E,'Checking Transaction Log'!$C:$C,">="&S1,'Checking Transaction Log'!$C:$C,"<="&T1,'Checking Transaction Log'!$A:$A,"s",'Checking Transaction Log'!$B:$B,36) -> 50 | T45: =H45-S45 -> 0 | U45: =SUMIFS('Checking Transaction Log'!$E:$E,'Checking Transaction Log'!$C:$C,">="&U1,'Checking Transaction Log'!$C:$C,"<="&V1,'Checking Transaction Log'!$A:$A,"s",'Checking Transaction Log'!$B:$B,36) -> 50 | V45: =H45-U45 -> 0 | W45: =SUMIFS('Checking Transaction Log'!$E:$E,'Checking Transaction Log'!$C:$C,">="&W1,'Checking Transaction Log'!$C:$C,"<="&X1,'Checking Transaction Log'!$A:$A,"s",'Checking Transaction Log'!$B:$B,36) -> 50 | X45: =H45-W45 -> 0 | Y45: =SUMIFS('Checking Transaction Log'!$E:$E,'Checking Transaction Log'!$C:$C,">="&Y1,'Checking Transaction Log'!$C:$C,"<="&Z1,'Checking Transaction Log'!$A:$A,"s",'Checking Transaction Log'!$B:$B,36) -> 50 | Z45: =H45-Y45 -> 0 | AA45: =SUMIFS('Checking Transaction Log'!$E:$E,'Checking Transaction Log'!$C:$C,">="&AA1,'Checking Transaction Log'!$C:$C,"<="&AB1,'Checking Transaction Log'!$A:$A,"s",'Checking Transaction Log'!$B:$B,36) -> 0 | AB45: =H45-AA45 -> 50 | AC45: =SUMIFS('Checking Transaction Log'!$E:$E,'Checking Transaction Log'!$C:$C,">="&AC1,'Checking Transaction Log'!$C:$C,"<="&AD1,'Checking Transaction Log'!$A:$A,"s",'Checking Transaction Log'!$B:$B,36) -> 0 | AD45: =H45-AC45 -> 50 | AE45: =SUMIFS('Checking Transaction Log'!$E:$E,'Checking Transaction Log'!$C:$C,">="&AE1,'Checking Transaction Log'!$C:$C,"<="&AF1,'Checking Transaction Log'!$A:$A,"s",'Checking Transaction Log'!$B:$B,36) -> 0 | AF45: =H45-AE45 -> 50
A46: ='Proposed Budget'!A46 -> S | B46: ='Proposed Budget'!B46 -> 37 | C46: ='Proposed Budget'!C46 -> Our Savings | D46: =(E46/(TODAY()-$I$1))*30.42 -> 4334.8823 | E46: =Q46+S46+U46+W46+Y46+AA46+AC46+AE46+I46+K46+M46+O46 -> 42892.82 | F46: =J46+L46+N46+P46+R46+T46+V46+X46+Z46+AB46 -> -1590.1516 | G46: =1-((E46/SUM(E46:F46))) -> -0.038499973 | H46: ='Proposed Budget'!D46 -> 4130.2668 | I46: =SUMIFS('Checking Transaction Log'!E:E,'Checking Transaction Log'!C:C,">="&I1,'Checking Transaction Log'!C:C,"<="&J1,'Checking Transaction Log'!A:A,"S",'Checking Transaction Log'!B:B,37) -> 3194.64 | J46: =H46-I46 -> 935.62684 | K46: =SUMIFS('Checking Transaction Log'!E:E,'Checking Transaction Log'!C:C,">="&K1,'Checking Transaction Log'!C:C,"<="&L1,'Checking Transaction Log'!A:A,"S",'Checking Transaction Log'!B:B,37) -> 3764.91 | L46: =H46-K46 -> 365.35684 | M46: =SUMIFS('Checking Transaction Log'!$E:$E,'Checking Transaction Log'!$C:$C,">="&M1,'Checking Transaction Log'!$C:$C,"<="&N1,'Checking Transaction Log'!$A:$A,"s",'Checking Transaction Log'!$B:$B,37) -> 4309.58 | N46: =H46-M46 -> -179.31316 | O46: =SUMIFS('Checking Transaction Log'!$E:$E,'Checking Transaction Log'!$C:$C,">="&O1,'Checking Transaction Log'!$C:$C,"<="&P1,'Checking Transaction Log'!$A:$A,"s",'Checking Transaction Log'!$B:$B,37) -> 5616.82 | P46: =H46-O46 -> -1486.5532 | Q46: =SUMIFS('Checking Transaction Log'!$E:$E,'Checking Transaction Log'!$C:$C,">="&Q1,'Checking Transaction Log'!$C:$C,"<="&R1,'Checking Transaction Log'!$A:$A,"s",'Checking Transaction Log'!$B:$B,37) -> 1160.36 | R46: =H46-Q46 -> 2969.9068 | S46: =SUMIFS('Checking Transaction Log'!$E:$E,'Checking Transaction Log'!$C:$C,">="&S1,'Checking Transaction Log'!$C:$C,"<="&T1,'Checking Transaction Log'!$A:$A,"s",'Checking Transaction Log'!$B:$B,37) -> 6487.16 | T46: =H46-S46 -> -2356.8932 | U46: =SUMIFS('Checking Transaction Log'!$E:$E,'Checking Transaction Log'!$C:$C,">="&U1,'Checking Transaction Log'!$C:$C,"<="&V1,'Checking Transaction Log'!$A:$A,"s",'Checking Transaction Log'!$B:$B,37) -> 8746.27 | V46: =H46-U46 -> -4616.0032 | W46: =SUMIFS('Checking Transaction Log'!$E:$E,'Checking Transaction Log'!$C:$C,">="&W1,'Checking Transaction Log'!$C:$C,"<="&X1,'Checking Transaction Log'!$A:$A,"s",'Checking Transaction Log'!$B:$B,37) -> 6794.38 | X46: =H46-W46 -> -2664.1132 | Y46: =SUMIFS('Checking Transaction Log'!$E:$E,'Checking Transaction Log'!$C:$C,">="&Y1,'Checking Transaction Log'!$C:$C,"<="&Z1,'Checking Transaction Log'!$A:$A,"s",'Checking Transaction Log'!$B:$B,37) -> 2768.7 | Z46: =H46-Y46 -> 1361.5668 | AA46: =SUMIFS('Checking Transaction Log'!$E:$E,'Checking Transaction Log'!$C:$C,">="&AA1,'Checking Transaction Log'!$C:$C,"<="&AB1,'Checking Transaction Log'!$A:$A,"s",'Checking Transaction Log'!$B:$B,37) -> 50 | AB46: =H46-AA46 -> 4080.2668 | AC46: =SUMIFS('Checking Transaction Log'!$E:$E,'Checking Transaction Log'!$C:$C,">="&AC1,'Checking Transaction Log'!$C:$C,"<="&AD1,'Checking Transaction Log'!$A:$A,"s",'Checking Transaction Log'!$B:$B,37) -> 0 | AD46: =H46-AC46 -> 4130.2668 | AE46: =SUMIFS('Checking Transaction Log'!$E:$E,'Checking Transaction Log'!$C:$C,">="&AE1,'Checking Transaction Log'!$C:$C,"<="&AF1,'Checking Transaction Log'!$A:$A,"s",'Checking Transaction Log'!$B:$B,37) -> 0 | AF46: =H46-AE46 -> 4130.2668
E47: Total | F47: Total | G47: %
E48: Made | F48: Difference | G48: More
A49: I | B49: 38 | C49: Lorri Income | D49: =(E49/(TODAY()-$I$1))*30.42 -> 8800.7425 | E49: =Q49+S49+U49+W49+Y49+AA49+AC49+AE49+I49+K49+M49+O49 -> 87081.64 | F49: =E49-('Proposed Budget'!J68*14) -> 22712.072 | G49: =(E49/(E49-F49))-1 -> 0.35283866 | I49: =SUMIFS('Checking Transaction Log'!F:F,'Checking Transaction Log'!C:C,">="&I1,'Checking Transaction Log'!C:C,"<="&J1,'Checking Transaction Log'!A:A,"i",'Checking Transaction Log'!B:B,38) -> 8731.32 | K49: =SUMIFS('Checking Transaction Log'!F:F,'Checking Transaction Log'!C:C,">="&K1,'Checking Transaction Log'!C:C,"<="&L1,'Checking Transaction Log'!A:A,"i",'Checking Transaction Log'!B:B,38) -> 8556.31 | M49: =SUMIFS('Checking Transaction Log'!$F:$F,'Checking Transaction Log'!$C:$C,">="&M1,'Checking Transaction Log'!$C:$C,"<="&N1,'Checking Transaction Log'!$A:$A,"i",'Checking Transaction Log'!$B:$B,38) -> 9005.06 | O49: =SUMIFS('Checking Transaction Log'!$F:$F,'Checking Transaction Log'!$C:$C,">="&O1,'Checking Transaction Log'!$C:$C,"<="&P1,'Checking Transaction Log'!$A:$A,"i",'Checking Transaction Log'!$B:$B,38) -> 9195.64 | Q49: =SUMIFS('Checking Transaction Log'!$F:$F,'Checking Transaction Log'!$C:$C,">="&Q1,'Checking Transaction Log'!$C:$C,"<="&R1,'Checking Transaction Log'!$A:$A,"i",'Checking Transaction Log'!$B:$B,38) -> 9195.63 | S49: =SUMIFS('Checking Transaction Log'!$F:$F,'Checking Transaction Log'!$C:$C,">="&S1,'Checking Transaction Log'!$C:$C,"<="&T1,'Checking Transaction Log'!$A:$A,"i",'Checking Transaction Log'!$B:$B,38) -> 9318.68 | U49: =SUMIFS('Checking Transaction Log'!$F:$F,'Checking Transaction Log'!$C:$C,">="&U1,'Checking Transaction Log'!$C:$C,"<="&V1,'Checking Transaction Log'!$A:$A,"i",'Checking Transaction Log'!$B:$B,38) -> 9441.7 | W49: =SUMIFS('Checking Transaction Log'!$F:$F,'Checking Transaction Log'!$C:$C,">="&W1,'Checking Transaction Log'!$C:$C,"<="&X1,'Checking Transaction Log'!$A:$A,"i",'Checking Transaction Log'!$B:$B,38) -> 9458.67 | Y49: =SUMIFS('Checking Transaction Log'!$F:$F,'Checking Transaction Log'!$C:$C,">="&Y1,'Checking Transaction Log'!$C:$C,"<="&Z1,'Checking Transaction Log'!$A:$A,"i",'Checking Transaction Log'!$B:$B,38) -> 9449.31 | AA49: =SUMIFS('Checking Transaction Log'!$F:$F,'Checking Transaction Log'!$C:$C,">="&AA1,'Checking Transaction Log'!$C:$C,"<="&AB1,'Checking Transaction Log'!$A:$A,"i",'Checking Transaction Log'!$B:$B,38) -> 4729.32 | AC49: =SUMIFS('Checking Transaction Log'!$F:$F,'Checking Transaction Log'!$C:$C,">="&AC1,'Checking Transaction Log'!$C:$C,"<="&AD1,'Checking Transaction Log'!$A:$A,"i",'Checking Transaction Log'!$B:$B,38) -> 0 | AE49: =SUMIFS('Checking Transaction Log'!$F:$F,'Checking Transaction Log'!$C:$C,">="&AE1,'Checking Transaction Log'!$C:$C,"<="&AF1,'Checking Transaction Log'!$A:$A,"i",'Checking Transaction Log'!$B:$B,38) -> 0
A50: I | B50: 39 | C50: Isaac Income | D50: =(E50/(TODAY()-$I$1))*30.42 -> 6238.4932 | E50: =Q50+S50+U50+W50+Y50+AA50+AC50+AE50+I50+K50+M50+O50 -> 61728.68 | F50: =E50-('Proposed Budget'!J44*14) -> 23035.711 | G50: =(E50/(E50-F50))-1 -> 0.59534617 | I50: =SUMIFS('Checking Transaction Log'!F:F,'Checking Transaction Log'!C:C,">="&I1,'Checking Transaction Log'!C:C,"<="&J1,'Checking Transaction Log'!A:A,"i",'Checking Transaction Log'!B:B,39) -> 6108.04 | K50: =SUMIFS('Checking Transaction Log'!F:F,'Checking Transaction Log'!C:C,">="&K1,'Checking Transaction Log'!C:C,"<="&L1,'Checking Transaction Log'!A:A,"i",'Checking Transaction Log'!B:B,39) -> 5527.56 | M50: =SUMIFS('Checking Transaction Log'!$F:$F,'Checking Transaction Log'!$C:$C,">="&M1,'Checking Transaction Log'!$C:$C,"<="&N1,'Checking Transaction Log'!$A:$A,"i",'Checking Transaction Log'!$B:$B,39) -> 5527.56 | O50: =SUMIFS('Checking Transaction Log'!$F:$F,'Checking Transaction Log'!$C:$C,">="&O1,'Checking Transaction Log'!$C:$C,"<="&P1,'Checking Transaction Log'!$A:$A,"i",'Checking Transaction Log'!$B:$B,39) -> 8291.34 | Q50: =SUMIFS('Checking Transaction Log'!$F:$F,'Checking Transaction Log'!$C:$C,">="&Q1,'Checking Transaction Log'!$C:$C,"<="&R1,'Checking Transaction Log'!$A:$A,"i",'Checking Transaction Log'!$B:$B,39) -> 5527.57 | S50: =SUMIFS('Checking Transaction Log'!$F:$F,'Checking Transaction Log'!$C:$C,">="&S1,'Checking Transaction Log'!$C:$C,"<="&T1,'Checking Transaction Log'!$A:$A,"i",'Checking Transaction Log'!$B:$B,39) -> 5527.55 | U50: =SUMIFS('Checking Transaction Log'!$F:$F,'Checking Transaction Log'!$C:$C,">="&U1,'Checking Transaction Log'!$C:$C,"<="&V1,'Checking Transaction Log'!$A:$A,"i",'Checking Transaction Log'!$B:$B,39) -> 5527.56 | W50: =SUMIFS('Checking Transaction Log'!$F:$F,'Checking Transaction Log'!$C:$C,">="&W1,'Checking Transaction Log'!$C:$C,"<="&X1,'Checking Transaction Log'!$A:$A,"i",'Checking Transaction Log'!$B:$B,39) -> 5527.56 | Y50: =SUMIFS('Checking Transaction Log'!$F:$F,'Checking Transaction Log'!$C:$C,">="&Y1,'Checking Transaction Log'!$C:$C,"<="&Z1,'Checking Transaction Log'!$A:$A,"i",'Checking Transaction Log'!$B:$B,39) -> 5529.33 | AA50: =SUMIFS('Checking Transaction Log'!$F:$F,'Checking Transaction Log'!$C:$C,">="&AA1,'Checking Transaction Log'!$C:$C,"<="&AB1,'Checking Transaction Log'!$A:$A,"i",'Checking Transaction Log'!$B:$B,39) -> 8634.61 | AC50: =SUMIFS('Checking Transaction Log'!$F:$F,'Checking Transaction Log'!$C:$C,">="&AC1,'Checking Transaction Log'!$C:$C,"<="&AD1,'Checking Transaction Log'!$A:$A,"i",'Checking Transaction Log'!$B:$B,39) -> 0 | AE50: =SUMIFS('Checking Transaction Log'!$F:$F,'Checking Transaction Log'!$C:$C,">="&AE1,'Checking Transaction Log'!$C:$C,"<="&AF1,'Checking Transaction Log'!$A:$A,"i",'Checking Transaction Log'!$B:$B,39) -> 0
A51: I | B51: 40 | C51: Isaac Guard Income | D51: =(E51/(TODAY()-$I$1))*30.42 -> 1247.1634 | E51: =Q51+S51+U51+W51+Y51+AA51+AC51+AE51+I51+K51+M51+O51 -> 12340.44 | I51: =SUMIFS('Checking Transaction Log'!F:F,'Checking Transaction Log'!C:C,">="&I1,'Checking Transaction Log'!C:C,"<="&J1,'Checking Transaction Log'!A:A,"i",'Checking Transaction Log'!B:B,40) -> 0 | K51: =SUMIFS('Checking Transaction Log'!F:F,'Checking Transaction Log'!C:C,">="&K1,'Checking Transaction Log'!C:C,"<="&L1,'Checking Transaction Log'!A:A,"i",'Checking Transaction Log'!B:B,40) -> 2531.75 | M51: =SUMIFS('Checking Transaction Log'!$F:$F,'Checking Transaction Log'!$C:$C,">="&M1,'Checking Transaction Log'!$C:$C,"<="&N1,'Checking Transaction Log'!$A:$A,"i",'Checking Transaction Log'!$B:$B,40) -> 838.67 | O51: =SUMIFS('Checking Transaction Log'!$F:$F,'Checking Transaction Log'!$C:$C,">="&O1,'Checking Transaction Log'!$C:$C,"<="&P1,'Checking Transaction Log'!$A:$A,"i",'Checking Transaction Log'!$B:$B,40) -> 838.69 | Q51: =SUMIFS('Checking Transaction Log'!$F:$F,'Checking Transaction Log'!$C:$C,">="&Q1,'Checking Transaction Log'!$C:$C,"<="&R1,'Checking Transaction Log'!$A:$A,"i",'Checking Transaction Log'!$B:$B,40) -> 0 | S51: =SUMIFS('Checking Transaction Log'!$F:$F,'Checking Transaction Log'!$C:$C,">="&S1,'Checking Transaction Log'!$C:$C,"<="&T1,'Checking Transaction Log'!$A:$A,"i",'Checking Transaction Log'!$B:$B,40) -> 2104.55 | U51: =SUMIFS('Checking Transaction Log'!$F:$F,'Checking Transaction Log'!$C:$C,">="&U1,'Checking Transaction Log'!$C:$C,"<="&V1,'Checking Transaction Log'!$A:$A,"i",'Checking Transaction Log'!$B:$B,40) -> 4292.68 | W51: =SUMIFS('Checking Transaction Log'!$F:$F,'Checking Transaction Log'!$C:$C,">="&W1,'Checking Transaction Log'!$C:$C,"<="&X1,'Checking Transaction Log'!$A:$A,"i",'Checking Transaction Log'!$B:$B,40) -> 896.92 | Y51: =SUMIFS('Checking Transaction Log'!$F:$F,'Checking Transaction Log'!$C:$C,">="&Y1,'Checking Transaction Log'!$C:$C,"<="&Z1,'Checking Transaction Log'!$A:$A,"i",'Checking Transaction Log'!$B:$B,40) -> 0 | AA51: =SUMIFS('Checking Transaction Log'!$F:$F,'Checking Transaction Log'!$C:$C,">="&AA1,'Checking Transaction Log'!$C:$C,"<="&AB1,'Checking Transaction Log'!$A:$A,"i",'Checking Transaction Log'!$B:$B,40) -> 837.18 | AC51: =SUMIFS('Checking Transaction Log'!$F:$F,'Checking Transaction Log'!$C:$C,">="&AC1,'Checking Transaction Log'!$C:$C,"<="&AD1,'Checking Transaction Log'!$A:$A,"i",'Checking Transaction Log'!$B:$B,40) -> 0 | AE51: =SUMIFS('Checking Transaction Log'!$F:$F,'Checking Transaction Log'!$C:$C,">="&AE1,'Checking Transaction Log'!$C:$C,"<="&AF1,'Checking Transaction Log'!$A:$A,"i",'Checking Transaction Log'!$B:$B,40) -> 0
A52: I | B52: 41 | C52: Rental Income | D52: =(E52/(TODAY()-$I$1))*30.42 -> 808.50498 | E52: =Q52+S52+U52+W52+Y52+AA52+AC52+AE52+I52+K52+M52+O52 -> 8000 | I52: =SUMIFS('Checking Transaction Log'!F:F,'Checking Transaction Log'!C:C,">="&I1,'Checking Transaction Log'!C:C,"<="&J1,'Checking Transaction Log'!A:A,"i",'Checking Transaction Log'!B:B,41) -> 800 | K52: =SUMIFS('Checking Transaction Log'!F:F,'Checking Transaction Log'!C:C,">="&K1,'Checking Transaction Log'!C:C,"<="&L1,'Checking Transaction Log'!A:A,"i",'Checking Transaction Log'!B:B,41) -> 0 | M52: =SUMIFS('Checking Transaction Log'!$F:$F,'Checking Transaction Log'!$C:$C,">="&M1,'Checking Transaction Log'!$C:$C,"<="&N1,'Checking Transaction Log'!$A:$A,"i",'Checking Transaction Log'!$B:$B,41) -> 1600 | O52: =SUMIFS('Checking Transaction Log'!$F:$F,'Checking Transaction Log'!$C:$C,">="&O1,'Checking Transaction Log'!$C:$C,"<="&P1,'Checking Transaction Log'!$A:$A,"i",'Checking Transaction Log'!$B:$B,41) -> 550 | Q52: =SUMIFS('Checking Transaction Log'!$F:$F,'Checking Transaction Log'!$C:$C,">="&Q1,'Checking Transaction Log'!$C:$C,"<="&R1,'Checking Transaction Log'!$A:$A,"i",'Checking Transaction Log'!$B:$B,41) -> 250 | S52: =SUMIFS('Checking Transaction Log'!$F:$F,'Checking Transaction Log'!$C:$C,">="&S1,'Checking Transaction Log'!$C:$C,"<="&T1,'Checking Transaction Log'!$A:$A,"i",'Checking Transaction Log'!$B:$B,41) -> 800 | U52: =SUMIFS('Checking Transaction Log'!$F:$F,'Checking Transaction Log'!$C:$C,">="&U1,'Checking Transaction Log'!$C:$C,"<="&V1,'Checking Transaction Log'!$A:$A,"i",'Checking Transaction Log'!$B:$B,41) -> 800 | W52: =SUMIFS('Checking Transaction Log'!$F:$F,'Checking Transaction Log'!$C:$C,">="&W1,'Checking Transaction Log'!$C:$C,"<="&X1,'Checking Transaction Log'!$A:$A,"i",'Checking Transaction Log'!$B:$B,41) -> 1600 | Y52: =SUMIFS('Checking Transaction Log'!$F:$F,'Checking Transaction Log'!$C:$C,">="&Y1,'Checking Transaction Log'!$C:$C,"<="&Z1,'Checking Transaction Log'!$A:$A,"i",'Checking Transaction Log'!$B:$B,41) -> 0 | AA52: =SUMIFS('Checking Transaction Log'!$F:$F,'Checking Transaction Log'!$C:$C,">="&AA1,'Checking Transaction Log'!$C:$C,"<="&AB1,'Checking Transaction Log'!$A:$A,"i",'Checking Transaction Log'!$B:$B,41) -> 1600 | AC52: =SUMIFS('Checking Transaction Log'!$F:$F,'Checking Transaction Log'!$C:$C,">="&AC1,'Checking Transaction Log'!$C:$C,"<="&AD1,'Checking Transaction Log'!$A:$A,"i",'Checking Transaction Log'!$B:$B,41) -> 0 | AE52: =SUMIFS('Checking Transaction Log'!$F:$F,'Checking Transaction Log'!$C:$C,">="&AE1,'Checking Transaction Log'!$C:$C,"<="&AF1,'Checking Transaction Log'!$A:$A,"i",'Checking Transaction Log'!$B:$B,41) -> 0
E54: =SUM(E49:E52) -> 169150.76 | F54: =F49+F50+E52 -> 53747.783 | G54: =(E54/(E54-F54))-1 -> 0.46574 | I54: =SUM(I49:I52) -> 15639.36 | K54: =SUM(K49:K52) -> 16615.62 | M54: =SUM(M49:M52) -> 16971.29 | O54: =SUM(O49:O52) -> 18875.67 | Q54: =SUM(Q49:Q52) -> 14973.2 | S54: =SUM(S49:S52) -> 17750.78 | U54: =SUM(U49:U52) -> 20061.94 | W54: =SUM(W49:W52) -> 17483.15 | Y54: =SUM(Y49:Y52) -> 14978.64 | AA54: =SUM(AA49:AA52) -> 15801.11 | AC54: =SUM(AC49:AC52) -> 0 | AE54: =SUM(AE49:AE52) -> 0

Sheet Budget Breakdown
A1: Month | B1: L | C1: I | E1: P Income | F1: A Income | G1: Diff | H1: % Over | J1: P Spending | K1: A Spending | L1: Diff | M1: % Under | O1: P Savings | P1: A Savings | Q1: Diff
A2: JAN | B2: 2 | C2: 2 | D2: x | E2: =(B2*'Proposed Budget'!$O$68)+(C2*'Proposed Budget'!$O$44)+'Proposed Budget'!$L$21+'Proposed Budget'!$L$22 -> 16719.636 | F2: =SUM('Monthly Breakdown'!I49:I52) -> 15639.36 | G2: =F2-E2 -> -1080.2763 | H2: =((F2-E2)/E2) -> -0.064611229 | J2: =SUM(O20,E20,J20) -> 13000 | K2: =SUM(P20,F20,K20) -> 12394.72 | L2: =J2-K2 -> 605.28 | M2: =((K2-J2)/J2) -> -0.04656 | O2: =E2-O20-E20-J20 -> 3719.6363 | P2: =SUM('Monthly Breakdown'!I45:I46) -> 3244.64 | Q2: =P2-O2 -> -474.99625 | T2: =F2-K2-P2 -> 0
A3: FEB | B3: 2 | C3: 2 | D3: x | E3: =(B3*'Proposed Budget'!$O$68)+(C3*'Proposed Budget'!$O$44)+'Proposed Budget'!$L$21+'Proposed Budget'!$L$22 -> 16719.636 | F3: =SUM('Monthly Breakdown'!K49:K52) -> 16615.62 | G3: =F3-E3 -> -104.01625 | H3: =((F3-E3)/E3) -> -0.0062212032 | J3: =SUM(O21,E21,J21) -> 13000 | K3: =SUM(P21,F21,K21) -> 12800.71 | L3: =J3-K3 -> 199.29 | M3: =((K3-J3)/J3) -> -0.01533 | O3: =E3-O21-E21-J21 -> 3719.6363 | P3: =SUM('Monthly Breakdown'!K45:K46) -> 3814.91 | Q3: =P3-O3 -> 95.273746 | T3: =F3-K3-P3 -> 0
A4: MAR | B4: 2 | C4: 2 | D4: x | E4: =(B4*'Proposed Budget'!$O$68)+(C4*'Proposed Budget'!$O$44)+'Proposed Budget'!$L$21+'Proposed Budget'!$L$22 -> 16719.636 | F4: =SUM('Monthly Breakdown'!M49:M52) -> 16971.29 | G4: =F4-E4 -> 251.65375 | H4: =((F4-E4)/E4) -> 0.015051389 | J4: =SUM(O22,E22,J22) -> 13000 | K4: =SUM(P22,F22,K22) -> 12611.71 | L4: =J4-K4 -> 388.29 | M4: =((K4-J4)/J4) -> -0.029868462 | O4: =E4-O22-E22-J22 -> 3719.6363 | P4: =SUM('Monthly Breakdown'!M45:M46) -> 4359.58 | Q4: =P4-O4 -> 639.94375 | T4: =F4-K4-P4 -> 0
A5: APR | B5: 2 | C5: 3 | D5: x | E5: =(B5*'Proposed Budget'!$O$68)+(C5*'Proposed Budget'!$O$44)+'Proposed Budget'!$L$21+'Proposed Budget'!$L$22 -> 19483.42 | F5: =SUM('Monthly Breakdown'!O49:O52) -> 18875.67 | G5: =F5-E5 -> -607.74976 | H5: =((F5-E5)/E5) -> -0.031193177 | J5: =SUM(O23,E23,J23) -> 13000 | K5: =SUM(P23,F23,K23) -> 13208.85 | L5: =J5-K5 -> -208.85 | M5: =((K5-J5)/J5) -> 0.016065385 | O5: =E5-O23-E23-J23 -> 6483.4198 | P5: =SUM('Monthly Breakdown'!O45:O46) -> 5666.82 | Q5: =P5-O5 -> -816.59976 | T5: =F5-K5-P5 -> 0
A6: MAY | B6: 2 | C6: 2 | D6: x | E6: =(B6*'Proposed Budget'!$O$68)+(C6*'Proposed Budget'!$O$44)+'Proposed Budget'!$L$21+'Proposed Budget'!$L$22 -> 16719.636 | F6: =SUM('Monthly Breakdown'!Q49:Q52) -> 14973.2 | G6: =F6-E6 -> -1746.4363 | H6: =((F6-E6)/E6) -> -0.1044542 | J6: =SUM(O24,E24,J24) -> 13000 | K6: =SUM(P24,F24,K24) -> 13762.84 | L6: =J6-K6 -> -762.84 | M6: =((K6-J6)/J6) -> 0.05868 | O6: =E6-O24-E24-J24 -> 3719.6363 | P6: =SUM('Monthly Breakdown'!Q45:Q46) -> 1210.36 | Q6: =P6-O6 -> -2509.2763 | T6: =F6-K6-P6 -> 0
A7: JUN | B7: 2 | C7: 2 | D7: x | E7: =(B7*'Proposed Budget'!$O$68)+(C7*'Proposed Budget'!$O$44)+'Proposed Budget'!$L$21+'Proposed Budget'!$L$22 -> 16719.636 | F7: =SUM('Monthly Breakdown'!S49:S52) -> 17750.78 | G7: =F7-E7 -> 1031.1437 | H7: =((F7-E7)/E7) -> 0.061672618 | J7: =SUM(O25,E25,J25) -> 13000 | K7: =SUM(P25,F25,K25) -> 11213.62 | L7: =J7-K7 -> 1786.38 | M7: =((K7-J7)/J7) -> -0.13741385 | O7: =E7-O25-E25-J25 -> 3719.6363 | P7: =SUM('Monthly Breakdown'!S45:S46) -> 6537.16 | Q7: =P7-O7 -> 2817.5237 | T7: =F7-K7-P7 -> 0
A8: JUL | B8: 2 | C8: 2 | D8: x | E8: =(B8*'Proposed Budget'!$O$68)+(C8*'Proposed Budget'!$O$44)+'Proposed Budget'!$L$21+'Proposed Budget'!$L$22 -> 16719.636 | F8: =SUM('Monthly Breakdown'!U49:U52) -> 20061.94 | G8: =F8-E8 -> 3342.3037 | H8: =((F8-E8)/E8) -> 0.1999029 | J8: =SUM(O26,E26,J26) -> 13000 | K8: =SUM(P26,F26,K26) -> 11265.67 | L8: =J8-K8 -> 1734.33 | M8: =((K8-J8)/J8) -> -0.13341 | O8: =E8-O26-E26-J26 -> 3719.6363 | P8: =SUM('Monthly Breakdown'!U45:U46) -> 8796.27 | Q8: =P8-O8 -> 5076.6337 | T8: =F8-K8-P8 -> 0
A9: AUG | B9: 2 | C9: 2 | D9: x | E9: =(B9*'Proposed Budget'!$O$68)+(C9*'Proposed Budget'!$O$44)+'Proposed Budget'!$L$21+'Proposed Budget'!$L$22 -> 16719.636 | F9: =SUM('Monthly Breakdown'!W49:W52) -> 17483.15 | G9: =F9-E9 -> 763.51375 | H9: =((F9-E9)/E9) -> 0.045665691 | J9: =SUM(O27,E27,J27) -> 13000 | K9: =SUM(P27,F27,K27) -> 10638.77 | L9: =J9-K9 -> 2361.23 | M9: =((K9-J9)/J9) -> -0.18163308 | O9: =E9-O27-E27-J27 -> 3719.6363 | P9: =SUM('Monthly Breakdown'!W45:W46) -> 6844.38 | Q9: =P9-O9 -> 3124.7437 | T9: =F9-K9-P9 -> 0
A10: SEP | B10: 2 | C10: 2 | D10: x | E10: =(B10*'Proposed Budget'!$O$68)+(C10*'Proposed Budget'!$O$44)+'Proposed Budget'!$L$21+'Proposed Budget'!$L$22 -> 16719.636 | F10: =SUM('Monthly Breakdown'!Y49:Y52) -> 14978.64 | G10: =F10-E10 -> -1740.9963 | H10: =((F10-E10)/E10) -> -0.10412884 | J10: =SUM(O28,E28,J28) -> 13000 | K10: =SUM(P28,F28,K28) -> 12159.94 | L10: =J10-K10 -> 840.06 | M10: =((K10-J10)/J10) -> -0.06462 | O10: =E10-O28-E28-J28 -> 3719.6363 | P10: =SUM('Monthly Breakdown'!Y45:Y46) -> 2818.7 | Q10: =P10-O10 -> -900.93625 | T10: =F10-K10-P10 -> 0
A11: OCT | B11: 2 | C11: 3 | E11: =(B11*'Proposed Budget'!$O$68)+(C11*'Proposed Budget'!$O$44)+'Proposed Budget'!$L$21+'Proposed Budget'!$L$22 -> 19483.42 | F11: =SUM('Monthly Breakdown'!AA49:AA52) -> 15801.11 | G11: =F11-E11 -> -3682.3098 | H11: =((F11-E11)/E11) -> -0.1889971 | J11: =SUM(O29,E29,J29) -> 13000 | K11: =SUM(P29,F29,K29) -> 10707.46 | L11: =J11-K11 -> 2292.54 | M11: =((K11-J11)/J11) -> -0.17634923 | O11: =E11-O29-E29-J29 -> 6483.4198 | P11: =SUM('Monthly Breakdown'!AA45:AA46) -> 50 | Q11: =P11-O11 -> -6433.4198 | T11: =F11-K11-P11 -> 5043.65
A12: NOV | B12: 2 | C12: 2 | E12: =(B12*'Proposed Budget'!$O$68)+(C12*'Proposed Budget'!$O$44)+'Proposed Budget'!$L$21+'Proposed Budget'!$L$22 -> 16719.636 | F12: =SUM('Monthly Breakdown'!AC49:AC52) -> 0 | G12: =F12-E12 -> -16719.636 | H12: =((F12-E12)/E12) -> -1 | J12: =SUM(O30,E30,J30) -> 13000 | K12: =SUM(P30,F30,K30) -> 0 | L12: =J12-K12 -> 13000 | M12: =((K12-J12)/J12) -> -1 | O12: =E12-O30-E30-J30 -> 3719.6363 | P12: =SUM('Monthly Breakdown'!AC45:AC46) -> 0 | Q12: =P12-O12 -> -3719.6363 | T12: =F12-K12-P12 -> 0
A13: DEC | B13: 2 | C13: 2 | E13: =(B13*'Proposed Budget'!$O$68)+(C13*'Proposed Budget'!$O$44)+'Proposed Budget'!$L$21+'Proposed Budget'!$L$22 -> 16719.636 | F13: =SUM('Monthly Breakdown'!AE49:AE52) -> 0 | G13: =F13-E13 -> -16719.636 | H13: =((F13-E13)/E13) -> -1 | J13: =SUM(O31,E31,J31) -> 13000 | K13: =SUM(P31,F31,K31) -> 0 | L13: =J13-K13 -> 13000 | M13: =((K13-J13)/J13) -> -1 | O13: =E13-O31-E31-J31 -> 3719.6363 | P13: =SUM('Monthly Breakdown'!AE45:AE46) -> 0 | Q13: =P13-O13 -> -3719.6363 | T13: =F13-K13-P13 -> 0
A16: Total | E16: =SUM(E2:E11) -> 172723.93 | F16: =SUM(F2:F11) -> 169150.76 | G16: =SUM(G2:G11) -> -3573.1696 | H16: =((SUM(F16))-SUM(E16))/SUM(E16) -> -0.020687172 | J16: =SUM(J2:J11) -> 130000 | K16: =SUM(K2:K11) -> 120764.29 | L16: =SUM(L2:L11) -> 9235.71 | M16: =((K16-SUM(J16))/SUM(J16)) -> -0.071043923 | O16: =SUM(O2:O11) -> 42723.93 | P16: =SUM(P2:P11) -> 43342.82 | Q16: =SUM(Q2:Q11) -> 618.89045 | R16: =((P16-SUM(O16))/SUM(O16)) -> 0.014485803 | T16: =F16-K16-P16 -> 5043.65
A19: Month | E19: P Fixed | F19: A Fixed | G19: Diff | H19: % Under | J19: P Non-Fixed | K19: A Non-Fixed | L19: Diff | M19: % Under | O19: P NMB | P19: A NMB | Q19: Diff
A20: JAN | E20: =SUM('Proposed Budget'!$D$14:$D$31) -> 5200 | F20: =SUM('Monthly Breakdown'!I14:I31) -> 4819.04 | G20: =E20-F20 -> 380.96 | H20: =((F20-E20)/E20) -> -0.073261538 | J20: =SUM('Proposed Budget'!$D$5:$D$12) -> 5800 | K20: =SUM('Monthly Breakdown'!I5:I12) -> 5575.68 | L20: =J20-K20 -> 224.32 | M20: =((K20-J20)/J20) -> -0.038675862 | O20: =SUM('Proposed Budget'!$D$33:$D$43) -> 2000 | P20: =SUM('Monthly Breakdown'!I33:I43) -> 2000 | Q20: =O20-P20 -> 0
A21: FEB | E21: =SUM('Proposed Budget'!$D$14:$D$31) -> 5200 | F21: =SUM('Monthly Breakdown'!K14:K31) -> 4930.48 | G21: =E21-F21 -> 269.52 | H21: =((F21-E21)/E21) -> -0.051830769 | J21: =SUM('Proposed Budget'!$D$5:$D$12) -> 5800 | K21: =SUM('Monthly Breakdown'!K5:K12) -> 5870.23 | L21: =J21-K21 -> -70.23 | M21: =((K21-J21)/J21) -> 0.012108621 | O21: =SUM('Proposed Budget'!$D$33:$D$43) -> 2000 | P21: =SUM('Monthly Breakdown'!K33:K43) -> 2000 | Q21: =O21-P21 -> 0
A22: MAR | E22: =SUM('Proposed Budget'!$D$14:$D$31) -> 5200 | F22: =SUM('Monthly Breakdown'!M14:M31) -> 5444.89 | G22: =E22-F22 -> -244.89 | H22: =((F22-E22)/E22) -> 0.047094231 | J22: =SUM('Proposed Budget'!$D$5:$D$12) -> 5800 | K22: =SUM('Monthly Breakdown'!M5:M12) -> 5166.82 | L22: =J22-K22 -> 633.18 | M22: =((K22-J22)/J22) -> -0.10916897 | O22: =SUM('Proposed Budget'!$D$33:$D$43) -> 2000 | P22: =SUM('Monthly Breakdown'!M33:M43) -> 2000 | Q22: =O22-P22 -> 0
A23: APR | E23: =SUM('Proposed Budget'!$D$14:$D$31) -> 5200 | F23: =SUM('Monthly Breakdown'!O14:O31) -> 4511.19 | G23: =E23-F23 -> 688.81 | H23: =((F23-E23)/E23) -> -0.13246346 | J23: =SUM('Proposed Budget'!$D$5:$D$12) -> 5800 | K23: =SUM('Monthly Breakdown'!O5:O12) -> 6697.66 | L23: =J23-K23 -> -897.66 | M23: =((K23-J23)/J23) -> 0.15476897 | O23: =SUM('Proposed Budget'!$D$33:$D$43) -> 2000 | P23: =SUM('Monthly Breakdown'!O33:O43) -> 2000 | Q23: =O23-P23 -> 0
A24: MAY | E24: =SUM('Proposed Budget'!$D$14:$D$31) -> 5200 | F24: =SUM('Monthly Breakdown'!Q14:Q31) -> 5063.4 | G24: =E24-F24 -> 136.6 | H24: =((F24-E24)/E24) -> -0.026269231 | J24: =SUM('Proposed Budget'!$D$5:$D$12) -> 5800 | K24: =SUM('Monthly Breakdown'!Q5:Q12) -> 6699.44 | L24: =J24-K24 -> -899.44 | M24: =((K24-J24)/J24) -> 0.15507586 | O24: =SUM('Proposed Budget'!$D$33:$D$43) -> 2000 | P24: =SUM('Monthly Breakdown'!Q33:Q43) -> 2000 | Q24: =O24-P24 -> 0
A25: JUN | E25: =SUM('Proposed Budget'!$D$14:$D$31) -> 5200 | F25: =SUM('Monthly Breakdown'!S14:S31) -> 4742.14 | G25: =E25-F25 -> 457.86 | H25: =((F25-E25)/E25) -> -0.08805 | J25: =SUM('Proposed Budget'!$D$5:$D$12) -> 5800 | K25: =SUM('Monthly Breakdown'!S5:S12) -> 4471.48 | L25: =J25-K25 -> 1328.52 | M25: =((K25-J25)/J25) -> -0.22905517 | O25: =SUM('Proposed Budget'!$D$33:$D$43) -> 2000 | P25: =SUM('Monthly Breakdown'!S33:S43) -> 2000 | Q25: =O25-P25 -> 0
A26: JUL | E26: =SUM('Proposed Budget'!$D$14:$D$31) -> 5200 | F26: =SUM('Monthly Breakdown'!U14:U31) -> 4087.32 | G26: =E26-F26 -> 1112.68 | H26: =((F26-E26)/E26) -> -0.21397692 | J26: =SUM('Proposed Budget'!$D$5:$D$12) -> 5800 | K26: =SUM('Monthly Breakdown'!U5:U12) -> 5178.35 | L26: =J26-K26 -> 621.65 | M26: =((K26-J26)/J26) -> -0.10718103 | O26: =SUM('Proposed Budget'!$D$33:$D$43) -> 2000 | P26: =SUM('Monthly Breakdown'!U33:U43) -> 2000 | Q26: =O26-P26 -> 0
A27: AUG | E27: =SUM('Proposed Budget'!$D$14:$D$31) -> 5200 | F27: =SUM('Monthly Breakdown'!W14:W31) -> 4137.04 | G27: =E27-F27 -> 1062.96 | H27: =((F27-E27)/E27) -> -0.20441538 | J27: =SUM('Proposed Budget'!$D$5:$D$12) -> 5800 | K27: =SUM('Monthly Breakdown'!W5:W12) -> 4501.73 | L27: =J27-K27 -> 1298.27 | M27: =((K27-J27)/J27) -> -0.22383966 | O27: =SUM('Proposed Budget'!$D$33:$D$43) -> 2000 | P27: =SUM('Monthly Breakdown'!W33:W43) -> 2000 | Q27: =O27-P27 -> 0
A28: SEP | E28: =SUM('Proposed Budget'!$D$14:$D$31) -> 5200 | F28: =SUM('Monthly Breakdown'!Y14:Y31) -> 4226.66 | G28: =E28-F28 -> 973.34 | H28: =((F28-E28)/E28) -> -0.18718077 | J28: =SUM('Proposed Budget'!$D$5:$D$12) -> 5800 | K28: =SUM('Monthly Breakdown'!Y5:Y12) -> 5933.28 | L28: =J28-K28 -> -133.28 | M28: =((K28-J28)/J28) -> 0.02297931 | O28: =SUM('Proposed Budget'!$D$33:$D$43) -> 2000 | P28: =SUM('Monthly Breakdown'!Y33:Y43) -> 2000 | Q28: =O28-P28 -> 0
A29: OCT | E29: =SUM('Proposed Budget'!$D$14:$D$31) -> 5200 | F29: =SUM('Monthly Breakdown'!AA14:AA31) -> 5323.8 | G29: =E29-F29 -> -123.8 | H29: =((F29-E29)/E29) -> 0.023807692 | J29: =SUM('Proposed Budget'!$D$5:$D$12) -> 5800 | K29: =SUM('Monthly Breakdown'!AA5:AA12) -> 5383.66 | L29: =J29-K29 -> 416.34 | M29: =((K29-J29)/J29) -> -0.071782759 | O29: =SUM('Proposed Budget'!$D$33:$D$43) -> 2000 | P29: =SUM('Monthly Breakdown'!AA33:AA43) -> 0 | Q29: =O29-P29 -> 2000
A30: NOV | E30: =SUM('Proposed Budget'!$D$14:$D$31) -> 5200 | F30: =SUM('Monthly Breakdown'!AC14:AC31) -> 0 | G30: =E30-F30 -> 5200 | H30: =((F30-E30)/E30) -> -1 | J30: =SUM('Proposed Budget'!$D$5:$D$12) -> 5800 | K30: =SUM('Monthly Breakdown'!AC5:AC12) -> 0 | L30: =J30-K30 -> 5800 | M30: =((K30-J30)/J30) -> -1 | O30: =SUM('Proposed Budget'!$D$33:$D$43) -> 2000 | P30: =SUM('Monthly Breakdown'!AC33:AC43) -> 0 | Q30: =O30-P30 -> 2000
A31: DEC | E31: =SUM('Proposed Budget'!$D$14:$D$31) -> 5200 | F31: =SUM('Monthly Breakdown'!AE14:AE31) -> 0 | G31: =E31-F31 -> 5200 | H31: =((F31-E31)/E31) -> -1 | J31: =SUM('Proposed Budget'!$D$5:$D$12) -> 5800 | K31: =SUM('Monthly Breakdown'!AE5:AE12) -> 0 | L31: =J31-K31 -> 5800 | M31: =((K31-J31)/J31) -> -1 | O31: =SUM('Proposed Budget'!$D$33:$D$43) -> 2000 | P31: =SUM('Monthly Breakdown'!AE33:AE43) -> 0 | Q31: =O31-P31 -> 2000
A34: Total | E34: =SUM(E20:E29) -> 52000 | F34: =SUM(F20:F29) -> 47285.96 | G34: =SUM(G20:G29) -> 4714.04 | H34: =((F34-SUM(E34)))/SUM(E34) -> -0.090654615 | J34: =SUM(J20:J29) -> 58000 | K34: =SUM(K20:K29) -> 55478.33 | L34: =SUM(L20:L29) -> 2521.67 | M34: =((K34-SUM(J34))/SUM(J34)) -> -0.043477069 | O34: =SUM(O20:O31) -> 24000 | P34: =SUM(P20:P31) -> 18000 | Q34: =SUM(Q20:Q31) -> 6000

Sheet Checking Transaction Log
A1: ID | C1: Date | D1: Description | E1: Checking Account Balance | G1: =(SUM(INDIRECT("g5:g5")))+J2+L2+N2+P2-R2+T2-G1865 -> 7573.13 | I1: PNC (I) | J1: 25000 | K1: PNC (L) | L1: 25000 | M1: Chase (I) | N1: =10500-N2 -> 10500 | O1: Chase (L) | P1: =5000-P2 -> 5000 | Q1: Cash On Hand | S1: Chase (I) | T1: =1200-T2 -> 1200
E2: Cash On Hand | G2: =R2 -> 180 | I2: #1 (8539) | J2: =SUMIFS(E:E,I:I,"1") -> 0 | K2: #2 (4990) | L2: =(SUMIFS(E:E,I:I,"2")) -> 32.12 | M2: #3 (5153) | N2: =SUMIFS(E:E,I:I,"3") -> 0 | O2: #4 (2711) | P2: =SUMIFS(E:E,I:I,"4") -> 0 | R2: =SUMIFS(F:F,H:H,"cash")-SUMIFS(E:E,H:H,"cash") -> 180 | S2: #6 (5411) | T2: =SUMIFS(E:E,I:I,"6") -> 0
E3: Available Credit | G3: =SUM(J1,L1,N1,P1,T1) -> 66700
E4: DEBIT | F4: CREDIT | G4: BALANCE
A5: xx | B5: xx | C5: 46324 | D5: Rental Utilities | F5: 147 | G5: =G6-E5+F5 -> 7721.01
A6: f | B6: 20 | C6: 46324 | D6: Wells Fargo - Deck | E6: 600 | G6: =G7-E6+F6 -> 7574.01
A7: i | B7: 39 | C7: 46324 | D7: Isaac Pay Check | F7: 2765.53 | G7: =G8-E7+F7 -> 8174.01
A8: d | B8: 6 | C8: 46324 | D8: Tranfer from CashApp | E8: -100 | G8: =G9-E8+F8 -> 5408.48
A9: d | B9: 6 | C9: 46322 | D9: Personal Creations | E9: 25.12 | G9: =G10-E9+F9 -> 5308.48 | I9: 2
A10: d | B10: 6 | C10: 46322 | D10: Goodwill | E10: 7 | G10: =G11-E10+F10 -> 5333.6 | I10: 2
A11: d | B11: 8 | C11: 46322 | D11: Coopershawk | E11: 49.49 | G11: =G12-E11+F11 -> 5340.6
A12: f | B12: 22 | C12: 46322 | D12: Amazon Digital Services | E12: 15.96 | G12: =G13-E12+F12 -> 5390.09
A13: d | B13: 8 | C13: 46322 | D13: Lorain Smokes and Beverage | E13: 21.03 | G13: =G14-E13+F13 -> 5406.05
A14: d | B14: 8 | C14: 46322 | D14: GetGo | E14: 21.75 | G14: =G15-E14+F14 -> 5427.08
A15: d | B15: 6 | C15: 46322 | D15: Consumers Builders Supply | E15: 26.04 | G15: =G16-E15+F15 -> 5448.83
C16: 46322 | D16: Lowes | E16: 327.08 | G16: =G17-E16+F16 -> 5474.87
A17: d | B17: 6 | C17: 46322 | D17: Lowes | E17: 133.23 | G17: =G18-E17+F17 -> 5801.95
A18: d | B18: 4 | C18: 46321 | D18: Speedway | E18: 49.56 | G18: =G19-E18+F18 -> 5935.18
A19: y | B19: y | C19: 46321 | D19: Hot Topic | E19: 36.53 | F19: 36.53 | G19: =G20-E19+F19 -> 5984.74
A20: y | B20: y | C20: 46321 | D20: RB Liquidations | E20: 16.97 | F20: 16.97 | G20: =G21-E20+F20 -> 5984.74
A21: y | B21: y | C21: 46321 | D21: Christmas Towne | E21: 16.19 | F21: 16.19 | G21: =G22-E21+F21 -> 5984.74
A22: d | B22: 5 | C22: 46321 | D22: Cedar Point | E22: 31.58 | G22: =G23-E22+F22 -> 5984.74
A23: d | B23: 6 | C23: 46321 | D23: Autozone | E23: 14.37 | G23: =G24-E23+F23 -> 6016.32
A24: d | B24: 8 | C24: 46321 | D24: GetGo | E24: 12.05 | G24: =G25-E24+F24 -> 6030.69
A25: d | B25: 2 | C25: 46321 | D25: Chipotle | E25: 18.7 | G25: =G26-E25+F25 -> 6042.74
A26: d | B26: 6 | C26: 46321 | D26: Target | E26: 14.93 | G26: =G27-E26+F26 -> 6061.44
A27: d | B27: 2 | C27: 46321 | D27: Raising Canes | E27: 24.31 | G27: =G28-E27+F27 -> 6076.37
A28: d | B28: 7 | C28: 46321 | D28: Spirit Halloween | E28: 67.07 | G28: =G29-E28+F28 -> 6100.68
A29: f | B29: 22 | C29: 46321 | D29: NBA TV | E29: 119.27 | G29: =G30-E29+F29 -> 6167.75
A30: d | B30: 2 | C30: 46320 | D30: Cedar Point Food | E30: 34.66 | G30: =G31-E30+F30 -> 6287.02
A31: d | B31: 1 | C31: 46320 | D31: Giant Eagle | E31: 22.47 | G31: =G32-E31+F31 -> 6321.68
A32: d | B32: 4 | C32: 46320 | D32: BP | E32: 42.76 | G32: =G33-E32+F32 -> 6344.15
A33: f | B33: 12 | C33: 46320 | D33: Spectrum | E33: 204.48 | G33: =G34-E33+F33 -> 6386.91
... A45: d | B45: 5 | C45: 46318 | D45: High School Football | E45: 28.83 | G45: =G46-E45+F45 -> 7111.03
A46: x | B46: x | C46: 46317 | D46: Rumpke Waste | E46: 134.52 | F46: 134.52 | G46: =G47-E46+F46 -> 7139.86
A47: d | B47: 2 | C47: 46317 | D47: Taco Bell | E47: 18.77 | G47: =G48-E47+F47 -> 7139.86
A48: d | B48: 4 | C48: 46317 | D48: 7-Eleven | E48: 49.49 | G48: =G49-E48+F48 -> 7158.63
A49: d | B49: 7 | C49: 46317 | D49: Shein | E49: 53.49 | G49: =G50-E49+F49 -> 7208.12
A50: d | B50: 4 | C50: 46317 | D50: Friendship | E50: 44.14 | G50: =G51-E50+F50 -> 7261.61
A51: d | B51: 2 | C51: 46317 | D51: Friendship | E51: 7.63 | G51: =G52-E51+F51 -> 7305.75
A52: d | B52: 3 | C52: 46317 | D52: Dunkin | E52: 6.73 | G52: =G53-E52+F52 -> 7313.38
A53: d | B53: 5 | C53: 46316 | D53: Bowling | E53: 80 | G53: =G54-E53+F53 -> 7320.11 | H53: cash
A54: d | B54: 8 | C54: 46316 | D54: Lorain Smokes and Beverage | E54: 9.03 | G54: =G55-E54+F54 -> 7400.11
A55: f | B55: 16 | C55: 46316 | D55: Innovative Counseling | E55: 75 | G55: =G56-E55+F55 -> 7409.14
A56: f | B56: 16 | C56: 46316 | D56: Cleveland Clinic | E56: 755.78 | G56: =G57-E56+F56 -> 7484.14
A57: d | B57: 6 | C57: 46315 | D57: Amazon | E57: 13.83 | G57: =G58-E57+F57 -> 8239.92
A58: d | B58: 6 | C58: 46315 | D58: Transfer from Venmo | E58: -185 | G58: =G59-E58+F58 -> 8253.75
A59: d | B59: 5 | C59: 46315 | D59: Transfer to Venmo - Robin Weiss;Guardians | E59: 87 | G59: =G60-E59+F59 -> 8068.75
A60: d | B60: 1 | C60: 46314 | D60: ALDI | E60: 16.87 | G60: =G61-E60+F60 -> 8155.75
A61: i | B61: 41 | C61: 46314 | D61: October Rent | F61: 800 | G61: =G62-E61+F61 -> 8172.62
A62: xx | B62: xx | C62: 46314 | D62: Rental Utilities | F62: 200 | G62: =G63-E62+F62 -> 7372.62
A63: d | B63: 1 | C63: 46314 | D63: Walmart | E63: 108.9 | G63: =G64-E63+F63 -> 7172.62
A64: d | B64: 4 | C64: 46314 | D64: Sheetz | E64: 42.01 | G64: =G65-E64+F64 -> 7281.52
A65: d | B65: 8 | C65: 46314 | D65: Southern Tier Brewing | E65: 39.07 | G65: =G66-E65+F65 -> 7323.53
A66: d | B66: 2 | C66: 46314 | D66: Winking Lizard | E66: 41.32 | G66: =G67-E66+F66 -> 7362.6
A67: f | B67: 22 | C67: 46314 | D67: Disney Plus | E67: 7.46 | G67: =G68-E67+F67 -> 7403.92
A68: d | B68: 6 | C68: 46314 | D68: Amazon Marketplace | E68: 40.41 | G68: =G69-E68+F68 -> 7411.38
A69: f | B69: 17 | C69: 46314 | D69: Planet Fitness | E69: 42.65 | G69: =G70-E69+F69 -> 7451.79
A70: f | B70: 22 | C70: 46314 | D70: Spotify | E70: 23.42 | G70: =G71-E70+F70 -> 7494.44
A71: f | B71: 23 | C71: 46314 | D71: Lormet | E71: 529.46 | G71: =G72-E71+F71 -> 7517.86
A72: d | B72: 6 | C72: 46314 | D72: Transfer to CashApp | E72: 100 | G72: =G73-E72+F72 -> 8047.32
A73: d | B73: 5 | C73: 46313 | D73: The Solver | E73: 37.99 | G73: =G74-E73+F73 -> 8147.32
A74: d | B74: 6 | C74: 46313 | D74: Walmart | E74: 67.53 | G74: =G75-E74+F74 -> 8185.31
... A90: d | B90: 6 | C90: 46311 | D90: JM Tax Prep | E90: 207.8 | G90: =G91-E90+F90 -> 8834.19
A91: x | B91: x | C91: 46311 | D91: Transfer from Regan | F91: 200 | G91: =G92-E91+F91 -> 9041.99 | H91: cash
A92: x | B92: x | C92: 46311 | D92: Transfer to Regan | E92: 200 | G92: =G93-E92+F92 -> 8841.99
A93: d | B93: 1 | C93: 46310 | D93: ALDI | E93: 4.18 | G93: =G94-E93+F93 -> 9041.99
A94: d | B94: 2 | C94: 46310 | D94: Five Guys | E94: 21.73 | G94: =G95-E94+F94 -> 9046.17
A95: d | B95: 1 | C95: 46310 | D95: Sams Club | E95: 146.27 | G95: =G96-E95+F95 -> 9067.9
A96: d | B96: 4 | C96: 46310 | D96: Friendship | E96: 43.46 | G96: =G97-E96+F96 -> 9214.17
A97: d | B97: 8 | C97: 46310 | D97: Friendship | E97: 10.52 | G97: =G98-E97+F97 -> 9257.63
A98: f | B98: 24 | C98: 46310 | D98: E-Zpass | E98: 95.42 | G98: =G99-E98+F98 -> 9268.15
A99: f | B99: 11 | C99: 46310 | D99: Verizon Wireless | E99: 256.84 | G99: =G100-E99+F99 -> 9363.57
A100: d | B100: 2 | C100: 46310 | D100: Chipotle | E100: 30 | G100: =G101-E100+F100 -> 9620.41
A101: d | B101: 6 | C101: 46310 | D101: Cash App - Water | E101: 32.36 | G101: =G102-E101+F101 -> 9650.41
A102: d | B102: 3 | C102: 46310 | D102: Cash App - Pulp | E102: 10 | G102: =G103-E102+F102 -> 9682.77
A103: i | B103: 39 | C103: 46310 | D103: Isaac Pay Check | F103: 3103.54 | G103: =G104-E103+F103 -> 9692.77
A104: i | B104: 38 | C104: 46310 | D104: Lorri Pay Check | F104: 4729.32 | G104: =G105-E104+F104 -> 6589.23
A105: d | B105: 8 | C105: 46309 | D105: Lorain Smokes and Beverage | E105: 17.54 | G105: =G106-E105+F105 -> 1859.91
A106: d | B106: 4 | C106: 46309 | D106: Friendship | E106: 84.26 | G106: =G107-E106+F106 -> 1877.45
A107: d | B107: 8 | C107: 46309 | D107: AMF North Ridgeville | E107: 27.88 | G107: =G108-E107+F107 -> 1961.71
A108: d | B108: 2 | C108: 46309 | D108: AMF North Ridgeville | E108: 24.17 | G108: =G109-E108+F108 -> 1989.59
A109: f | B109: 16 | C109: 46309 | D109: Innovative Counseling | E109: 85 | G109: =G110-E109+F109 -> 2013.76
A110: f | B110: 19 | C110: 46308 | D110: Wells Fargo - Pool | E110: 200 | G110: =G111-E110+F110 -> 2098.76
A111: d | B111: 2 | C111: 46308 | D111: Chick-fil-A | E111: 14.36 | G111: =G112-E111+F111 -> 2298.76
A112: d | B112: 2 | C112: 46308 | D112: Chipotle | E112: 16.05 | G112: =G113-E112+F112 -> 2313.12
A113: d | B113: 6 | C113: 46308 | D113: ATM Fee Reimbursement | E113: -10 | G113: =G114-E113+F113 -> 2329.17
A114: d | B114: 5 | C114: 46308 | D114: Transfer to Venmo - Katie Cammerata; Wine | E114: 25 | G114: =G115-E114+F114 -> 2319.17
A115: d | B115: 2 | C115: 46308 | D115: Transfer to Venmo - Brittany; Ramen | E115: 50 | G115: =G116-E115+F115 -> 2344.17
A116: d | B116: 6 | C116: 46308 | D116: Interest Income | E116: -0.05 | G116: =G117-E116+F116 -> 2394.17
A117: xx | B117: xx | C117: 46308 | D117: Columbia Gas | E117: 63.68 | G117: =G118-E117+F117 -> 2394.12
A118: f | B118: 15 | C118: 46308 | D118: Columbia Gas | E118: 63.68 | G118: =G119-E118+F118 -> 2457.8
A119: d | B119: 6 | C119: 46307 | D119: Autozone | E119: 12.24 | G119: =G120-E119+F119 -> 2521.48
A120: d | B120: 1 | C120: 46306 | D120: Walmart | E120: 102.88 | G120: =G121-E120+F120 -> 2533.72
A121: f | B121: 22 | C121: 46306 | D121: Netflix | E121: 21.29 | G121: =G122-E121+F121 -> 2636.6
A122: d | B122: 8 | C122: 46306 | D122: Lorain Smokes and Beverage | E122: 25.43 | G122: =G123-E122+F122 -> 2657.89
A123: d | B123: 4 | C123: 46306 | D123: GetGo | E123: 44.36 | G123: =G124-E123+F123 -> 2683.32
A124: d | B124: 6 | C124: 46306 | D124: Mapleside Farms | E124: 53.86 | G124: =G125-E124+F124 -> 2727.68
A125: d | B125: 8 | C125: 46305 | D125: Speedway | E125: 10.64 | G125: =G126-E125+F125 -> 2781.54
A126: d | B126: 1 | C126: 46305 | D126: ALDI | E126: 158.04 | G126: =G127-E126+F126 -> 2792.18
...

Sheet Savings Transaction Log
A1: TOTAL BALANCE | D1: SAVINGS | F1: CC REWARDS - XMAS | H1: ='Proposed Budget'!C33 -> Vehicle Maintenance | J1: ='Proposed Budget'!C34 -> Car Insurance | L1: ='Proposed Budget'!C35 -> Rental Garbage | N1: ='Proposed Budget'!C36 -> Garbage | P1: ='Monthly Breakdown'!C37 -> Sanitation - Main | R1: ='Proposed Budget'!C38 -> Camping/Vacation | T1: ='Proposed Budget'!C39 -> Home Maintenance | V1: ='Proposed Budget'!C40 -> Rental Repairs | X1: ='Proposed Budget'!C41 -> Rental Insurance | Z1: ='Proposed Budget'!C42 -> Rental Property Taxes | AB1: ='Proposed Budget'!C43 -> Rental Sanitation
A2: =SUM(G2,E2,U2,I2,S2,O2,K2,M2,Q2,W2,Y2,AA2,AC2) -> 11690.04 | D2: DIFF: | E2: =E3-E142 -> 29724.14 | F2: DIFF: | G2: =G3-G142 -> 1271.16 | H2: DIFF: | I2: =I3-I142 -> 1533.36 | J2: DIFF: | K2: =K3-K142 -> 721 | L2: DIFF: | M2: =M3-M142 -> -35.79 | N2: DIFF: | O2: =O3-O142 -> -35.79 | P2: DIFF: | Q2: =Q3-Q142 -> 30.72 | R2: DIFF: | S2: =S3-S142 -> -3041.09 | T2: DIFF: | U2: =U3-U142 -> -19295.11 | V2: DIFF: | W2: =W3-W142 -> 900 | X2: DIFF: | Y2: =Y3-Y142 -> 264.5 | Z2: DIFF: | AA2: =AA3-AA142 -> -377.78 | AB2: DIFF: | AC2: =AC3-AC142 -> 30.72
A3: =SUM(G3,E3,U3,I3,S3,O3,K3,M3,Q3,W3,Y3,AA3,AC3) -> 23930.53 | D3: BAL: | E3: =SUM(E6:E142)-SUM(D6:D142) -> 31434.63 | F3: BAL: | G3: =SUM(G6:G142)-SUM(F6:F142) -> 1771.16 | H3: BAL: | I3: =SUM(I6:I142)-SUM(H6:H142) -> 3533.36 | J3: BAL: | K3: =SUM(K6:K142)-SUM(J6:J142) -> 1721 | L3: BAL: | M3: =SUM(M6:M142)-SUM(L6:L142) -> 29.21 | N3: BAL: | O3: =SUM(O6:O142)-SUM(N6:N142) -> 29.21 | P3: BAL: | Q3: =SUM(Q6:Q142)-SUM(P6:P142) -> 130.72 | R3: BAL: | S3: =SUM(S6:S142)-SUM(R6:R142) -> -1041.09 | T3: BAL: | U3: =SUM(U6:U142)-SUM(T6:T142) -> -16795.11 | V3: BAL: | W3: =SUM(W6:W142)-SUM(V6:V142) -> 1400 | X3: BAL: | Y3: =SUM(Y6:Y142)-SUM(X6:X142) -> 464.5 | Z3: BAL: | AA3: =SUM(AA6:AA142)-SUM(Z6:Z142) -> 1122.22 | AB3: BAL: | AC3: =SUM(AC6:AC142)-SUM(AB6:AB142) -> 130.72
A4: SPENT | D4: Amount | F4: Amount | H4: Amount | J4: Amount | L4: Amount | N4: Amount | P4: Amount | R4: Amount ($25) Per Week | T4: Interest ($625) | V4: Amount | X4: Amount | Z4: Amount | AB4: Amount
A5: SAVED | D5: =SUM(D6:D141) -> 21300.18 | E5: =SUM(E6:E141) -> 51024.32 | F5: =SUM(F6:F141) -> 69.69 | G5: =SUM(G6:G141) -> 1340.85 | H5: =SUM(H6:H141) -> 1616.64 | I5: =SUM(I6:I141) -> 3150 | J5: =SUM(J6:J141) -> 2159 | K5: =SUM(K6:K141) -> 2880 | ... AC5: =SUM(AC6:AC141) -> 405
A6: DATE | B6: TOTAL | C6: DESCRIPTION | D6: DEBIT | E6: CREDIT | F6: DEBIT | G6: CREDIT | H6: DEBIT | I6: CREDIT | J6: DEBIT | K6: CREDIT | L6: DEBIT | M6: CREDIT | N6: DEBIT | O6: CREDIT | P6: DEBIT | Q6: CREDIT | R6: DEBIT | S6: CREDIT | T6: DEBIT | U6: CREDIT | V6: DEBIT | W6: CREDIT | X6: DEBIT | Y6: CREDIT | Z6: DEBIT | AA6: CREDIT | AB6: DEBIT | AC6: CREDIT
A7: 46323 | B7: =SUM(E7,U7,K7,G7,I7,S7,O7,M7,Q7,W7,Y7,AA7,AC7)-SUM(D7,F7,T7,H7,R7,N7,J7,L7,P7,V7,X7,Z7,AB7) -> -69.69 | C7: Xmas Gifts | F7: 69.69
A8: 46323 | B8: =SUM(E8,U8,K8,G8,I8,S8,O8,M8,Q8,W8,Y8,AA8,AC8)-SUM(D8,F8,T8,H8,R8,N8,J8,L8,P8,V8,X8,Z8,AB8) -> 1705 | C8: Federal Tax Return | E8: 1705
A9: 46321 | B9: =SUM(E9,U9,K9,G9,I9,S9,O9,M9,Q9,W9,Y9,AA9,AC9)-SUM(D9,F9,T9,H9,R9,N9,J9,L9,P9,V9,X9,Z9,AB9) -> 781 | C9: Ohio Tax Return | E9: 781
A10: 46321 | B10: =SUM(E10,U10,K10,G10,I10,S10,O10,M10,Q10,W10,Y10,AA10,AC10)-SUM(D10,F10,T10,H10,R10,N10,J10,L10,P10,V10,X10,Z10,AB10) -> -134.52 | C10: Rumpke Waste | L10: 67.26 | N10: 67.26
A11: 46314 | B11: =SUM(E11,U11,K11,G11,I11,S11,O11,M11,Q11,W11,Y11,AA11,AC11)-SUM(D11,F11,T11,H11,R11,N11,J11,L11,P11,V11,X11,Z11,AB11) -> 54.24 | C11: Lorri CC Rewards | G11: 54.24
A12: 46304 | B12: =SUM(E12,U12,K12,G12,I12,S12,O12,M12,Q12,W12,Y12,AA12,AC12)-SUM(D12,F12,T12,H12,R12,N12,J12,L12,P12,V12,X12,Z12,AB12) -> -959.8 | C12: Lowes Rewards CC - Kitchen | T12: 959.8
A13: 46304 | B13: =SUM(E13,U13,K13,G13,I13,S13,O13,M13,Q13,W13,Y13,AA13,AC13)-SUM(D13,F13,T13,H13,R13,N13,J13,L13,P13,V13,X13,Z13,AB13) -> 1000 | C13: Golf Cart - Austin | E13: 1000
A14: 46304 | B14: =SUM(E14,U14,K14,G14,I14,S14,O14,M14,Q14,W14,Y14,AA14,AC14)-SUM(D14,F14,T14,H14,R14,N14,J14,L14,P14,V14,X14,Z14,AB14) -> -80.89 | C14: Pool Maintenance - Chemicals | D14: 80.89
A15: 46303 | B15: =SUM(E15,U15,K15,G15,I15,S15,O15,M15,Q15,W15,Y15,AA15,AC15)-SUM(D15,F15,T15,H15,R15,N15,J15,L15,P15,V15,X15,Z15,AB15) -> -960 | C15: Lowes Rewards CC - Kitchen | T15: 960
A16: 46300 | B16: =SUM(E16,U16,K16,G16,I16,S16,O16,M16,Q16,W16,Y16,AA16,AC16)-SUM(D16,F16,T16,H16,R16,N16,J16,L16,P16,V16,X16,Z16,AB16) -> 292 | C16: Hollywood Casino | D16: 1508 | E16: 1800
A17: 46297 | B17: =SUM(E17,U17,K17,G17,I17,S17,O17,M17,Q17,W17,Y17,AA17,AC17)-SUM(D17,F17,T17,H17,R17,N17,J17,L17,P17,V17,X17,Z17,AB17) -> -112.25 | C17: Hilton Grand Vacations | R17: 112.25
A18: 46295 | B18: =SUM(E18,U18,K18,G18,I18,S18,O18,M18,Q18,W18,Y18,AA18,AC18)-SUM(D18,F18,T18,H18,R18,N18,J18,L18,P18,V18,X18,Z18,AB18) -> 2768.7 | C18: September Savings | E18: 2768.7
A19: 46295 | B19: =SUM(E19,U19,K19,G19,I19,S19,O19,M19,Q19,W19,Y19,AA19,AC19)-SUM(D19,F19,T19,H19,R19,N19,J19,L19,P19,V19,X19,Z19,AB19) -> 2000 | C19: September Transfer | I19: 350 | K19: 320 | M19: 25 | O19: 25 | Q19: 45 | S19: 400 | U19: 375 | W19: 100 | Y19: 85 | AA19: 230 | AC19: 45
A20: 46295 | B20: =SUM(E20,U20,K20,G20,I20,S20,O20,M20,Q20,W20,Y20,AA20,AC20)-SUM(D20,F20,T20,H20,R20,N20,J20,L20,P20,V20,X20,Z20,AB20) -> 0.6 | C20: Interest Payment | G20: 0.6
A21: 46295 | B21: =SUM(E21,U21,K21,G21,I21,S21,O21,M21,Q21,W21,Y21,AA21,AC21)-SUM(D21,F21,T21,H21,R21,N21,J21,L21,P21,V21,X21,Z21,AB21) -> 60.95 | C21: Isaac CC Rewards | G21: 60.95
A22: 46279 | B22: =SUM(E22,U22,K22,G22,I22,S22,O22,M22,Q22,W22,Y22,AA22,AC22)-SUM(D22,F22,T22,H22,R22,N22,J22,L22,P22,V22,X22,Z22,AB22) -> -1360 | C22: Pool Gas Line | T22: 1360
A23: 46273 | B23: =SUM(E23,U23,K23,G23,I23,S23,O23,M23,Q23,W23,Y23,AA23,AC23)-SUM(D23,F23,T23,H23,R23,N23,J23,L23,P23,V23,X23,Z23,AB23) -> -960 | C23: Lowes Rewards CC - Kitchen | T23: 960
A24: 46272 | B24: =SUM(E24,U24,K24,G24,I24,S24,O24,M24,Q24,W24,Y24,AA24,AC24)-SUM(D24,F24,T24,H24,R24,N24,J24,L24,P24,V24,X24,Z24,AB24) -> -600 | C24: Casino | D24: 600
A25: 46265 | B25: =SUM(E25,U25,K25,G25,I25,S25,O25,M25,Q25,W25,Y25,AA25,AC25)-SUM(D25,F25,T25,H25,R25,N25,J25,L25,P25,V25,X25,Z25,AB25) -> 6794.38 | C25: August Savings | E25: 6794.38
A26: 46265 | B26: =SUM(E26,U26,K26,G26,I26,S26,O26,M26,Q26,W26,Y26,AA26,AC26)-SUM(D26,F26,T26,H26,R26,N26,J26,L26,P26,V26,X26,Z26,AB26) -> 2000 | C26: August Transfer | I26: 350 | K26: 320 | M26: 25 | O26: 25 | Q26: 45 | S26: 400 | U26: 375 | W26: 100 | Y26: 85 | AA26: 230 | AC26: 45
A27: 46265 | B27: =SUM(E27,U27,K27,G27,I27,S27,O27,M27,Q27,W27,Y27,AA27,AC27)-SUM(D27,F27,T27,H27,R27,N27,J27,L27,P27,V27,X27,Z27,AB27) -> 53.41 | C27: Lorri CC Rewards | G27: 53.41
A28: 46265 | B28: =SUM(E28,U28,K28,G28,I28,S28,O28,M28,Q28,W28,Y28,AA28,AC28)-SUM(D28,F28,T28,H28,R28,N28,J28,L28,P28,V28,X28,Z28,AB28) -> 0.41 | C28: Interest Payment | G28: 0.41
A29: 46265 | B29: =SUM(E29,U29,K29,G29,I29,S29,O29,M29,Q29,W29,Y29,AA29,AC29)-SUM(D29,F29,T29,H29,R29,N29,J29,L29,P29,V29,X29,Z29,AB29) -> -191.64 | C29: Sanitation | P29: 95.82 | AB29: 95.82
A30: 46261 | B30: =SUM(E30,U30,K30,G30,I30,S30,O30,M30,Q30,W30,Y30,AA30,AC30)-SUM(D30,F30,T30,H30,R30,N30,J30,L30,P30,V30,X30,Z30,AB30) -> 99.61 | C30: Isaac CC Rewards | G30: 99.61
A31: 46253 | B31: =SUM(E31,U31,K31,G31,I31,S31,O31,M31,Q31,W31,Y31,AA31,AC31)-SUM(D31,F31,T31,H31,R31,N31,J31,L31,P31,V31,X31,Z31,AB31) -> -219.38 | C31: Pandys - Landscaping | T31: 219.38
A32: 46244 | B32: =SUM(E32,U32,K32,G32,I32,S32,O32,M32,Q32,W32,Y32,AA32,AC32)-SUM(D32,F32,T32,H32,R32,N32,J32,L32,P32,V32,X32,Z32,AB32) -> -960 | C32: Lowes Rewards CC - Kitchen | T32: 960
A33: 46243 | B33: =SUM(E33,U33,K33,G33,I33,S33,O33,M33,Q33,W33,Y33,AA33,AC33)-SUM(D33,F33,T33,H33,R33,N33,J33,L33,P33,V33,X33,Z33,AB33) -> -116.04 | C33: Pool Maintenance - Chemicals | D33: 116.04
A34: 46240 | B34: =SUM(E34,U34,K34,G34,I34,S34,O34,M34,Q34,W34,Y34,AA34,AC34)-SUM(D34,F34,T34,H34,R34,N34,J34,L34,P34,V34,X34,Z34,AB34) -> 52.8 | C34: Isaac CC Rewards | G34: 52.8
A35: 46238 | B35: =SUM(E35,U35,K35,G35,I35,S35,O35,M35,Q35,W35,Y35,AA35,AC35)-SUM(D35,F35,T35,H35,R35,N35,J35,L35,P35,V35,X35,Z35,AB35) -> -500 | C35: Transfer to Kraken | D35: 500
A36: 46238 | B36: =SUM(E36,U36,K36,G36,I36,S36,O36,M36,Q36,W36,Y36,AA36,AC36)-SUM(D36,F36,T36,H36,R36,N36,J36,L36,P36,V36,X36,Z36,AB36) -> -500 | C36: Transfer to M1 | D36: 500
A37: 46238 | B37: =SUM(E37,U37,K37,G37,I37,S37,O37,M37,Q37,W37,Y37,AA37,AC37)-SUM(D37,F37,T37,H37,R37,N37,J37,L37,P37,V37,X37,Z37,AB37) -> -121.4 | C37: Toyota Rav4 Oil Change | H37: 121.4
A38: 46234 | B38: =SUM(E38,U38,K38,G38,I38,S38,O38,M38,Q38,W38,Y38,AA38,AC38)-SUM(D38,F38,T38,H38,R38,N38,J38,L38,P38,V38,X38,Z38,AB38) -> 8746.27 | C38: July Savings | E38: 8746.27
A39: 46234 | B39: =SUM(E39,U39,K39,G39,I39,S39,O39,M39,Q39,W39,Y39,AA39,AC39)-SUM(D39,F39,T39,H39,R39,N39,J39,L39,P39,V39,X39,Z39,AB39) -> 2000 | C39: July Transfer | I39: 350 | K39: 320 | M39: 25 | O39: 25 | Q39: 45 | S39: 400 | U39: 375 | W39: 100 | Y39: 85 | AA39: 230 | AC39: 45
A40: 46234 | B40: =SUM(E40,U40,K40,G40,I40,S40,O40,M40,Q40,W40,Y40,AA40,AC40)-SUM(D40,F40,T40,H40,R40,N40,J40,L40,P40,V40,X40,Z40,AB40) -> 0.22 | C40: Interest Payment | G40: 0.22
A41: 46232 | B41: =SUM(E41,U41,K41,G41,I41,S41,O41,M41,Q41,W41,Y41,AA41,AC41)-SUM(D41,F41,T41,H41,R41,N41,J41,L41,P41,V41,X41,Z41,AB41) -> 52.7 | C41: Lorri CC Rewards | G41: 52.7
A42: 46231 | B42: =SUM(E42,U42,K42,G42,I42,S42,O42,M42,Q42,W42,Y42,AA42,AC42)-SUM(D42,F42,T42,H42,R42,N42,J42,L42,P42,V42,X42,Z42,AB42) -> -1171.38 | C42: Property Taxes | Z42: 1171.38
A43: 46226 | B43: =SUM(E43,U43,K43,G43,I43,S43,O43,M43,Q43,W43,Y43,AA43,AC43)-SUM(D43,F43,T43,H43,R43,N43,J43,L43,P43,V43,X43,Z43,AB43) -> -133.14 | C43: Rumpke Waste | L43: 66.57 | N43: 66.57
